; source chunk: nasutoceratops.lua.bin

; function [0] definition (level 1) 0
; 1 upvalues, 0 params, is_vararg = 1, 24 stacks
.function  1 0 1 24
.upvalue  ""  1  0  ; 0  instack=1  idx=0
.const  "setmetatable"  ; 0
.const  "__index"  ; 1
.const  "_G"  ; 2
.const  "module"  ; 3
.const  "require"  ; 4
.const  "Vector2"  ; 5
.const  "Vector3"  ; 6
.const  "Root"  ; 7
.const  "Prefab"  ; 8
.const  "DinosaurBase"  ; 9
.const  "Properties"  ; 10
.const  "AssetPackages"  ; 11
.const  "Default"  ; 12
.const  "Nasutoceratops"  ; 13
.const  "__inheritance"  ; 14
.const  "Append"  ; 15
.const  "MaterialCollectionName"  ; 16
.const  "ModelName"  ; 17
.const  "MotionGraphName"  ; 18
.const  "Components"  ; 19
.const  "DinosaurCamera"  ; 20
.const  "FocusRadius"  ; 21
.const  4.0  ; 22
.const  "HatcheryExit"  ; 23
.const  "FocusYOffset"  ; 24
.const  0.1  ; 25
.const  "PivotDistanceMultiplier"  ; 26
.const  1.2  ; 27
.const  "Radius"  ; 28
.const  2.3  ; 29
.const  "FlowDiscomfort"  ; 30
.const  "DiscomfortRadius"  ; 31
.const  6.0  ; 32
.const  "DiscomfortValue"  ; 33
.const  20.0  ; 34
.const  "IKFootPlant"  ; 35
.const  "FootEffectSize"  ; 36
.const  "Medium"  ; 37
.const  "PlantSpecs"  ; 38
.const  "BoneChainDepth"  ; 39
.const  4  ; 40
.const  "BoneName"  ; 41
.const  "def_l_frontFoot_joint"  ; 42
.const  "def_r_frontFoot_joint"  ; 43
.const  "def_l_rearFoot_joint"  ; 44
.const  "def_r_rearFoot_joint"  ; 45
.const  "ZRotationLimit"  ; 46
.const  45.0  ; 47
.const  "IKHeadLook"  ; 48
.const  "BoneChain"  ; 49
.const  3  ; 50
.const  "def_c_head_joint"  ; 51
.const  "HeadTranslationEllipsoid"  ; 52
.const  "Ellipsoid"  ; 53
.const  "RadiusD"  ; 54
.const  0.901  ; 55
.const  "RadiusFB"  ; 56
.const  0.8  ; 57
.const  "RadiusLR"  ; 58
.const  1.073  ; 59
.const  "RadiusU"  ; 60
.const  "HeadDynamics"  ; 61
.const  "Constraints"  ; 62
.const  "ComfortPitchDown"  ; 63
.const  30.0  ; 64
.const  "ComfortPitchUp"  ; 65
.const  40.0  ; 66
.const  "ComfortYaw"  ; 67
.const  21.0  ; 68
.const  "StrainPitchDown"  ; 69
.const  25.0  ; 70
.const  "StrainPitchUp"  ; 71
.const  31.0  ; 72
.const  "StrainYaw"  ; 73
.const  42.0  ; 74
.const  "TorsionSpring"  ; 75
.const  "Damping"  ; 76
.const  55.0  ; 77
.const  "MaxStrength"  ; 78
.const  100.0  ; 79
.const  "MinStrength"  ; 80
.const  "NeckDynamics"  ; 81
.const  18.0  ; 82
.const  86.0  ; 83
.const  "PivotOffset"  ; 84
.const  "IKSolver"  ; 86
.const  "WarmFactor"  ; 87
.const  0.3  ; 88
.const  "Model"  ; 89
.const  "BoundingScaler"  ; 90
.const  1.85  ; 91
.const  "MotionGraphLocomotion"  ; 92
.const  "CurveExpansion"  ; 93
.const  2.0  ; 94
.const  "RotationSpringConstant"  ; 95
.const  10.0  ; 96
.const  "PhysicsCapsuleShape"  ; 97
.const  "Length"  ; 98
.const  1.65  ; 99
.const  "PhysicsRigidBody"  ; 100
.const  "ShapeOffset"  ; 101
.const  "SpatialSphere"  ; 103
.const  2.5  ; 104
.const  "Winchable"  ; 105
.const  "StrapsEntity"  ; 106
.const  "./Straps"  ; 107
.const  "Children"  ; 108
.const  "AudioCore"  ; 109
.const  "AudioDinosaurCore"  ; 110
.const  "Family"  ; 111
.const  "Cerapod"  ; 112
.const  "Name"  ; 113
.const  "RootEntity"  ; 114
.const  ".."  ; 115
.const  "FrontFeet"  ; 116
.const  "LeftFootBoneName"  ; 117
.const  "RightFootBoneName"  ; 118
.const  "BoneTransform"  ; 119
.const  "AnimEntity"  ; 120
.const  "Transform"  ; 121
.const  "AudioDinosaurRagdoll"  ; 122
.const  "CaptureRadius"  ; 123
.const  1.5  ; 124
.const  "AudioHead"  ; 125
.const  "AudioDinosaurDetail"  ; 126
.const  "Core"  ; 127
.const  "../../AudioCore"  ; 128
.const  "DataStreamEntity"  ; 129
.const  "../.."  ; 130
.const  "Type"  ; 131
.const  "Head"  ; 132
.const  "Rotation"  ; 133
.const  "HeadlookTargetPicker"  ; 135
.const  "HeadlookTargetPickerDefender"  ; 136
.const  "VFX_Fence_Impact"  ; 137
.const  "ParticleSelector"  ; 138
.const  "Parent"  ; 139
.const  "ParticleTrigger"  ; 140
.const  "Position"  ; 141
.const  "Scale"  ; 143
.const  1.0  ; 144
.const  "def_c_spine01_joint"  ; 145
.const  "def_c_tail05_joint"  ; 146
.const  "Tail"  ; 147
.const  "AudioTail"  ; 148
.const  "def_l_frontLeglwr_joint"  ; 149
.const  "VFX_Fall_Impact"  ; 150
.const  "AssetPackageProvider"  ; 151
.const  "LoaderPath"  ; 152
.const  "Particle"  ; 153
.const  "ParticleName"  ; 154
.const  "NERO_DF_Triceratops_Fall_Impact"  ; 155
.const  "def_l_frontLegupr_joint"  ; 156
.const  "VFX_Fall_Impact_02"  ; 157
.const  "StatusIcon"  ; 158
.const  "Straps"  ; 160
.const  "DinosaurStraps"  ; 161
.const  "Nasutoceratops_AirliftStraps"  ; 162
.const  "AssetPackageLoader"  ; 163
.const  "PackageNames"  ; 164
.const  "WinchAttachPoints"  ; 165
.const  "Neck"  ; 166
.const  "RopeAttachPoint"  ; 167
.const  "def_c_neck01_joint"  ; 168
.const  "def_c_tail01_joint"  ; 170
.const  "FlattenedRoot"  ; 172
.const  "AudioDinosaurBody"  ; 173
.const  "ComponentSources"  ; 174
.const  "AudioBoundingVolume"  ; 175
.const  "AudioDoppler"  ; 176
.const  "AudioPosition"  ; 177
.const  "BoundingVolumeBroadphase"  ; 178
.const  "Velocity"  ; 179
.const  "AudioDataStream"  ; 180
.const  "__property"  ; 181
.const  "IncompleteComponents"  ; 182
.const  "entity"  ; 183
.const  "Body"  ; 184
.const  "Enum"  ; 185
.const  "AudioDinosaurType"  ; 186
.const  "uint8"  ; 187
.const  "AudioDinosaurFootplant"  ; 188
.const  "UseTransform"  ; 189
.const  false  ; 190
.const  "Optional"  ; 191
.const  true  ; 192
.const  "Footplant"  ; 193
.const  "AudioWithinListenerRange"  ; 194
.const  "FamilySize"  ; 195
.const  "FootplantType"  ; 196
.const  "AudioDinosaurFamily"  ; 197
.const  "AudioDinosaurFamilySize"  ; 198
.const  "AudioDinosaurFootplantType"  ; 199
.const  "string"  ; 200
.const  "HeadLookReactionBite"  ; 201
.const  "NearbyBuildingBlocker"  ; 202
.const  "SpatialCapsule"  ; 203
.const  3.0  ; 204
.const  7.0  ; 205
.const  "SpatialGroups"  ; 206
.const  "dinosaur_nearby"  ; 207
.const  "SpatialDatabase"  ; 208
.const  "ObjectiveMarker"  ; 209
.const  "DinosaurObjectiveMarker"  ; 210
.const  "Dinosaur"  ; 211
.const  "Icon"  ; 212
.const  "None"  ; 213
.const  "DinosaurStatusIcon"  ; 215
.const  "DinosaurBase/StatusIcon"  ; 216
.const  "IgnoreParentRotation"  ; 217
.const  "AnimationProxy"  ; 218
.const  "AnimationEntity"  ; 219
.const  "AnimationType"  ; 220
.const  "FGDK Animation"  ; 221
.const  "ManualPackageNames"  ; 222
.const  "DinosaurCommon"  ; 223
.const  "."  ; 224
.const  "UIGroup"  ; 225
.const  "Visuals"  ; 226
.const  "LowerBack"  ; 227
.const  "PhysicsEntity"  ; 228
.const  "PhysicsEntityIsDrivenSkeleton"  ; 229
.const  "UpperBack"  ; 233
.const  "DinosaurBase/WinchAttachPoints"  ; 235
.const  "AudioEmitter"  ; 236
.const  "WeightType"  ; 237
.const  "float"  ; 238
.const  "BodyFront"  ; 239
.const  "AudioDinosaurRagdollType"  ; 240
.const  "AudioDinosaurRagdollWeight"  ; 241
.const  "HeadlookTarget"  ; 243
.const  "HeadLookTarget"  ; 244
.const  "RootEntityID"  ; 245
.const  "SpatialEntityID"  ; 246
.const  "TargetType"  ; 247
.const  "DinosaurHeadLookTargetPicker"  ; 248
.const  "AttentionSettings"  ; 249
.const  "MaxLookAtDistance"  ; 250
.const  150.0  ; 251
.const  "MaxTime"  ; 252
.const  "MinTime"  ; 253
.const  8.0  ; 254
.const  "IdleLooking"  ; 255
.const  "IdleChance"  ; 256
.const  0.5  ; 257
.const  5.0  ; 258
.const  "OldTargetsScorePenalty"  ; 259
.const  0.4  ; 260
.const  0.2  ; 261
.const  "TargetPicking"  ; 262
.const  "CrowdLookAtTargetSetting"  ; 263
.const  "ScorePerPerson"  ; 264
.const  "SpatialQueryFlags"  ; 265
.const  "path"  ; 266
.const  "DinosaurLookAtTargetSetting"  ; 267
.const  "dinosaur"  ; 268
.const  "FlareLookAtTargetSetting"  ; 269
.const  "flare"  ; 270
.const  "ScoreMinimum"  ; 271
.const  "tree"  ; 272
.const  "buildingmodule"  ; 273
.const  "powercable"  ; 274
.const  "dinosaurgoalpoint_food_meat"  ; 275
.const  "dinosaurgoalpoint_food_lowherb"  ; 276
.const  "dinosaurgoalpoint_food_highherb"  ; 277
.const  "power_transmittor"  ; 278
.const  "gate_open"  ; 279
.const  "SpatialQuerySphereRadius"  ; 280
.const  "VehiclesLookAtTargetSetting"  ; 281
.const  "vehicle"  ; 282
.const  "InterestingEventSpawner"  ; 283
.const  "CrowdInterestingEventSpawner"  ; 284
.const  "InterestingEventSettings"  ; 285
.const  "SourceBoundRadius"  ; 286
.const  "PhysicsRaycastFlagName"  ; 287
.const  "Flag"  ; 288
.const  "Landscape"  ; 289
.const  "Foliage"  ; 290
.const  "Building"  ; 291
.const  "Wall"  ; 292
.const  "Pylon"  ; 293
.const  "Track"  ; 294
.const  "QueryInterval"  ; 295
.const  "TriggerRadius"  ; 296
.const  "TriggerSpatialFlag"  ; 297
.const  "DinosaurBase/def_c_head_joint"  ; 298
.const  "def_c_root_joint"  ; 299
.const  "AmenityProvider"  ; 300
.const  "Animation"  ; 301
.const  "AssetPackageStream"  ; 302
.const  "BehaviourTreeAgent"  ; 303
.const  "Coordination"  ; 304
.const  "CrowdPhysicsCollider"  ; 305
.const  "DinosaurAmenities"  ; 306
.const  "DinosaurBehaviourTag"  ; 307
.const  "DinosaurHeadLookReaction"  ; 308
.const  "DinosaurMaterialDecay"  ; 309
.const  "DinosaurMovementTarget"  ; 310
.const  "DinosaurStatistics"  ; 311
.const  "DinosaurThreat"  ; 312
.const  "DinosaurTreeAgent"  ; 313
.const  "DinosaurUIContext"  ; 314
.const  "FlowDirection"  ; 315
.const  "FlowMotion"  ; 316
.const  "FlowParticle"  ; 317
.const  "FlowPath"  ; 318
.const  "FlowStreamPath"  ; 319
.const  "FlowTargetReservation"  ; 320
.const  "FlowTheatre"  ; 321
.const  "GuestThreatMap"  ; 322
.const  "HerdMembership"  ; 323
.const  "LevelOfDetail"  ; 324
.const  "Locomotion"  ; 325
.const  "MapIcon"  ; 326
.const  "MotionApplication"  ; 327
.const  "PhysicsProxy"  ; 328
.const  "PhysicsRagdollImpact"  ; 329
.const  "RenderBoundingVolume"  ; 330
.const  "SkeletonDebug"  ; 331
.const  "TheatreActor"  ; 332
.const  "ViewFilter"  ; 333
.const  "ViewpointTarget"  ; 334
.const  "HierName"  ; 335
.const  "DinosaurBaseMotionGraph"  ; 336
.const  "RequestType"  ; 337
.const  "LocationVolume"  ; 338
.const  "BehaviourTreeProvider"  ; 339
.const  "BehaviourTree"  ; 340
.const  "AlternateFocusBone"  ; 341
.const  "FocusBone"  ; 342
.const  "DinosaurDiseaseSource"  ; 343
.const  "InfectAmount"  ; 344
.const  "InfectTimer"  ; 345
.const  "InfectRadius"  ; 346
.const  "DinosaurGenome"  ; 347
.const  "AttackModification"  ; 348
.const  "CosmeticGenes"  ; 349
.const  "CostMultiplier"  ; 350
.const  "DefenceModification"  ; 351
.const  "ForestMultiplierModification"  ; 352
.const  "GeneTypePriorities"  ; 353
.const  "GeneTypes"  ; 354
.const  "GrasslandMultiplierModification"  ; 355
.const  "LifespanModification"  ; 356
.const  "MaxOvercrowdingAdjustmentModification"  ; 357
.const  "MaxSocialAdjustmentModification"  ; 358
.const  "MinOvercrowdingAdjustmentModification"  ; 359
.const  "MinSocialAdjustmentModification"  ; 360
.const  "NumModifiedGenes"  ; 361
.const  "NumUnmodifiedGenes"  ; 362
.const  "Percentage"  ; 363
.const  "GenomePercentage"  ; 364
.const  "PrestigeBonusModification"  ; 365
.const  "ResilienceModification"  ; 366
.const  "StressThresholdAdjustmentModification"  ; 367
.const  "DinosaurLifecycle"  ; 368
.const  "EffectiveAge"  ; 369
.const  "RealAge"  ; 370
.const  "SpawnFromHatcheryWithCutscene"  ; 371
.const  "SpawnUnconscious"  ; 372
.const  "StartUnconscious"  ; 373
.const  "SpawnedFromHatchery"  ; 374
.const  "Food_Tranquillised"  ; 375
.const  "DinosaurSimulation"  ; 376
.const  "DinosaurSpecies"  ; 377
.const  "IsDead"  ; 378
.const  "Species"  ; 379
.const  "ThreatCategory"  ; 380
.const  "ApplyDiscomfort"  ; 381
.const  "DiscomfortGradient"  ; 382
.const  "ObstructionType"  ; 383
.const  "MediumDino"  ; 384
.const  "Active"  ; 385
.const  "DensityMultiplier"  ; 386
.const  "FillDistance"  ; 387
.const  90.0  ; 388
.const  "MinDistance"  ; 389
.const  50.0  ; 390
.const  "GlobalBlendWeightStreams"  ; 391
.const  "IsInverseRelated"  ; 392
.const  "StreamName"  ; 393
.const  "SleepBlendOff"  ; 394
.const  "StreamType"  ; 395
.const  "Sleep"  ; 396
.const  "ConeEase"  ; 397
.const  "SafeZoneRadius"  ; 398
.const  ""  ; 399
.const  "IconClass"  ; 400
.const  "DinosaurIcon"  ; 401
.const  "MaterialCollection"  ; 402
.const  "ForceOnAllLODs"  ; 403
.const  "MaterialCollectionResource"  ; 404
.const  "MaterialCollectionVariantsName"  ; 405
.const  "ModelSkeleton"  ; 406
.const  "MotionGraph"  ; 407
.const  "HookNodeName"  ; 408
.const  "MotionGraphHook"  ; 409
.const  "ADLPlannerConfigName"  ; 410
.const  "Nero"  ; 411
.const  "DefaultMinCycles"  ; 412
.const  2  ; 413
.const  "ForwardErrorTol"  ; 414
.const  "ForwardSpringConstant"  ; 415
.const  "ForwardSpringDamping"  ; 416
.const  "LateralErrorTol"  ; 417
.const  "LateralSpringConstant"  ; 418
.const  "LateralSpringDamping"  ; 419
.const  "PlaybackRateSpringConstant"  ; 420
.const  "PlaybackRateSpringDamping"  ; 421
.const  "RadiusReduction"  ; 422
.const  "RotationSpringDamping"  ; 423
.const  "SetTransformWhenStopped"  ; 424
.const  "PhysicsDrivenSkeleton"  ; 425
.const  "CollisionEnabled"  ; 426
.const  "PhysicsWorldEntity"  ; 427
.const  "/MainPhysicsWorld"  ; 428
.const  "SpatialEnabled"  ; 429
.const  "Synchronised"  ; 430
.const  "MinCollisionLOD"  ; 431
.const  1  ; 432
.const  "MinSpatialLOD"  ; 433
.const  "ClassificationName"  ; 434
.const  "DinosaurCollisionProxy"  ; 435
.const  "PhysicsShapeEntity"  ; 436
.const  "PhysicsShapeType"  ; 437
.const  "Capsule"  ; 438
.const  "StartKinematicallyDriven"  ; 439
.const  "SurfaceName"  ; 440
.const  "DinosaurLimb"  ; 441
.const  "EnableDebugRender"  ; 442
.const  "UIEntityName"  ; 443
.const  "InitialNameFormat"  ; 444
.const  "%s-%03i"  ; 445
.const  "InitialNamePrefix"  ; 446
.const  "SaveName"  ; 447
.const  "EnvironmentMap"  ; 448
.const  "Perturbation"  ; 449
.const  "ShadowCascade4to7"  ; 450
.const  "AttachPoints"  ; 451
.const  "./WinchAttachPoints/Neck"  ; 452
.const  "./WinchAttachPoints/Tail"  ; 453
.const  "./WinchAttachPoints/UpperBack"  ; 454
.const  "./WinchAttachPoints/LowerBack"  ; 455
.const  "Contents"  ; 456
.const  "array"  ; 457
.const  0  ; 458
.const  "int32"  ; 459
.const  "Genetics"  ; 460
.const  "DinosaurBehaviours"  ; 461
.const  "Behaviours"  ; 462
.const  "uint32"  ; 463
.const  0.0  ; 464
.const  "Simulation"  ; 465
.const  15.0  ; 466
.const  "UI"  ; 467
.const  "bool"  ; 468
.const  nil  ; 469
.const  "GetRoot"  ; 470
.const  "GetFlattenedRoot"  ; 471
[0001] gettabup  0   0   256  ; R0 := U0[K0(="setmetatable")]
[0002] newtable  1   0   1    ; R1 := {} , array_size=0, hash_size=1
[0003] gettabup  2   0   258  ; R2 := U0[K2(="_G")]
[0004] settable  1   257 2    ; R1[K1(="__index")] := R2
[0005] gettabup  2   0   259  ; R2 := U0[K3(="module")]
[0006] vararg    3   0        ; R3 to top := ...
[0007] call      2   0   2    ; R2 := R2(R3 to top)
[0008] move      3   0        ; R3 := R0
[0009] move      4   2        ; R4 := R2
[0010] move      5   1        ; R5 := R1
[0011] call      3   3   1    ;  := R3(R4, R5)
[0012] gettabup  3   0   260  ; R3 := U0[K4(="require")]
[0013] loadk     4   5        ; R4 := K5(="Vector2")
[0014] call      3   2   2    ; R3 := R3(R4)
[0015] gettabup  4   0   260  ; R4 := U0[K4(="require")]
[0016] loadk     5   6        ; R5 := K6(="Vector3")
[0017] call      4   2   2    ; R4 := R4(R5)
[0018] newtable  5   0   4    ; R5 := {} , array_size=0, hash_size=4
[0019] settable  5   264 265  ; R5[K8(="Prefab")] := K9(="DinosaurBase")
[0020] newtable  6   0   4    ; R6 := {} , array_size=0, hash_size=4
[0021] newtable  7   0   1    ; R7 := {} , array_size=0, hash_size=1
[0022] newtable  8   1   1    ; R8 := {} , array_size=1, hash_size=1
[0023] loadk     9   13       ; R9 := K13(="Nasutoceratops")
[0024] settable  8   270 271  ; R8[K14(="__inheritance")] := K15(="Append")
[0025] setlist   8   1   1    ; R8[1 to 1] := R9 to R9
[0026] settable  7   268 8    ; R7[K12(="Default")] := R8
[0027] settable  6   267 7    ; R6[K11(="AssetPackages")] := R7
[0028] newtable  7   0   1    ; R7 := {} , array_size=0, hash_size=1
[0029] settable  7   268 269  ; R7[K12(="Default")] := K13(="Nasutoceratops")
[0030] settable  6   272 7    ; R6[K16(="MaterialCollectionName")] := R7
[0031] newtable  7   0   1    ; R7 := {} , array_size=0, hash_size=1
[0032] settable  7   268 269  ; R7[K12(="Default")] := K13(="Nasutoceratops")
[0033] settable  6   273 7    ; R6[K17(="ModelName")] := R7
[0034] newtable  7   0   1    ; R7 := {} , array_size=0, hash_size=1
[0035] settable  7   268 269  ; R7[K12(="Default")] := K13(="Nasutoceratops")
[0036] settable  6   274 7    ; R6[K18(="MotionGraphName")] := R7
[0037] settable  5   266 6    ; R5[K10(="Properties")] := R6
[0038] newtable  6   0   11   ; R6 := {} , array_size=0, hash_size=11
[0039] newtable  7   0   2    ; R7 := {} , array_size=0, hash_size=2
[0040] settable  7   277 278  ; R7[K21(="FocusRadius")] := K22(=4.0)
[0041] newtable  8   0   3    ; R8 := {} , array_size=0, hash_size=3
[0042] settable  8   280 281  ; R8[K24(="FocusYOffset")] := K25(=0.1)
[0043] settable  8   282 283  ; R8[K26(="PivotDistanceMultiplier")] := K27(=1.2)
[0044] settable  8   284 285  ; R8[K28(="Radius")] := K29(=2.3)
[0045] settable  7   279 8    ; R7[K23(="HatcheryExit")] := R8
[0046] settable  6   276 7    ; R6[K20(="DinosaurCamera")] := R7
[0047] newtable  7   0   2    ; R7 := {} , array_size=0, hash_size=2
[0048] settable  7   287 288  ; R7[K31(="DiscomfortRadius")] := K32(=6.0)
[0049] settable  7   289 290  ; R7[K33(="DiscomfortValue")] := K34(=20.0)
[0050] settable  6   286 7    ; R6[K30(="FlowDiscomfort")] := R7
[0051] newtable  7   0   3    ; R7 := {} , array_size=0, hash_size=3
[0052] settable  7   292 293  ; R7[K36(="FootEffectSize")] := K37(="Medium")
[0053] newtable  8   4   0    ; R8 := {} , array_size=4, hash_size=0
[0054] newtable  9   0   2    ; R9 := {} , array_size=0, hash_size=2
[0055] settable  9   295 296  ; R9[K39(="BoneChainDepth")] := K40(=4)
[0056] settable  9   297 298  ; R9[K41(="BoneName")] := K42(="def_l_frontFoot_joint")
[0057] newtable  10  0   2    ; R10 := {} , array_size=0, hash_size=2
[0058] settable  10  295 296  ; R10[K39(="BoneChainDepth")] := K40(=4)
[0059] settable  10  297 299  ; R10[K41(="BoneName")] := K43(="def_r_frontFoot_joint")
[0060] newtable  11  0   2    ; R11 := {} , array_size=0, hash_size=2
[0061] settable  11  295 296  ; R11[K39(="BoneChainDepth")] := K40(=4)
[0062] settable  11  297 300  ; R11[K41(="BoneName")] := K44(="def_l_rearFoot_joint")
[0063] newtable  12  0   2    ; R12 := {} , array_size=0, hash_size=2
[0064] settable  12  295 296  ; R12[K39(="BoneChainDepth")] := K40(=4)
[0065] settable  12  297 301  ; R12[K41(="BoneName")] := K45(="def_r_rearFoot_joint")
[0066] setlist   8   4   1    ; R8[1 to 4] := R9 to R12
[0067] settable  7   294 8    ; R7[K38(="PlantSpecs")] := R8
[0068] settable  7   302 303  ; R7[K46(="ZRotationLimit")] := K47(=45.0)
[0069] settable  6   291 7    ; R6[K35(="IKFootPlant")] := R7
[0070] newtable  7   0   2    ; R7 := {} , array_size=0, hash_size=2
[0071] newtable  8   0   2    ; R8 := {} , array_size=0, hash_size=2
[0072] settable  8   295 306  ; R8[K39(="BoneChainDepth")] := K50(=3)
[0073] settable  8   297 307  ; R8[K41(="BoneName")] := K51(="def_c_head_joint")
[0074] settable  7   305 8    ; R7[K49(="BoneChain")] := R8
[0075] newtable  8   0   4    ; R8 := {} , array_size=0, hash_size=4
[0076] newtable  9   0   4    ; R9 := {} , array_size=0, hash_size=4
[0077] settable  9   310 311  ; R9[K54(="RadiusD")] := K55(=0.901)
[0078] settable  9   312 313  ; R9[K56(="RadiusFB")] := K57(=0.8)
[0079] settable  9   314 315  ; R9[K58(="RadiusLR")] := K59(=1.073)
[0080] settable  9   316 311  ; R9[K60(="RadiusU")] := K55(=0.901)
[0081] settable  8   309 9    ; R8[K53(="Ellipsoid")] := R9
[0082] newtable  9   0   2    ; R9 := {} , array_size=0, hash_size=2
[0083] newtable  10  0   6    ; R10 := {} , array_size=0, hash_size=6
[0084] settable  10  319 320  ; R10[K63(="ComfortPitchDown")] := K64(=30.0)
[0085] settable  10  321 322  ; R10[K65(="ComfortPitchUp")] := K66(=40.0)
[0086] settable  10  323 324  ; R10[K67(="ComfortYaw")] := K68(=21.0)
[0087] settable  10  325 326  ; R10[K69(="StrainPitchDown")] := K70(=25.0)
[0088] settable  10  327 328  ; R10[K71(="StrainPitchUp")] := K72(=31.0)
[0089] settable  10  329 330  ; R10[K73(="StrainYaw")] := K74(=42.0)
[0090] settable  9   318 10   ; R9[K62(="Constraints")] := R10
[0091] newtable  10  0   3    ; R10 := {} , array_size=0, hash_size=3
[0092] settable  10  332 333  ; R10[K76(="Damping")] := K77(=55.0)
[0093] settable  10  334 335  ; R10[K78(="MaxStrength")] := K79(=100.0)
[0094] settable  10  336 322  ; R10[K80(="MinStrength")] := K66(=40.0)
[0095] settable  9   331 10   ; R9[K75(="TorsionSpring")] := R10
[0096] settable  8   317 9    ; R8[K61(="HeadDynamics")] := R9
[0097] newtable  9   0   2    ; R9 := {} , array_size=0, hash_size=2
[0098] newtable  10  0   6    ; R10 := {} , array_size=0, hash_size=6
[0099] settable  10  319 290  ; R10[K63(="ComfortPitchDown")] := K34(=20.0)
[0100] settable  10  321 326  ; R10[K65(="ComfortPitchUp")] := K70(=25.0)
[0101] settable  10  323 338  ; R10[K67(="ComfortYaw")] := K82(=18.0)
[0102] settable  10  325 326  ; R10[K69(="StrainPitchDown")] := K70(=25.0)
[0103] settable  10  327 320  ; R10[K71(="StrainPitchUp")] := K64(=30.0)
[0104] settable  10  329 338  ; R10[K73(="StrainYaw")] := K82(=18.0)
[0105] settable  9   318 10   ; R9[K62(="Constraints")] := R10
[0106] newtable  10  0   3    ; R10 := {} , array_size=0, hash_size=3
[0107] settable  10  332 333  ; R10[K76(="Damping")] := K77(=55.0)
[0108] settable  10  334 339  ; R10[K78(="MaxStrength")] := K83(=86.0)
[0109] settable  10  336 303  ; R10[K80(="MinStrength")] := K47(=45.0)
[0110] settable  9   331 10   ; R9[K75(="TorsionSpring")] := R10
[0111] settable  8   337 9    ; R8[K81(="NeckDynamics")] := R9
[0112] settable  8   340 341  ; R8[K84(="PivotOffset")] := K85(=nil)
[0113] settable  7   308 8    ; R7[K52(="HeadTranslationEllipsoid")] := R8
[0114] settable  6   304 7    ; R6[K48(="IKHeadLook")] := R7
[0115] newtable  7   0   1    ; R7 := {} , array_size=0, hash_size=1
[0116] settable  7   343 344  ; R7[K87(="WarmFactor")] := K88(=0.3)
[0117] settable  6   342 7    ; R6[K86(="IKSolver")] := R7
[0118] newtable  7   0   1    ; R7 := {} , array_size=0, hash_size=1
[0119] settable  7   346 347  ; R7[K90(="BoundingScaler")] := K91(=1.85)
[0120] settable  6   345 7    ; R6[K89(="Model")] := R7
[0121] newtable  7   0   2    ; R7 := {} , array_size=0, hash_size=2
[0122] settable  7   349 350  ; R7[K93(="CurveExpansion")] := K94(=2.0)
[0123] settable  7   351 352  ; R7[K95(="RotationSpringConstant")] := K96(=10.0)
[0124] settable  6   348 7    ; R6[K92(="MotionGraphLocomotion")] := R7
[0125] newtable  7   0   2    ; R7 := {} , array_size=0, hash_size=2
[0126] settable  7   354 350  ; R7[K98(="Length")] := K94(=2.0)
[0127] settable  7   284 355  ; R7[K28(="Radius")] := K99(=1.65)
[0128] settable  6   353 7    ; R6[K97(="PhysicsCapsuleShape")] := R7
[0129] newtable  7   0   1    ; R7 := {} , array_size=0, hash_size=1
[0130] settable  7   357 358  ; R7[K101(="ShapeOffset")] := K102(=nil)
[0131] settable  6   356 7    ; R6[K100(="PhysicsRigidBody")] := R7
[0132] newtable  7   0   1    ; R7 := {} , array_size=0, hash_size=1
[0133] settable  7   284 360  ; R7[K28(="Radius")] := K104(=2.5)
[0134] settable  6   359 7    ; R6[K103(="SpatialSphere")] := R7
[0135] newtable  7   0   1    ; R7 := {} , array_size=0, hash_size=1
[0136] settable  7   362 363  ; R7[K106(="StrapsEntity")] := K107(="./Straps")
[0137] settable  6   361 7    ; R6[K105(="Winchable")] := R7
[0138] settable  5   275 6    ; R5[K19(="Components")] := R6
[0139] newtable  6   0   9    ; R6 := {} , array_size=0, hash_size=9
[0140] newtable  7   0   3    ; R7 := {} , array_size=0, hash_size=3
[0141] settable  7   264 366  ; R7[K8(="Prefab")] := K110(="AudioDinosaurCore")
[0142] newtable  8   0   3    ; R8 := {} , array_size=0, hash_size=3
[0143] newtable  9   0   1    ; R9 := {} , array_size=0, hash_size=1
[0144] settable  9   268 368  ; R9[K12(="Default")] := K112(="Cerapod")
[0145] settable  8   367 9    ; R8[K111(="Family")] := R9
[0146] newtable  9   0   1    ; R9 := {} , array_size=0, hash_size=1
[0147] settable  9   268 269  ; R9[K12(="Default")] := K13(="Nasutoceratops")
[0148] settable  8   369 9    ; R8[K113(="Name")] := R9
[0149] newtable  9   0   1    ; R9 := {} , array_size=0, hash_size=1
[0150] settable  9   268 371  ; R9[K12(="Default")] := K115(="..")
[0151] settable  8   370 9    ; R8[K114(="RootEntity")] := R9
[0152] settable  7   266 8    ; R7[K10(="Properties")] := R8
[0153] newtable  8   0   1    ; R8 := {} , array_size=0, hash_size=1
[0154] newtable  9   0   1    ; R9 := {} , array_size=0, hash_size=1
[0155] newtable  10  0   2    ; R10 := {} , array_size=0, hash_size=2
[0156] settable  10  373 298  ; R10[K117(="LeftFootBoneName")] := K42(="def_l_frontFoot_joint")
[0157] settable  10  374 299  ; R10[K118(="RightFootBoneName")] := K43(="def_r_frontFoot_joint")
[0158] settable  9   372 10   ; R9[K116(="FrontFeet")] := R10
[0159] settable  8   366 9    ; R8[K110(="AudioDinosaurCore")] := R9
[0160] settable  7   275 8    ; R7[K19(="Components")] := R8
[0161] settable  6   365 7    ; R6[K109(="AudioCore")] := R7
[0162] newtable  7   0   2    ; R7 := {} , array_size=0, hash_size=2
[0163] newtable  8   0   2    ; R8 := {} , array_size=0, hash_size=2
[0164] newtable  9   0   2    ; R9 := {} , array_size=0, hash_size=2
[0165] settable  9   376 371  ; R9[K120(="AnimEntity")] := K115(="..")
[0166] settable  9   297 307  ; R9[K41(="BoneName")] := K51(="def_c_head_joint")
[0167] settable  8   375 9    ; R8[K119(="BoneTransform")] := R9
[0168] newtable  9   0   0    ; R9 := {} , array_size=0, hash_size=0
[0169] settable  8   377 9    ; R8[K121(="Transform")] := R9
[0170] settable  7   275 8    ; R7[K19(="Components")] := R8
[0171] newtable  8   0   4    ; R8 := {} , array_size=0, hash_size=4
[0172] newtable  9   0   3    ; R9 := {} , array_size=0, hash_size=3
[0173] settable  9   264 378  ; R9[K8(="Prefab")] := K122(="AudioDinosaurRagdoll")
[0174] newtable  10  0   1    ; R10 := {} , array_size=0, hash_size=1
[0175] newtable  11  0   1    ; R11 := {} , array_size=0, hash_size=1
[0176] settable  11  268 380  ; R11[K12(="Default")] := K124(=1.5)
[0177] settable  10  379 11   ; R10[K123(="CaptureRadius")] := R11
[0178] settable  9   266 10   ; R9[K10(="Properties")] := R10
[0179] newtable  10  0   1    ; R10 := {} , array_size=0, hash_size=1
[0180] newtable  11  0   0    ; R11 := {} , array_size=0, hash_size=0
[0181] settable  10  377 11   ; R10[K121(="Transform")] := R11
[0182] settable  9   275 10   ; R9[K19(="Components")] := R10
[0183] settable  8   378 9    ; R8[K122(="AudioDinosaurRagdoll")] := R9
[0184] newtable  9   0   3    ; R9 := {} , array_size=0, hash_size=3
[0185] settable  9   264 382  ; R9[K8(="Prefab")] := K126(="AudioDinosaurDetail")
[0186] newtable  10  0   3    ; R10 := {} , array_size=0, hash_size=3
[0187] newtable  11  0   1    ; R11 := {} , array_size=0, hash_size=1
[0188] settable  11  268 384  ; R11[K12(="Default")] := K128(="../../AudioCore")
[0189] settable  10  383 11   ; R10[K127(="Core")] := R11
[0190] newtable  11  0   1    ; R11 := {} , array_size=0, hash_size=1
[0191] settable  11  268 386  ; R11[K12(="Default")] := K130(="../..")
[0192] settable  10  385 11   ; R10[K129(="DataStreamEntity")] := R11
[0193] newtable  11  0   1    ; R11 := {} , array_size=0, hash_size=1
[0194] settable  11  268 388  ; R11[K12(="Default")] := K132(="Head")
[0195] settable  10  387 11   ; R10[K131(="Type")] := R11
[0196] settable  9   266 10   ; R9[K10(="Properties")] := R10
[0197] newtable  10  0   1    ; R10 := {} , array_size=0, hash_size=1
[0198] newtable  11  0   1    ; R11 := {} , array_size=0, hash_size=1
[0199] settable  11  389 390  ; R11[K133(="Rotation")] := K134(=nil)
[0200] settable  10  377 11   ; R10[K121(="Transform")] := R11
[0201] settable  9   275 10   ; R9[K19(="Components")] := R10
[0202] settable  8   381 9    ; R8[K125(="AudioHead")] := R9
[0203] newtable  9   0   1    ; R9 := {} , array_size=0, hash_size=1
[0204] settable  9   264 392  ; R9[K8(="Prefab")] := K136(="HeadlookTargetPickerDefender")
[0205] settable  8   391 9    ; R8[K135(="HeadlookTargetPicker")] := R9
[0206] newtable  9   0   1    ; R9 := {} , array_size=0, hash_size=1
[0207] newtable  10  0   3    ; R10 := {} , array_size=0, hash_size=3
[0208] newtable  11  0   1    ; R11 := {} , array_size=0, hash_size=1
[0209] settable  11  395 386  ; R11[K139(="Parent")] := K130(="../..")
[0210] settable  10  394 11   ; R10[K138(="ParticleSelector")] := R11
[0211] newtable  11  0   1    ; R11 := {} , array_size=0, hash_size=1
[0212] settable  11  385 386  ; R11[K129(="DataStreamEntity")] := K130(="../..")
[0213] settable  10  396 11   ; R10[K140(="ParticleTrigger")] := R11
[0214] newtable  11  0   3    ; R11 := {} , array_size=0, hash_size=3
[0215] settable  11  397 398  ; R11[K141(="Position")] := K142(=nil)
[0216] settable  11  389 398  ; R11[K133(="Rotation")] := K142(=nil)
[0217] settable  11  399 400  ; R11[K143(="Scale")] := K144(=1.0)
[0218] settable  10  377 11   ; R10[K121(="Transform")] := R11
[0219] settable  9   275 10   ; R9[K19(="Components")] := R10
[0220] settable  8   393 9    ; R8[K137(="VFX_Fence_Impact")] := R9
[0221] settable  7   364 8    ; R7[K108(="Children")] := R8
[0222] settable  6   307 7    ; R6[K51(="def_c_head_joint")] := R7
[0223] newtable  7   0   2    ; R7 := {} , array_size=0, hash_size=2
[0224] newtable  8   0   2    ; R8 := {} , array_size=0, hash_size=2
[0225] newtable  9   0   2    ; R9 := {} , array_size=0, hash_size=2
[0226] settable  9   376 371  ; R9[K120(="AnimEntity")] := K115(="..")
[0227] settable  9   297 401  ; R9[K41(="BoneName")] := K145(="def_c_spine01_joint")
[0228] settable  8   375 9    ; R8[K119(="BoneTransform")] := R9
[0229] newtable  9   0   0    ; R9 := {} , array_size=0, hash_size=0
[0230] settable  8   377 9    ; R8[K121(="Transform")] := R9
[0231] settable  7   275 8    ; R7[K19(="Components")] := R8
[0232] newtable  8   0   1    ; R8 := {} , array_size=0, hash_size=1
[0233] newtable  9   0   3    ; R9 := {} , array_size=0, hash_size=3
[0234] settable  9   264 378  ; R9[K8(="Prefab")] := K122(="AudioDinosaurRagdoll")
[0235] newtable  10  0   1    ; R10 := {} , array_size=0, hash_size=1
[0236] newtable  11  0   1    ; R11 := {} , array_size=0, hash_size=1
[0237] settable  11  268 360  ; R11[K12(="Default")] := K104(=2.5)
[0238] settable  10  379 11   ; R10[K123(="CaptureRadius")] := R11
[0239] settable  9   266 10   ; R9[K10(="Properties")] := R10
[0240] newtable  10  0   1    ; R10 := {} , array_size=0, hash_size=1
[0241] newtable  11  0   0    ; R11 := {} , array_size=0, hash_size=0
[0242] settable  10  377 11   ; R10[K121(="Transform")] := R11
[0243] settable  9   275 10   ; R9[K19(="Components")] := R10
[0244] settable  8   378 9    ; R8[K122(="AudioDinosaurRagdoll")] := R9
[0245] settable  7   364 8    ; R7[K108(="Children")] := R8
[0246] settable  6   401 7    ; R6[K145(="def_c_spine01_joint")] := R7
[0247] newtable  7   0   2    ; R7 := {} , array_size=0, hash_size=2
[0248] newtable  8   0   2    ; R8 := {} , array_size=0, hash_size=2
[0249] newtable  9   0   2    ; R9 := {} , array_size=0, hash_size=2
[0250] settable  9   376 371  ; R9[K120(="AnimEntity")] := K115(="..")
[0251] settable  9   297 402  ; R9[K41(="BoneName")] := K146(="def_c_tail05_joint")
[0252] settable  8   375 9    ; R8[K119(="BoneTransform")] := R9
[0253] newtable  9   0   0    ; R9 := {} , array_size=0, hash_size=0
[0254] settable  8   377 9    ; R8[K121(="Transform")] := R9
[0255] settable  7   275 8    ; R7[K19(="Components")] := R8
[0256] newtable  8   0   2    ; R8 := {} , array_size=0, hash_size=2
[0257] newtable  9   0   3    ; R9 := {} , array_size=0, hash_size=3
[0258] settable  9   264 378  ; R9[K8(="Prefab")] := K122(="AudioDinosaurRagdoll")
[0259] newtable  10  0   2    ; R10 := {} , array_size=0, hash_size=2
[0260] newtable  11  0   1    ; R11 := {} , array_size=0, hash_size=1
[0261] settable  11  268 400  ; R11[K12(="Default")] := K144(=1.0)
[0262] settable  10  379 11   ; R10[K123(="CaptureRadius")] := R11
[0263] newtable  11  0   1    ; R11 := {} , array_size=0, hash_size=1
[0264] settable  11  268 403  ; R11[K12(="Default")] := K147(="Tail")
[0265] settable  10  387 11   ; R10[K131(="Type")] := R11
[0266] settable  9   266 10   ; R9[K10(="Properties")] := R10
[0267] newtable  10  0   1    ; R10 := {} , array_size=0, hash_size=1
[0268] newtable  11  0   0    ; R11 := {} , array_size=0, hash_size=0
[0269] settable  10  377 11   ; R10[K121(="Transform")] := R11
[0270] settable  9   275 10   ; R9[K19(="Components")] := R10
[0271] settable  8   378 9    ; R8[K122(="AudioDinosaurRagdoll")] := R9
[0272] newtable  9   0   3    ; R9 := {} , array_size=0, hash_size=3
[0273] settable  9   264 382  ; R9[K8(="Prefab")] := K126(="AudioDinosaurDetail")
[0274] newtable  10  0   3    ; R10 := {} , array_size=0, hash_size=3
[0275] newtable  11  0   1    ; R11 := {} , array_size=0, hash_size=1
[0276] settable  11  268 384  ; R11[K12(="Default")] := K128(="../../AudioCore")
[0277] settable  10  383 11   ; R10[K127(="Core")] := R11
[0278] newtable  11  0   1    ; R11 := {} , array_size=0, hash_size=1
[0279] settable  11  268 386  ; R11[K12(="Default")] := K130(="../..")
[0280] settable  10  385 11   ; R10[K129(="DataStreamEntity")] := R11
[0281] newtable  11  0   1    ; R11 := {} , array_size=0, hash_size=1
[0282] settable  11  268 403  ; R11[K12(="Default")] := K147(="Tail")
[0283] settable  10  387 11   ; R10[K131(="Type")] := R11
[0284] settable  9   266 10   ; R9[K10(="Properties")] := R10
[0285] newtable  10  0   1    ; R10 := {} , array_size=0, hash_size=1
[0286] newtable  11  0   0    ; R11 := {} , array_size=0, hash_size=0
[0287] settable  10  377 11   ; R10[K121(="Transform")] := R11
[0288] settable  9   275 10   ; R9[K19(="Components")] := R10
[0289] settable  8   404 9    ; R8[K148(="AudioTail")] := R9
[0290] settable  7   364 8    ; R7[K108(="Children")] := R8
[0291] settable  6   402 7    ; R6[K146(="def_c_tail05_joint")] := R7
[0292] newtable  7   0   2    ; R7 := {} , array_size=0, hash_size=2
[0293] newtable  8   0   2    ; R8 := {} , array_size=0, hash_size=2
[0294] newtable  9   0   2    ; R9 := {} , array_size=0, hash_size=2
[0295] settable  9   376 371  ; R9[K120(="AnimEntity")] := K115(="..")
[0296] settable  9   297 405  ; R9[K41(="BoneName")] := K149(="def_l_frontLeglwr_joint")
[0297] settable  8   375 9    ; R8[K119(="BoneTransform")] := R9
[0298] newtable  9   0   0    ; R9 := {} , array_size=0, hash_size=0
[0299] settable  8   377 9    ; R8[K121(="Transform")] := R9
[0300] settable  7   275 8    ; R7[K19(="Components")] := R8
[0301] newtable  8   0   1    ; R8 := {} , array_size=0, hash_size=1
[0302] newtable  9   0   1    ; R9 := {} , array_size=0, hash_size=1
[0303] newtable  10  0   4    ; R10 := {} , array_size=0, hash_size=4
[0304] newtable  11  0   1    ; R11 := {} , array_size=0, hash_size=1
[0305] settable  11  408 386  ; R11[K152(="LoaderPath")] := K130(="../..")
[0306] settable  10  407 11   ; R10[K151(="AssetPackageProvider")] := R11
[0307] newtable  11  0   1    ; R11 := {} , array_size=0, hash_size=1
[0308] settable  11  410 411  ; R11[K154(="ParticleName")] := K155(="NERO_DF_Triceratops_Fall_Impact")
[0309] settable  10  409 11   ; R10[K153(="Particle")] := R11
[0310] newtable  11  0   1    ; R11 := {} , array_size=0, hash_size=1
[0311] settable  11  385 386  ; R11[K129(="DataStreamEntity")] := K130(="../..")
[0312] settable  10  396 11   ; R10[K140(="ParticleTrigger")] := R11
[0313] newtable  11  0   0    ; R11 := {} , array_size=0, hash_size=0
[0314] settable  10  377 11   ; R10[K121(="Transform")] := R11
[0315] settable  9   275 10   ; R9[K19(="Components")] := R10
[0316] settable  8   406 9    ; R8[K150(="VFX_Fall_Impact")] := R9
[0317] settable  7   364 8    ; R7[K108(="Children")] := R8
[0318] settable  6   405 7    ; R6[K149(="def_l_frontLeglwr_joint")] := R7
[0319] newtable  7   0   2    ; R7 := {} , array_size=0, hash_size=2
[0320] newtable  8   0   2    ; R8 := {} , array_size=0, hash_size=2
[0321] newtable  9   0   2    ; R9 := {} , array_size=0, hash_size=2
[0322] settable  9   376 371  ; R9[K120(="AnimEntity")] := K115(="..")
[0323] settable  9   297 412  ; R9[K41(="BoneName")] := K156(="def_l_frontLegupr_joint")
[0324] settable  8   375 9    ; R8[K119(="BoneTransform")] := R9
[0325] newtable  9   0   0    ; R9 := {} , array_size=0, hash_size=0
[0326] settable  8   377 9    ; R8[K121(="Transform")] := R9
[0327] settable  7   275 8    ; R7[K19(="Components")] := R8
[0328] newtable  8   0   1    ; R8 := {} , array_size=0, hash_size=1
[0329] newtable  9   0   1    ; R9 := {} , array_size=0, hash_size=1
[0330] newtable  10  0   4    ; R10 := {} , array_size=0, hash_size=4
[0331] newtable  11  0   1    ; R11 := {} , array_size=0, hash_size=1
[0332] settable  11  408 386  ; R11[K152(="LoaderPath")] := K130(="../..")
[0333] settable  10  407 11   ; R10[K151(="AssetPackageProvider")] := R11
[0334] newtable  11  0   1    ; R11 := {} , array_size=0, hash_size=1
[0335] settable  11  410 411  ; R11[K154(="ParticleName")] := K155(="NERO_DF_Triceratops_Fall_Impact")
[0336] settable  10  409 11   ; R10[K153(="Particle")] := R11
[0337] newtable  11  0   1    ; R11 := {} , array_size=0, hash_size=1
[0338] settable  11  385 386  ; R11[K129(="DataStreamEntity")] := K130(="../..")
[0339] settable  10  396 11   ; R10[K140(="ParticleTrigger")] := R11
[0340] newtable  11  0   0    ; R11 := {} , array_size=0, hash_size=0
[0341] settable  10  377 11   ; R10[K121(="Transform")] := R11
[0342] settable  9   275 10   ; R9[K19(="Components")] := R10
[0343] settable  8   413 9    ; R8[K157(="VFX_Fall_Impact_02")] := R9
[0344] settable  7   364 8    ; R7[K108(="Children")] := R8
[0345] settable  6   412 7    ; R6[K156(="def_l_frontLegupr_joint")] := R7
[0346] newtable  7   0   1    ; R7 := {} , array_size=0, hash_size=1
[0347] newtable  8   0   1    ; R8 := {} , array_size=0, hash_size=1
[0348] newtable  9   0   1    ; R9 := {} , array_size=0, hash_size=1
[0349] settable  9   397 415  ; R9[K141(="Position")] := K159(=nil)
[0350] settable  8   377 9    ; R8[K121(="Transform")] := R9
[0351] settable  7   275 8    ; R7[K19(="Components")] := R8
[0352] settable  6   414 7    ; R6[K158(="StatusIcon")] := R7
[0353] newtable  7   0   3    ; R7 := {} , array_size=0, hash_size=3
[0354] settable  7   264 417  ; R7[K8(="Prefab")] := K161(="DinosaurStraps")
[0355] newtable  8   0   1    ; R8 := {} , array_size=0, hash_size=1
[0356] newtable  9   0   1    ; R9 := {} , array_size=0, hash_size=1
[0357] settable  9   268 418  ; R9[K12(="Default")] := K162(="Nasutoceratops_AirliftStraps")
[0358] settable  8   273 9    ; R8[K17(="ModelName")] := R9
[0359] settable  7   266 8    ; R7[K10(="Properties")] := R8
[0360] newtable  8   0   2    ; R8 := {} , array_size=0, hash_size=2
[0361] newtable  9   0   1    ; R9 := {} , array_size=0, hash_size=1
[0362] newtable  10  1   0    ; R10 := {} , array_size=1, hash_size=0
[0363] loadk     11  13       ; R11 := K13(="Nasutoceratops")
[0364] setlist   10  1   1    ; R10[1 to 1] := R11 to R11
[0365] settable  9   420 10   ; R9[K164(="PackageNames")] := R10
[0366] settable  8   419 9    ; R8[K163(="AssetPackageLoader")] := R9
[0367] newtable  9   0   1    ; R9 := {} , array_size=0, hash_size=1
[0368] settable  9   397 398  ; R9[K141(="Position")] := K142(=nil)
[0369] settable  8   377 9    ; R8[K121(="Transform")] := R9
[0370] settable  7   275 8    ; R7[K19(="Components")] := R8
[0371] settable  6   416 7    ; R6[K160(="Straps")] := R7
[0372] newtable  7   0   1    ; R7 := {} , array_size=0, hash_size=1
[0373] newtable  8   0   2    ; R8 := {} , array_size=0, hash_size=2
[0374] newtable  9   0   1    ; R9 := {} , array_size=0, hash_size=1
[0375] newtable  10  0   2    ; R10 := {} , array_size=0, hash_size=2
[0376] newtable  11  0   1    ; R11 := {} , array_size=0, hash_size=1
[0377] settable  11  297 424  ; R11[K41(="BoneName")] := K168(="def_c_neck01_joint")
[0378] settable  10  423 11   ; R10[K167(="RopeAttachPoint")] := R11
[0379] newtable  11  0   1    ; R11 := {} , array_size=0, hash_size=1
[0380] settable  11  397 425  ; R11[K141(="Position")] := K169(=nil)
[0381] settable  10  377 11   ; R10[K121(="Transform")] := R11
[0382] settable  9   275 10   ; R9[K19(="Components")] := R10
[0383] settable  8   422 9    ; R8[K166(="Neck")] := R9
[0384] newtable  9   0   1    ; R9 := {} , array_size=0, hash_size=1
[0385] newtable  10  0   2    ; R10 := {} , array_size=0, hash_size=2
[0386] newtable  11  0   1    ; R11 := {} , array_size=0, hash_size=1
[0387] settable  11  297 426  ; R11[K41(="BoneName")] := K170(="def_c_tail01_joint")
[0388] settable  10  423 11   ; R10[K167(="RopeAttachPoint")] := R11
[0389] newtable  11  0   1    ; R11 := {} , array_size=0, hash_size=1
[0390] settable  11  397 427  ; R11[K141(="Position")] := K171(=nil)
[0391] settable  10  377 11   ; R10[K121(="Transform")] := R11
[0392] settable  9   275 10   ; R9[K19(="Components")] := R10
[0393] settable  8   403 9    ; R8[K147(="Tail")] := R9
[0394] settable  7   364 8    ; R7[K108(="Children")] := R8
[0395] settable  6   421 7    ; R6[K165(="WinchAttachPoints")] := R7
[0396] settable  5   364 6    ; R5[K108(="Children")] := R6
[0397] settabup  0   263 5    ; U0[K7(="Root")] := R5
[0398] newtable  5   0   5    ; R5 := {} , array_size=0, hash_size=5
[0399] newtable  6   0   13   ; R6 := {} , array_size=0, hash_size=13
[0400] newtable  7   0   5    ; R7 := {} , array_size=0, hash_size=5
[0401] newtable  8   0   2    ; R8 := {} , array_size=0, hash_size=2
[0402] newtable  9   0   4    ; R9 := {} , array_size=0, hash_size=4
[0403] newtable  10  0   6    ; R10 := {} , array_size=0, hash_size=6
[0404] settable  10  431 382  ; R10[K175(="AudioBoundingVolume")] := K126(="AudioDinosaurDetail")
[0405] settable  10  432 382  ; R10[K176(="AudioDoppler")] := K126(="AudioDinosaurDetail")
[0406] settable  10  433 382  ; R10[K177(="AudioPosition")] := K126(="AudioDinosaurDetail")
[0407] settable  10  434 382  ; R10[K178(="BoundingVolumeBroadphase")] := K126(="AudioDinosaurDetail")
[0408] settable  10  377 382  ; R10[K121(="Transform")] := K126(="AudioDinosaurDetail")
[0409] settable  10  435 382  ; R10[K179(="Velocity")] := K126(="AudioDinosaurDetail")
[0410] settable  9   430 10   ; R9[K174(="ComponentSources")] := R10
[0411] newtable  10  0   8    ; R10 := {} , array_size=0, hash_size=8
[0412] newtable  11  0   0    ; R11 := {} , array_size=0, hash_size=0
[0413] settable  10  431 11   ; R10[K175(="AudioBoundingVolume")] := R11
[0414] newtable  11  0   1    ; R11 := {} , array_size=0, hash_size=1
[0415] newtable  12  0   1    ; R12 := {} , array_size=0, hash_size=1
[0416] settable  12  437 385  ; R12[K181(="__property")] := K129(="DataStreamEntity")
[0417] settable  11  385 12   ; R11[K129(="DataStreamEntity")] := R12
[0418] settable  10  436 11   ; R10[K180(="AudioDataStream")] := R11
[0419] newtable  11  0   2    ; R11 := {} , array_size=0, hash_size=2
[0420] newtable  12  0   1    ; R12 := {} , array_size=0, hash_size=1
[0421] settable  12  437 383  ; R12[K181(="__property")] := K127(="Core")
[0422] settable  11  383 12   ; R11[K127(="Core")] := R12
[0423] newtable  12  0   1    ; R12 := {} , array_size=0, hash_size=1
[0424] settable  12  437 387  ; R12[K181(="__property")] := K131(="Type")
[0425] settable  11  387 12   ; R11[K131(="Type")] := R12
[0426] settable  10  382 11   ; R10[K126(="AudioDinosaurDetail")] := R11
[0427] newtable  11  0   0    ; R11 := {} , array_size=0, hash_size=0
[0428] settable  10  432 11   ; R10[K176(="AudioDoppler")] := R11
[0429] newtable  11  0   0    ; R11 := {} , array_size=0, hash_size=0
[0430] settable  10  433 11   ; R10[K177(="AudioPosition")] := R11
[0431] newtable  11  0   0    ; R11 := {} , array_size=0, hash_size=0
[0432] settable  10  434 11   ; R10[K178(="BoundingVolumeBroadphase")] := R11
[0433] newtable  11  0   0    ; R11 := {} , array_size=0, hash_size=0
[0434] settable  10  377 11   ; R10[K121(="Transform")] := R11
[0435] newtable  11  0   0    ; R11 := {} , array_size=0, hash_size=0
[0436] settable  10  435 11   ; R10[K179(="Velocity")] := R11
[0437] settable  9   275 10   ; R9[K19(="Components")] := R10
[0438] newtable  10  0   0    ; R10 := {} , array_size=0, hash_size=0
[0439] settable  9   438 10   ; R9[K182(="IncompleteComponents")] := R10
[0440] newtable  10  0   3    ; R10 := {} , array_size=0, hash_size=3
[0441] newtable  11  0   2    ; R11 := {} , array_size=0, hash_size=2
[0442] settable  11  268 371  ; R11[K12(="Default")] := K115(="..")
[0443] settable  11  387 439  ; R11[K131(="Type")] := K183(="entity")
[0444] settable  10  383 11   ; R10[K127(="Core")] := R11
[0445] newtable  11  0   2    ; R11 := {} , array_size=0, hash_size=2
[0446] settable  11  268 386  ; R11[K12(="Default")] := K130(="../..")
[0447] settable  11  387 439  ; R11[K131(="Type")] := K183(="entity")
[0448] settable  10  385 11   ; R10[K129(="DataStreamEntity")] := R11
[0449] newtable  11  0   3    ; R11 := {} , array_size=0, hash_size=3
[0450] settable  11  268 440  ; R11[K12(="Default")] := K184(="Body")
[0451] settable  11  441 442  ; R11[K185(="Enum")] := K186(="AudioDinosaurType")
[0452] settable  11  387 443  ; R11[K131(="Type")] := K187(="uint8")
[0453] settable  10  387 11   ; R10[K131(="Type")] := R11
[0454] settable  9   266 10   ; R9[K10(="Properties")] := R10
[0455] settable  8   429 9    ; R8[K173(="AudioDinosaurBody")] := R9
[0456] newtable  9   0   4    ; R9 := {} , array_size=0, hash_size=4
[0457] newtable  10  0   1    ; R10 := {} , array_size=0, hash_size=1
[0458] settable  10  377 444  ; R10[K121(="Transform")] := K188(="AudioDinosaurFootplant")
[0459] settable  9   430 10   ; R9[K174(="ComponentSources")] := R10
[0460] newtable  10  0   3    ; R10 := {} , array_size=0, hash_size=3
[0461] newtable  11  0   1    ; R11 := {} , array_size=0, hash_size=1
[0462] newtable  12  0   1    ; R12 := {} , array_size=0, hash_size=1
[0463] settable  12  437 385  ; R12[K181(="__property")] := K129(="DataStreamEntity")
[0464] settable  11  385 12   ; R11[K129(="DataStreamEntity")] := R12
[0465] settable  10  436 11   ; R10[K180(="AudioDataStream")] := R11
[0466] newtable  11  0   2    ; R11 := {} , array_size=0, hash_size=2
[0467] newtable  12  0   1    ; R12 := {} , array_size=0, hash_size=1
[0468] settable  12  437 383  ; R12[K181(="__property")] := K127(="Core")
[0469] settable  11  383 12   ; R11[K127(="Core")] := R12
[0470] newtable  12  0   1    ; R12 := {} , array_size=0, hash_size=1
[0471] settable  12  437 387  ; R12[K181(="__property")] := K131(="Type")
[0472] settable  11  387 12   ; R11[K131(="Type")] := R12
[0473] settable  10  382 11   ; R10[K126(="AudioDinosaurDetail")] := R11
[0474] newtable  11  0   1    ; R11 := {} , array_size=0, hash_size=1
[0475] settable  11  445 446  ; R11[K189(="UseTransform")] := K190(=false)
[0476] settable  10  377 11   ; R10[K121(="Transform")] := R11
[0477] settable  9   275 10   ; R9[K19(="Components")] := R10
[0478] newtable  10  0   0    ; R10 := {} , array_size=0, hash_size=0
[0479] settable  9   438 10   ; R9[K182(="IncompleteComponents")] := R10
[0480] newtable  10  0   3    ; R10 := {} , array_size=0, hash_size=3
[0481] newtable  11  0   2    ; R11 := {} , array_size=0, hash_size=2
[0482] settable  11  268 371  ; R11[K12(="Default")] := K115(="..")
[0483] settable  11  387 439  ; R11[K131(="Type")] := K183(="entity")
[0484] settable  10  383 11   ; R10[K127(="Core")] := R11
[0485] newtable  11  0   3    ; R11 := {} , array_size=0, hash_size=3
[0486] settable  11  268 386  ; R11[K12(="Default")] := K130(="../..")
[0487] settable  11  447 448  ; R11[K191(="Optional")] := K192(=true)
[0488] settable  11  387 439  ; R11[K131(="Type")] := K183(="entity")
[0489] settable  10  385 11   ; R10[K129(="DataStreamEntity")] := R11
[0490] newtable  11  0   3    ; R11 := {} , array_size=0, hash_size=3
[0491] settable  11  268 449  ; R11[K12(="Default")] := K193(="Footplant")
[0492] settable  11  441 442  ; R11[K185(="Enum")] := K186(="AudioDinosaurType")
[0493] settable  11  387 443  ; R11[K131(="Type")] := K187(="uint8")
[0494] settable  10  387 11   ; R10[K131(="Type")] := R11
[0495] settable  9   266 10   ; R9[K10(="Properties")] := R10
[0496] settable  8   444 9    ; R8[K188(="AudioDinosaurFootplant")] := R9
[0497] settable  7   364 8    ; R7[K108(="Children")] := R8
[0498] newtable  8   0   7    ; R8 := {} , array_size=0, hash_size=7
[0499] settable  8   431 366  ; R8[K175(="AudioBoundingVolume")] := K110(="AudioDinosaurCore")
[0500] settable  8   432 366  ; R8[K176(="AudioDoppler")] := K110(="AudioDinosaurCore")
[0501] settable  8   433 366  ; R8[K177(="AudioPosition")] := K110(="AudioDinosaurCore")
[0502] settable  8   450 366  ; R8[K194(="AudioWithinListenerRange")] := K110(="AudioDinosaurCore")
[0503] settable  8   434 366  ; R8[K178(="BoundingVolumeBroadphase")] := K110(="AudioDinosaurCore")
[0504] settable  8   377 366  ; R8[K121(="Transform")] := K110(="AudioDinosaurCore")
[0505] settable  8   435 366  ; R8[K179(="Velocity")] := K110(="AudioDinosaurCore")
[0506] settable  7   430 8    ; R7[K174(="ComponentSources")] := R8
[0507] newtable  8   0   8    ; R8 := {} , array_size=0, hash_size=8
[0508] newtable  9   0   0    ; R9 := {} , array_size=0, hash_size=0
[0509] settable  8   431 9    ; R8[K175(="AudioBoundingVolume")] := R9
[0510] newtable  9   0   6    ; R9 := {} , array_size=0, hash_size=6
[0511] newtable  10  0   1    ; R10 := {} , array_size=0, hash_size=1
[0512] settable  10  437 367  ; R10[K181(="__property")] := K111(="Family")
[0513] settable  9   367 10   ; R9[K111(="Family")] := R10
[0514] newtable  10  0   1    ; R10 := {} , array_size=0, hash_size=1
[0515] settable  10  437 451  ; R10[K181(="__property")] := K195(="FamilySize")
[0516] settable  9   451 10   ; R9[K195(="FamilySize")] := R10
[0517] newtable  10  0   1    ; R10 := {} , array_size=0, hash_size=1
[0518] settable  10  437 452  ; R10[K181(="__property")] := K196(="FootplantType")
[0519] settable  9   452 10   ; R9[K196(="FootplantType")] := R10
[0520] newtable  10  0   2    ; R10 := {} , array_size=0, hash_size=2
[0521] settable  10  373 298  ; R10[K117(="LeftFootBoneName")] := K42(="def_l_frontFoot_joint")
[0522] settable  10  374 299  ; R10[K118(="RightFootBoneName")] := K43(="def_r_frontFoot_joint")
[0523] settable  9   372 10   ; R9[K116(="FrontFeet")] := R10
[0524] newtable  10  0   1    ; R10 := {} , array_size=0, hash_size=1
[0525] settable  10  437 369  ; R10[K181(="__property")] := K113(="Name")
[0526] settable  9   369 10   ; R9[K113(="Name")] := R10
[0527] newtable  10  0   1    ; R10 := {} , array_size=0, hash_size=1
[0528] settable  10  437 370  ; R10[K181(="__property")] := K114(="RootEntity")
[0529] settable  9   370 10   ; R9[K114(="RootEntity")] := R10
[0530] settable  8   366 9    ; R8[K110(="AudioDinosaurCore")] := R9
[0531] newtable  9   0   0    ; R9 := {} , array_size=0, hash_size=0
[0532] settable  8   432 9    ; R8[K176(="AudioDoppler")] := R9
[0533] newtable  9   0   0    ; R9 := {} , array_size=0, hash_size=0
[0534] settable  8   433 9    ; R8[K177(="AudioPosition")] := R9
[0535] newtable  9   0   0    ; R9 := {} , array_size=0, hash_size=0
[0536] settable  8   450 9    ; R8[K194(="AudioWithinListenerRange")] := R9
[0537] newtable  9   0   0    ; R9 := {} , array_size=0, hash_size=0
[0538] settable  8   434 9    ; R8[K178(="BoundingVolumeBroadphase")] := R9
[0539] newtable  9   0   0    ; R9 := {} , array_size=0, hash_size=0
[0540] settable  8   377 9    ; R8[K121(="Transform")] := R9
[0541] newtable  9   0   0    ; R9 := {} , array_size=0, hash_size=0
[0542] settable  8   435 9    ; R8[K179(="Velocity")] := R9
[0543] settable  7   275 8    ; R7[K19(="Components")] := R8
[0544] newtable  8   0   0    ; R8 := {} , array_size=0, hash_size=0
[0545] settable  7   438 8    ; R7[K182(="IncompleteComponents")] := R8
[0546] newtable  8   0   5    ; R8 := {} , array_size=0, hash_size=5
[0547] newtable  9   0   3    ; R9 := {} , array_size=0, hash_size=3
[0548] settable  9   268 368  ; R9[K12(="Default")] := K112(="Cerapod")
[0549] settable  9   441 453  ; R9[K185(="Enum")] := K197(="AudioDinosaurFamily")
[0550] settable  9   387 443  ; R9[K131(="Type")] := K187(="uint8")
[0551] settable  8   367 9    ; R8[K111(="Family")] := R9
[0552] newtable  9   0   3    ; R9 := {} , array_size=0, hash_size=3
[0553] settable  9   268 293  ; R9[K12(="Default")] := K37(="Medium")
[0554] settable  9   441 454  ; R9[K185(="Enum")] := K198(="AudioDinosaurFamilySize")
[0555] settable  9   387 443  ; R9[K131(="Type")] := K187(="uint8")
[0556] settable  8   451 9    ; R8[K195(="FamilySize")] := R9
[0557] newtable  9   0   4    ; R9 := {} , array_size=0, hash_size=4
[0558] settable  9   268 367  ; R9[K12(="Default")] := K111(="Family")
[0559] settable  9   441 455  ; R9[K185(="Enum")] := K199(="AudioDinosaurFootplantType")
[0560] settable  9   447 446  ; R9[K191(="Optional")] := K190(=false)
[0561] settable  9   387 443  ; R9[K131(="Type")] := K187(="uint8")
[0562] settable  8   452 9    ; R8[K196(="FootplantType")] := R9
[0563] newtable  9   0   2    ; R9 := {} , array_size=0, hash_size=2
[0564] settable  9   268 269  ; R9[K12(="Default")] := K13(="Nasutoceratops")
[0565] settable  9   387 456  ; R9[K131(="Type")] := K200(="string")
[0566] settable  8   369 9    ; R8[K113(="Name")] := R9
[0567] newtable  9   0   2    ; R9 := {} , array_size=0, hash_size=2
[0568] settable  9   268 371  ; R9[K12(="Default")] := K115(="..")
[0569] settable  9   387 439  ; R9[K131(="Type")] := K183(="entity")
[0570] settable  8   370 9    ; R8[K114(="RootEntity")] := R9
[0571] settable  7   266 8    ; R7[K10(="Properties")] := R8
[0572] settable  6   365 7    ; R6[K109(="AudioCore")] := R7
[0573] newtable  7   0   2    ; R7 := {} , array_size=0, hash_size=2
[0574] newtable  8   0   2    ; R8 := {} , array_size=0, hash_size=2
[0575] newtable  9   0   2    ; R9 := {} , array_size=0, hash_size=2
[0576] settable  9   376 371  ; R9[K120(="AnimEntity")] := K115(="..")
[0577] settable  9   297 307  ; R9[K41(="BoneName")] := K51(="def_c_head_joint")
[0578] settable  8   375 9    ; R8[K119(="BoneTransform")] := R9
[0579] newtable  9   0   0    ; R9 := {} , array_size=0, hash_size=0
[0580] settable  8   377 9    ; R8[K121(="Transform")] := R9
[0581] settable  7   275 8    ; R7[K19(="Components")] := R8
[0582] newtable  8   0   0    ; R8 := {} , array_size=0, hash_size=0
[0583] settable  7   438 8    ; R7[K182(="IncompleteComponents")] := R8
[0584] settable  6   457 7    ; R6[K201(="HeadLookReactionBite")] := R7
[0585] newtable  7   0   2    ; R7 := {} , array_size=0, hash_size=2
[0586] newtable  8   0   3    ; R8 := {} , array_size=0, hash_size=3
[0587] newtable  9   0   3    ; R9 := {} , array_size=0, hash_size=3
[0588] settable  9   354 460  ; R9[K98(="Length")] := K204(=3.0)
[0589] settable  9   284 461  ; R9[K28(="Radius")] := K205(=7.0)
[0590] newtable  10  1   0    ; R10 := {} , array_size=1, hash_size=0
[0591] loadk     11  207      ; R11 := K207(="dinosaur_nearby")
[0592] setlist   10  1   1    ; R10[1 to 1] := R11 to R11
[0593] settable  9   462 10   ; R9[K206(="SpatialGroups")] := R10
[0594] settable  8   459 9    ; R8[K203(="SpatialCapsule")] := R9
[0595] newtable  9   0   0    ; R9 := {} , array_size=0, hash_size=0
[0596] settable  8   464 9    ; R8[K208(="SpatialDatabase")] := R9
[0597] newtable  9   0   0    ; R9 := {} , array_size=0, hash_size=0
[0598] settable  8   377 9    ; R8[K121(="Transform")] := R9
[0599] settable  7   275 8    ; R7[K19(="Components")] := R8
[0600] newtable  8   0   0    ; R8 := {} , array_size=0, hash_size=0
[0601] settable  7   438 8    ; R7[K182(="IncompleteComponents")] := R8
[0602] settable  6   458 7    ; R6[K202(="NearbyBuildingBlocker")] := R7
[0603] newtable  7   0   2    ; R7 := {} , array_size=0, hash_size=2
[0604] newtable  8   0   3    ; R8 := {} , array_size=0, hash_size=3
[0605] newtable  9   0   1    ; R9 := {} , array_size=0, hash_size=1
[0606] settable  9   467 371  ; R9[K211(="Dinosaur")] := K115(="..")
[0607] settable  8   466 9    ; R8[K210(="DinosaurObjectiveMarker")] := R9
[0608] newtable  9   0   1    ; R9 := {} , array_size=0, hash_size=1
[0609] settable  9   468 469  ; R9[K212(="Icon")] := K213(="None")
[0610] settable  8   465 9    ; R8[K209(="ObjectiveMarker")] := R9
[0611] newtable  9   0   1    ; R9 := {} , array_size=0, hash_size=1
[0612] settable  9   397 470  ; R9[K141(="Position")] := K214(=nil)
[0613] settable  8   377 9    ; R8[K121(="Transform")] := R9
[0614] settable  7   275 8    ; R7[K19(="Components")] := R8
[0615] newtable  8   0   0    ; R8 := {} , array_size=0, hash_size=0
[0616] settable  7   438 8    ; R7[K182(="IncompleteComponents")] := R8
[0617] settable  6   465 7    ; R6[K209(="ObjectiveMarker")] := R7
[0618] newtable  7   0   3    ; R7 := {} , array_size=0, hash_size=3
[0619] newtable  8   0   2    ; R8 := {} , array_size=0, hash_size=2
[0620] settable  8   471 472  ; R8[K215(="DinosaurStatusIcon")] := K216(="DinosaurBase/StatusIcon")
[0621] settable  8   414 472  ; R8[K158(="StatusIcon")] := K216(="DinosaurBase/StatusIcon")
[0622] settable  7   430 8    ; R7[K174(="ComponentSources")] := R8
[0623] newtable  8   0   3    ; R8 := {} , array_size=0, hash_size=3
[0624] newtable  9   0   1    ; R9 := {} , array_size=0, hash_size=1
[0625] settable  9   467 371  ; R9[K211(="Dinosaur")] := K115(="..")
[0626] settable  8   471 9    ; R8[K215(="DinosaurStatusIcon")] := R9
[0627] newtable  9   0   1    ; R9 := {} , array_size=0, hash_size=1
[0628] settable  9   473 448  ; R9[K217(="IgnoreParentRotation")] := K192(=true)
[0629] settable  8   414 9    ; R8[K158(="StatusIcon")] := R9
[0630] newtable  9   0   1    ; R9 := {} , array_size=0, hash_size=1
[0631] settable  9   397 415  ; R9[K141(="Position")] := K159(=nil)
[0632] settable  8   377 9    ; R8[K121(="Transform")] := R9
[0633] settable  7   275 8    ; R7[K19(="Components")] := R8
[0634] newtable  8   0   0    ; R8 := {} , array_size=0, hash_size=0
[0635] settable  7   438 8    ; R7[K182(="IncompleteComponents")] := R8
[0636] settable  6   414 7    ; R6[K158(="StatusIcon")] := R7
[0637] newtable  7   0   4    ; R7 := {} , array_size=0, hash_size=4
[0638] newtable  8   0   2    ; R8 := {} , array_size=0, hash_size=2
[0639] settable  8   474 417  ; R8[K218(="AnimationProxy")] := K161(="DinosaurStraps")
[0640] settable  8   407 417  ; R8[K151(="AssetPackageProvider")] := K161(="DinosaurStraps")
[0641] settable  7   430 8    ; R7[K174(="ComponentSources")] := R8
[0642] newtable  8   0   5    ; R8 := {} , array_size=0, hash_size=5
[0643] newtable  9   0   2    ; R9 := {} , array_size=0, hash_size=2
[0644] settable  9   475 371  ; R9[K219(="AnimationEntity")] := K115(="..")
[0645] settable  9   476 477  ; R9[K220(="AnimationType")] := K221(="FGDK Animation")
[0646] settable  8   474 9    ; R8[K218(="AnimationProxy")] := R9
[0647] newtable  9   0   2    ; R9 := {} , array_size=0, hash_size=2
[0648] newtable  10  1   0    ; R10 := {} , array_size=1, hash_size=0
[0649] loadk     11  223      ; R11 := K223(="DinosaurCommon")
[0650] setlist   10  1   1    ; R10[1 to 1] := R11 to R11
[0651] settable  9   478 10   ; R9[K222(="ManualPackageNames")] := R10
[0652] newtable  10  1   0    ; R10 := {} , array_size=1, hash_size=0
[0653] loadk     11  13       ; R11 := K13(="Nasutoceratops")
[0654] setlist   10  1   1    ; R10[1 to 1] := R11 to R11
[0655] settable  9   420 10   ; R9[K164(="PackageNames")] := R10
[0656] settable  8   419 9    ; R8[K163(="AssetPackageLoader")] := R9
[0657] newtable  9   0   1    ; R9 := {} , array_size=0, hash_size=1
[0658] settable  9   408 480  ; R9[K152(="LoaderPath")] := K224(=".")
[0659] settable  8   407 9    ; R8[K151(="AssetPackageProvider")] := R9
[0660] newtable  9   0   1    ; R9 := {} , array_size=0, hash_size=1
[0661] newtable  10  0   1    ; R10 := {} , array_size=0, hash_size=1
[0662] settable  10  437 273  ; R10[K181(="__property")] := K17(="ModelName")
[0663] settable  9   273 10   ; R9[K17(="ModelName")] := R10
[0664] settable  8   345 9    ; R8[K89(="Model")] := R9
[0665] newtable  9   0   1    ; R9 := {} , array_size=0, hash_size=1
[0666] settable  9   397 398  ; R9[K141(="Position")] := K142(=nil)
[0667] settable  8   377 9    ; R8[K121(="Transform")] := R9
[0668] settable  7   275 8    ; R7[K19(="Components")] := R8
[0669] newtable  8   0   0    ; R8 := {} , array_size=0, hash_size=0
[0670] settable  7   438 8    ; R7[K182(="IncompleteComponents")] := R8
[0671] newtable  8   0   1    ; R8 := {} , array_size=0, hash_size=1
[0672] newtable  9   0   3    ; R9 := {} , array_size=0, hash_size=3
[0673] settable  9   268 418  ; R9[K12(="Default")] := K162(="Nasutoceratops_AirliftStraps")
[0674] settable  9   387 456  ; R9[K131(="Type")] := K200(="string")
[0675] settable  9   481 482  ; R9[K225(="UIGroup")] := K226(="Visuals")
[0676] settable  8   273 9    ; R8[K17(="ModelName")] := R9
[0677] settable  7   266 8    ; R7[K10(="Properties")] := R8
[0678] settable  6   416 7    ; R6[K160(="Straps")] := R7
[0679] newtable  7   0   4    ; R7 := {} , array_size=0, hash_size=4
[0680] newtable  8   0   4    ; R8 := {} , array_size=0, hash_size=4
[0681] newtable  9   0   2    ; R9 := {} , array_size=0, hash_size=2
[0682] newtable  10  0   2    ; R10 := {} , array_size=0, hash_size=2
[0683] newtable  11  0   2    ; R11 := {} , array_size=0, hash_size=2
[0684] settable  11  484 386  ; R11[K228(="PhysicsEntity")] := K130(="../..")
[0685] settable  11  485 448  ; R11[K229(="PhysicsEntityIsDrivenSkeleton")] := K192(=true)
[0686] settable  10  423 11   ; R10[K167(="RopeAttachPoint")] := R11
[0687] newtable  11  0   1    ; R11 := {} , array_size=0, hash_size=1
[0688] settable  11  397 486  ; R11[K141(="Position")] := K230(=nil)
[0689] settable  10  377 11   ; R10[K121(="Transform")] := R11
[0690] settable  9   275 10   ; R9[K19(="Components")] := R10
[0691] newtable  10  0   0    ; R10 := {} , array_size=0, hash_size=0
[0692] settable  9   438 10   ; R9[K182(="IncompleteComponents")] := R10
[0693] settable  8   483 9    ; R8[K227(="LowerBack")] := R9
[0694] newtable  9   0   2    ; R9 := {} , array_size=0, hash_size=2
[0695] newtable  10  0   2    ; R10 := {} , array_size=0, hash_size=2
[0696] newtable  11  0   3    ; R11 := {} , array_size=0, hash_size=3
[0697] settable  11  297 424  ; R11[K41(="BoneName")] := K168(="def_c_neck01_joint")
[0698] settable  11  484 386  ; R11[K228(="PhysicsEntity")] := K130(="../..")
[0699] settable  11  485 448  ; R11[K229(="PhysicsEntityIsDrivenSkeleton")] := K192(=true)
[0700] settable  10  423 11   ; R10[K167(="RopeAttachPoint")] := R11
[0701] newtable  11  0   1    ; R11 := {} , array_size=0, hash_size=1
[0702] settable  11  397 487  ; R11[K141(="Position")] := K231(=nil)
[0703] settable  10  377 11   ; R10[K121(="Transform")] := R11
[0704] settable  9   275 10   ; R9[K19(="Components")] := R10
[0705] newtable  10  0   0    ; R10 := {} , array_size=0, hash_size=0
[0706] settable  9   438 10   ; R9[K182(="IncompleteComponents")] := R10
[0707] settable  8   422 9    ; R8[K166(="Neck")] := R9
[0708] newtable  9   0   2    ; R9 := {} , array_size=0, hash_size=2
[0709] newtable  10  0   2    ; R10 := {} , array_size=0, hash_size=2
[0710] newtable  11  0   3    ; R11 := {} , array_size=0, hash_size=3
[0711] settable  11  297 426  ; R11[K41(="BoneName")] := K170(="def_c_tail01_joint")
[0712] settable  11  484 386  ; R11[K228(="PhysicsEntity")] := K130(="../..")
[0713] settable  11  485 448  ; R11[K229(="PhysicsEntityIsDrivenSkeleton")] := K192(=true)
[0714] settable  10  423 11   ; R10[K167(="RopeAttachPoint")] := R11
[0715] newtable  11  0   1    ; R11 := {} , array_size=0, hash_size=1
[0716] settable  11  397 488  ; R11[K141(="Position")] := K232(=nil)
[0717] settable  10  377 11   ; R10[K121(="Transform")] := R11
[0718] settable  9   275 10   ; R9[K19(="Components")] := R10
[0719] newtable  10  0   0    ; R10 := {} , array_size=0, hash_size=0
[0720] settable  9   438 10   ; R9[K182(="IncompleteComponents")] := R10
[0721] settable  8   403 9    ; R8[K147(="Tail")] := R9
[0722] newtable  9   0   2    ; R9 := {} , array_size=0, hash_size=2
[0723] newtable  10  0   2    ; R10 := {} , array_size=0, hash_size=2
[0724] newtable  11  0   2    ; R11 := {} , array_size=0, hash_size=2
[0725] settable  11  484 386  ; R11[K228(="PhysicsEntity")] := K130(="../..")
[0726] settable  11  485 448  ; R11[K229(="PhysicsEntityIsDrivenSkeleton")] := K192(=true)
[0727] settable  10  423 11   ; R10[K167(="RopeAttachPoint")] := R11
[0728] newtable  11  0   1    ; R11 := {} , array_size=0, hash_size=1
[0729] settable  11  397 490  ; R11[K141(="Position")] := K234(=nil)
[0730] settable  10  377 11   ; R10[K121(="Transform")] := R11
[0731] settable  9   275 10   ; R9[K19(="Components")] := R10
[0732] newtable  10  0   0    ; R10 := {} , array_size=0, hash_size=0
[0733] settable  9   438 10   ; R9[K182(="IncompleteComponents")] := R10
[0734] settable  8   489 9    ; R8[K233(="UpperBack")] := R9
[0735] settable  7   364 8    ; R7[K108(="Children")] := R8
[0736] newtable  8   0   1    ; R8 := {} , array_size=0, hash_size=1
[0737] settable  8   377 491  ; R8[K121(="Transform")] := K235(="DinosaurBase/WinchAttachPoints")
[0738] settable  7   430 8    ; R7[K174(="ComponentSources")] := R8
[0739] newtable  8   0   1    ; R8 := {} , array_size=0, hash_size=1
[0740] newtable  9   0   0    ; R9 := {} , array_size=0, hash_size=0
[0741] settable  8   377 9    ; R8[K121(="Transform")] := R9
[0742] settable  7   275 8    ; R7[K19(="Components")] := R8
[0743] newtable  8   0   0    ; R8 := {} , array_size=0, hash_size=0
[0744] settable  7   438 8    ; R7[K182(="IncompleteComponents")] := R8
[0745] settable  6   421 7    ; R6[K165(="WinchAttachPoints")] := R7
[0746] newtable  7   0   4    ; R7 := {} , array_size=0, hash_size=4
[0747] newtable  8   0   6    ; R8 := {} , array_size=0, hash_size=6
[0748] newtable  9   0   4    ; R9 := {} , array_size=0, hash_size=4
[0749] newtable  10  0   6    ; R10 := {} , array_size=0, hash_size=6
[0750] settable  10  431 378  ; R10[K175(="AudioBoundingVolume")] := K122(="AudioDinosaurRagdoll")
[0751] settable  10  432 492  ; R10[K176(="AudioDoppler")] := K236(="AudioEmitter")
[0752] settable  10  433 492  ; R10[K177(="AudioPosition")] := K236(="AudioEmitter")
[0753] settable  10  434 378  ; R10[K178(="BoundingVolumeBroadphase")] := K122(="AudioDinosaurRagdoll")
[0754] settable  10  377 492  ; R10[K121(="Transform")] := K236(="AudioEmitter")
[0755] settable  10  435 492  ; R10[K179(="Velocity")] := K236(="AudioEmitter")
[0756] settable  9   430 10   ; R9[K174(="ComponentSources")] := R10
[0757] newtable  10  0   7    ; R10 := {} , array_size=0, hash_size=7
[0758] newtable  11  0   0    ; R11 := {} , array_size=0, hash_size=0
[0759] settable  10  431 11   ; R10[K175(="AudioBoundingVolume")] := R11
[0760] newtable  11  0   4    ; R11 := {} , array_size=0, hash_size=4
[0761] newtable  12  0   1    ; R12 := {} , array_size=0, hash_size=1
[0762] settable  12  437 379  ; R12[K181(="__property")] := K123(="CaptureRadius")
[0763] settable  11  379 12   ; R11[K123(="CaptureRadius")] := R12
[0764] newtable  12  0   1    ; R12 := {} , array_size=0, hash_size=1
[0765] settable  12  437 370  ; R12[K181(="__property")] := K114(="RootEntity")
[0766] settable  11  370 12   ; R11[K114(="RootEntity")] := R12
[0767] newtable  12  0   1    ; R12 := {} , array_size=0, hash_size=1
[0768] settable  12  437 387  ; R12[K181(="__property")] := K131(="Type")
[0769] settable  11  387 12   ; R11[K131(="Type")] := R12
[0770] newtable  12  0   1    ; R12 := {} , array_size=0, hash_size=1
[0771] settable  12  437 493  ; R12[K181(="__property")] := K237(="WeightType")
[0772] settable  11  493 12   ; R11[K237(="WeightType")] := R12
[0773] settable  10  378 11   ; R10[K122(="AudioDinosaurRagdoll")] := R11
[0774] newtable  11  0   0    ; R11 := {} , array_size=0, hash_size=0
[0775] settable  10  432 11   ; R10[K176(="AudioDoppler")] := R11
[0776] newtable  11  0   0    ; R11 := {} , array_size=0, hash_size=0
[0777] settable  10  433 11   ; R10[K177(="AudioPosition")] := R11
[0778] newtable  11  0   0    ; R11 := {} , array_size=0, hash_size=0
[0779] settable  10  434 11   ; R10[K178(="BoundingVolumeBroadphase")] := R11
[0780] newtable  11  0   0    ; R11 := {} , array_size=0, hash_size=0
[0781] settable  10  377 11   ; R10[K121(="Transform")] := R11
[0782] newtable  11  0   0    ; R11 := {} , array_size=0, hash_size=0
[0783] settable  10  435 11   ; R10[K179(="Velocity")] := R11
[0784] settable  9   275 10   ; R9[K19(="Components")] := R10
[0785] newtable  10  0   0    ; R10 := {} , array_size=0, hash_size=0
[0786] settable  9   438 10   ; R9[K182(="IncompleteComponents")] := R10
[0787] newtable  10  0   4    ; R10 := {} , array_size=0, hash_size=4
[0788] newtable  11  0   2    ; R11 := {} , array_size=0, hash_size=2
[0789] settable  11  268 380  ; R11[K12(="Default")] := K124(=1.5)
[0790] settable  11  387 494  ; R11[K131(="Type")] := K238(="float")
[0791] settable  10  379 11   ; R10[K123(="CaptureRadius")] := R11
[0792] newtable  11  0   2    ; R11 := {} , array_size=0, hash_size=2
[0793] settable  11  268 386  ; R11[K12(="Default")] := K130(="../..")
[0794] settable  11  387 439  ; R11[K131(="Type")] := K183(="entity")
[0795] settable  10  370 11   ; R10[K114(="RootEntity")] := R11
[0796] newtable  11  0   4    ; R11 := {} , array_size=0, hash_size=4
[0797] settable  11  268 495  ; R11[K12(="Default")] := K239(="BodyFront")
[0798] settable  11  441 496  ; R11[K185(="Enum")] := K240(="AudioDinosaurRagdollType")
[0799] settable  11  447 446  ; R11[K191(="Optional")] := K190(=false)
[0800] settable  11  387 443  ; R11[K131(="Type")] := K187(="uint8")
[0801] settable  10  387 11   ; R10[K131(="Type")] := R11
[0802] newtable  11  0   4    ; R11 := {} , array_size=0, hash_size=4
[0803] settable  11  268 293  ; R11[K12(="Default")] := K37(="Medium")
[0804] settable  11  441 497  ; R11[K185(="Enum")] := K241(="AudioDinosaurRagdollWeight")
[0805] settable  11  447 446  ; R11[K191(="Optional")] := K190(=false)
[0806] settable  11  387 443  ; R11[K131(="Type")] := K187(="uint8")
[0807] settable  10  493 11   ; R10[K237(="WeightType")] := R11
[0808] settable  9   266 10   ; R9[K10(="Properties")] := R10
[0809] settable  8   378 9    ; R8[K122(="AudioDinosaurRagdoll")] := R9
[0810] newtable  9   0   4    ; R9 := {} , array_size=0, hash_size=4
[0811] newtable  10  0   5    ; R10 := {} , array_size=0, hash_size=5
[0812] settable  10  431 382  ; R10[K175(="AudioBoundingVolume")] := K126(="AudioDinosaurDetail")
[0813] settable  10  432 382  ; R10[K176(="AudioDoppler")] := K126(="AudioDinosaurDetail")
[0814] settable  10  433 382  ; R10[K177(="AudioPosition")] := K126(="AudioDinosaurDetail")
[0815] settable  10  434 382  ; R10[K178(="BoundingVolumeBroadphase")] := K126(="AudioDinosaurDetail")
[0816] settable  10  435 382  ; R10[K179(="Velocity")] := K126(="AudioDinosaurDetail")
[0817] settable  9   430 10   ; R9[K174(="ComponentSources")] := R10
[0818] newtable  10  0   8    ; R10 := {} , array_size=0, hash_size=8
[0819] newtable  11  0   0    ; R11 := {} , array_size=0, hash_size=0
[0820] settable  10  431 11   ; R10[K175(="AudioBoundingVolume")] := R11
[0821] newtable  11  0   1    ; R11 := {} , array_size=0, hash_size=1
[0822] newtable  12  0   1    ; R12 := {} , array_size=0, hash_size=1
[0823] settable  12  437 385  ; R12[K181(="__property")] := K129(="DataStreamEntity")
[0824] settable  11  385 12   ; R11[K129(="DataStreamEntity")] := R12
[0825] settable  10  436 11   ; R10[K180(="AudioDataStream")] := R11
[0826] newtable  11  0   2    ; R11 := {} , array_size=0, hash_size=2
[0827] newtable  12  0   1    ; R12 := {} , array_size=0, hash_size=1
[0828] settable  12  437 383  ; R12[K181(="__property")] := K127(="Core")
[0829] settable  11  383 12   ; R11[K127(="Core")] := R12
[0830] newtable  12  0   1    ; R12 := {} , array_size=0, hash_size=1
[0831] settable  12  437 387  ; R12[K181(="__property")] := K131(="Type")
[0832] settable  11  387 12   ; R11[K131(="Type")] := R12
[0833] settable  10  382 11   ; R10[K126(="AudioDinosaurDetail")] := R11
[0834] newtable  11  0   0    ; R11 := {} , array_size=0, hash_size=0
[0835] settable  10  432 11   ; R10[K176(="AudioDoppler")] := R11
[0836] newtable  11  0   0    ; R11 := {} , array_size=0, hash_size=0
[0837] settable  10  433 11   ; R10[K177(="AudioPosition")] := R11
[0838] newtable  11  0   0    ; R11 := {} , array_size=0, hash_size=0
[0839] settable  10  434 11   ; R10[K178(="BoundingVolumeBroadphase")] := R11
[0840] newtable  11  0   1    ; R11 := {} , array_size=0, hash_size=1
[0841] settable  11  389 498  ; R11[K133(="Rotation")] := K242(=nil)
[0842] settable  10  377 11   ; R10[K121(="Transform")] := R11
[0843] newtable  11  0   0    ; R11 := {} , array_size=0, hash_size=0
[0844] settable  10  435 11   ; R10[K179(="Velocity")] := R11
[0845] settable  9   275 10   ; R9[K19(="Components")] := R10
[0846] newtable  10  0   0    ; R10 := {} , array_size=0, hash_size=0
[0847] settable  9   438 10   ; R9[K182(="IncompleteComponents")] := R10
[0848] newtable  10  0   3    ; R10 := {} , array_size=0, hash_size=3
[0849] newtable  11  0   2    ; R11 := {} , array_size=0, hash_size=2
[0850] settable  11  268 384  ; R11[K12(="Default")] := K128(="../../AudioCore")
[0851] settable  11  387 439  ; R11[K131(="Type")] := K183(="entity")
[0852] settable  10  383 11   ; R10[K127(="Core")] := R11
[0853] newtable  11  0   2    ; R11 := {} , array_size=0, hash_size=2
[0854] settable  11  268 386  ; R11[K12(="Default")] := K130(="../..")
[0855] settable  11  387 439  ; R11[K131(="Type")] := K183(="entity")
[0856] settable  10  385 11   ; R10[K129(="DataStreamEntity")] := R11
[0857] newtable  11  0   3    ; R11 := {} , array_size=0, hash_size=3
[0858] settable  11  268 388  ; R11[K12(="Default")] := K132(="Head")
[0859] settable  11  441 442  ; R11[K185(="Enum")] := K186(="AudioDinosaurType")
[0860] settable  11  387 443  ; R11[K131(="Type")] := K187(="uint8")
[0861] settable  10  387 11   ; R10[K131(="Type")] := R11
[0862] settable  9   266 10   ; R9[K10(="Properties")] := R10
[0863] settable  8   381 9    ; R8[K125(="AudioHead")] := R9
[0864] newtable  9   0   2    ; R9 := {} , array_size=0, hash_size=2
[0865] newtable  10  0   2    ; R10 := {} , array_size=0, hash_size=2
[0866] newtable  11  0   3    ; R11 := {} , array_size=0, hash_size=3
[0867] settable  11  501 386  ; R11[K245(="RootEntityID")] := K130(="../..")
[0868] settable  11  502 386  ; R11[K246(="SpatialEntityID")] := K130(="../..")
[0869] settable  11  503 388  ; R11[K247(="TargetType")] := K132(="Head")
[0870] settable  10  500 11   ; R10[K244(="HeadLookTarget")] := R11
[0871] newtable  11  0   0    ; R11 := {} , array_size=0, hash_size=0
[0872] settable  10  377 11   ; R10[K121(="Transform")] := R11
[0873] settable  9   275 10   ; R9[K19(="Components")] := R10
[0874] newtable  10  0   0    ; R10 := {} , array_size=0, hash_size=0
[0875] settable  9   438 10   ; R9[K182(="IncompleteComponents")] := R10
[0876] settable  8   499 9    ; R8[K243(="HeadlookTarget")] := R9
[0877] newtable  9   0   3    ; R9 := {} , array_size=0, hash_size=3
[0878] newtable  10  0   2    ; R10 := {} , array_size=0, hash_size=2
[0879] settable  10  504 392  ; R10[K248(="DinosaurHeadLookTargetPicker")] := K136(="HeadlookTargetPickerDefender")
[0880] settable  10  377 392  ; R10[K121(="Transform")] := K136(="HeadlookTargetPickerDefender")
[0881] settable  9   430 10   ; R9[K174(="ComponentSources")] := R10
[0882] newtable  10  0   2    ; R10 := {} , array_size=0, hash_size=2
[0883] newtable  11  0   4    ; R11 := {} , array_size=0, hash_size=4
[0884] newtable  12  0   3    ; R12 := {} , array_size=0, hash_size=3
[0885] settable  12  506 507  ; R12[K250(="MaxLookAtDistance")] := K251(=150.0)
[0886] settable  12  508 352  ; R12[K252(="MaxTime")] := K96(=10.0)
[0887] settable  12  509 510  ; R12[K253(="MinTime")] := K254(=8.0)
[0888] settable  11  505 12   ; R11[K249(="AttentionSettings")] := R12
[0889] newtable  12  0   3    ; R12 := {} , array_size=0, hash_size=3
[0890] loadk     13  256      ; R13 := K256(="IdleChance")
[0891] loadk     14  257      ; R14 := K257(=0.5)
[0892] settable  12  13  14   ; R12[R13] := R14
[0893] settable  12  508 510  ; R12[K252(="MaxTime")] := K254(=8.0)
[0894] loadk     13  258      ; R13 := K258(=5.0)
[0895] settable  12  509 13   ; R12[K253(="MinTime")] := R13
[0896] settable  11  511 12   ; R11[K255(="IdleLooking")] := R12
[0897] loadk     12  259      ; R12 := K259(="OldTargetsScorePenalty")
[0898] newtable  13  4   0    ; R13 := {} , array_size=4, hash_size=0
[0899] loadk     14  260      ; R14 := K260(=0.4)
[0900] loadk     15  88       ; R15 := K88(=0.3)
[0901] loadk     16  261      ; R16 := K261(=0.2)
[0902] loadk     17  25       ; R17 := K25(=0.1)
[0903] setlist   13  4   1    ; R13[1 to 4] := R14 to R17
[0904] settable  11  12  13   ; R11[R12] := R13
[0905] loadk     12  262      ; R12 := K262(="TargetPicking")
[0906] newtable  13  0   7    ; R13 := {} , array_size=0, hash_size=7
[0907] loadk     14  263      ; R14 := K263(="CrowdLookAtTargetSetting")
[0908] newtable  15  0   2    ; R15 := {} , array_size=0, hash_size=2
[0909] loadk     16  264      ; R16 := K264(="ScorePerPerson")
[0910] settable  15  16  281  ; R15[R16] := K25(=0.1)
[0911] loadk     16  265      ; R16 := K265(="SpatialQueryFlags")
[0912] newtable  17  1   0    ; R17 := {} , array_size=1, hash_size=0
[0913] loadk     18  266      ; R18 := K266(="path")
[0914] setlist   17  1   1    ; R17[1 to 1] := R18 to R18
[0915] settable  15  16  17   ; R15[R16] := R17
[0916] settable  13  14  15   ; R13[R14] := R15
[0917] loadk     14  267      ; R14 := K267(="DinosaurLookAtTargetSetting")
[0918] newtable  15  0   1    ; R15 := {} , array_size=0, hash_size=1
[0919] loadk     16  265      ; R16 := K265(="SpatialQueryFlags")
[0920] newtable  17  1   0    ; R17 := {} , array_size=1, hash_size=0
[0921] loadk     18  268      ; R18 := K268(="dinosaur")
[0922] setlist   17  1   1    ; R17[1 to 1] := R18 to R18
[0923] settable  15  16  17   ; R15[R16] := R17
[0924] settable  13  14  15   ; R13[R14] := R15
[0925] loadk     14  269      ; R14 := K269(="FlareLookAtTargetSetting")
[0926] newtable  15  0   1    ; R15 := {} , array_size=0, hash_size=1
[0927] loadk     16  265      ; R16 := K265(="SpatialQueryFlags")
[0928] newtable  17  1   0    ; R17 := {} , array_size=1, hash_size=0
[0929] loadk     18  270      ; R18 := K270(="flare")
[0930] setlist   17  1   1    ; R17[1 to 1] := R18 to R18
[0931] settable  15  16  17   ; R15[R16] := R17
[0932] settable  13  14  15   ; R13[R14] := R15
[0933] loadk     14  271      ; R14 := K271(="ScoreMinimum")
[0934] loadk     15  257      ; R15 := K257(=0.5)
[0935] settable  13  14  15   ; R13[R14] := R15
[0936] loadk     14  265      ; R14 := K265(="SpatialQueryFlags")
[0937] newtable  15  8   0    ; R15 := {} , array_size=8, hash_size=0
[0938] loadk     16  272      ; R16 := K272(="tree")
[0939] loadk     17  273      ; R17 := K273(="buildingmodule")
[0940] loadk     18  274      ; R18 := K274(="powercable")
[0941] loadk     19  275      ; R19 := K275(="dinosaurgoalpoint_food_meat")
[0942] loadk     20  276      ; R20 := K276(="dinosaurgoalpoint_food_lowherb")
[0943] loadk     21  277      ; R21 := K277(="dinosaurgoalpoint_food_highherb")
[0944] loadk     22  278      ; R22 := K278(="power_transmittor")
[0945] loadk     23  279      ; R23 := K279(="gate_open")
[0946] setlist   15  8   1    ; R15[1 to 8] := R16 to R23
[0947] settable  13  14  15   ; R13[R14] := R15
[0948] loadk     14  280      ; R14 := K280(="SpatialQuerySphereRadius")
[0949] settable  13  14  335  ; R13[R14] := K79(=100.0)
[0950] loadk     14  281      ; R14 := K281(="VehiclesLookAtTargetSetting")
[0951] newtable  15  0   1    ; R15 := {} , array_size=0, hash_size=1
[0952] loadk     16  265      ; R16 := K265(="SpatialQueryFlags")
[0953] newtable  17  1   0    ; R17 := {} , array_size=1, hash_size=0
[0954] loadk     18  282      ; R18 := K282(="vehicle")
[0955] setlist   17  1   1    ; R17[1 to 1] := R18 to R18
[0956] settable  15  16  17   ; R15[R16] := R17
[0957] settable  13  14  15   ; R13[R14] := R15
[0958] settable  11  12  13   ; R11[R12] := R13
[0959] settable  10  504 11   ; R10[K248(="DinosaurHeadLookTargetPicker")] := R11
[0960] newtable  11  0   0    ; R11 := {} , array_size=0, hash_size=0
[0961] settable  10  377 11   ; R10[K121(="Transform")] := R11
[0962] settable  9   275 10   ; R9[K19(="Components")] := R10
[0963] newtable  10  0   0    ; R10 := {} , array_size=0, hash_size=0
[0964] settable  9   438 10   ; R9[K182(="IncompleteComponents")] := R10
[0965] settable  8   391 9    ; R8[K135(="HeadlookTargetPicker")] := R9
[0966] loadk     9   283      ; R9 := K283(="InterestingEventSpawner")
[0967] newtable  10  0   2    ; R10 := {} , array_size=0, hash_size=2
[0968] newtable  11  0   2    ; R11 := {} , array_size=0, hash_size=2
[0969] loadk     12  284      ; R12 := K284(="CrowdInterestingEventSpawner")
[0970] newtable  13  0   6    ; R13 := {} , array_size=0, hash_size=6
[0971] loadk     14  285      ; R14 := K285(="InterestingEventSettings")
[0972] newtable  15  0   1    ; R15 := {} , array_size=0, hash_size=1
[0973] loadk     16  286      ; R16 := K286(="SourceBoundRadius")
[0974] settable  15  16  320  ; R15[R16] := K64(=30.0)
[0975] settable  13  14  15   ; R13[R14] := R15
[0976] loadk     14  287      ; R14 := K287(="PhysicsRaycastFlagName")
[0977] newtable  15  6   0    ; R15 := {} , array_size=6, hash_size=0
[0978] newtable  16  0   1    ; R16 := {} , array_size=0, hash_size=1
[0979] loadk     17  288      ; R17 := K288(="Flag")
[0980] loadk     18  289      ; R18 := K289(="Landscape")
[0981] settable  16  17  18   ; R16[R17] := R18
[0982] newtable  17  0   1    ; R17 := {} , array_size=0, hash_size=1
[0983] loadk     18  288      ; R18 := K288(="Flag")
[0984] loadk     19  290      ; R19 := K290(="Foliage")
[0985] settable  17  18  19   ; R17[R18] := R19
[0986] newtable  18  0   1    ; R18 := {} , array_size=0, hash_size=1
[0987] loadk     19  288      ; R19 := K288(="Flag")
[0988] loadk     20  291      ; R20 := K291(="Building")
[0989] settable  18  19  20   ; R18[R19] := R20
[0990] newtable  19  0   1    ; R19 := {} , array_size=0, hash_size=1
[0991] loadk     20  288      ; R20 := K288(="Flag")
[0992] loadk     21  292      ; R21 := K292(="Wall")
[0993] settable  19  20  21   ; R19[R20] := R21
[0994] newtable  20  0   1    ; R20 := {} , array_size=0, hash_size=1
[0995] loadk     21  288      ; R21 := K288(="Flag")
[0996] loadk     22  293      ; R22 := K293(="Pylon")
[0997] settable  20  21  22   ; R20[R21] := R22
[0998] newtable  21  0   1    ; R21 := {} , array_size=0, hash_size=1
[0999] loadk     22  288      ; R22 := K288(="Flag")
[1000] loadk     23  294      ; R23 := K294(="Track")
[1001] settable  21  22  23   ; R21[R22] := R23
[1002] setlist   15  6   1    ; R15[1 to 6] := R16 to R21
[1003] settable  13  14  15   ; R13[R14] := R15
[1004] loadk     14  295      ; R14 := K295(="QueryInterval")
[1005] settable  13  14  290  ; R13[R14] := K34(=20.0)
[1006] settable  13  501 386  ; R13[K245(="RootEntityID")] := K130(="../..")
[1007] loadk     14  296      ; R14 := K296(="TriggerRadius")
[1008] settable  13  14  335  ; R13[R14] := K79(=100.0)
[1009] loadk     14  297      ; R14 := K297(="TriggerSpatialFlag")
[1010] newtable  15  1   0    ; R15 := {} , array_size=1, hash_size=0
[1011] loadk     16  266      ; R16 := K266(="path")
[1012] setlist   15  1   1    ; R15[1 to 1] := R16 to R16
[1013] settable  13  14  15   ; R13[R14] := R15
[1014] settable  11  12  13   ; R11[R12] := R13
[1015] newtable  12  0   0    ; R12 := {} , array_size=0, hash_size=0
[1016] settable  11  377 12   ; R11[K121(="Transform")] := R12
[1017] settable  10  275 11   ; R10[K19(="Components")] := R11
[1018] newtable  11  0   0    ; R11 := {} , array_size=0, hash_size=0
[1019] settable  10  438 11   ; R10[K182(="IncompleteComponents")] := R11
[1020] settable  8   9   10   ; R8[R9] := R10
[1021] newtable  9   0   2    ; R9 := {} , array_size=0, hash_size=2
[1022] newtable  10  0   3    ; R10 := {} , array_size=0, hash_size=3
[1023] newtable  11  0   1    ; R11 := {} , array_size=0, hash_size=1
[1024] settable  11  395 386  ; R11[K139(="Parent")] := K130(="../..")
[1025] settable  10  394 11   ; R10[K138(="ParticleSelector")] := R11
[1026] newtable  11  0   1    ; R11 := {} , array_size=0, hash_size=1
[1027] settable  11  385 386  ; R11[K129(="DataStreamEntity")] := K130(="../..")
[1028] settable  10  396 11   ; R10[K140(="ParticleTrigger")] := R11
[1029] newtable  11  0   3    ; R11 := {} , array_size=0, hash_size=3
[1030] settable  11  397 398  ; R11[K141(="Position")] := K142(=nil)
[1031] settable  11  389 398  ; R11[K133(="Rotation")] := K142(=nil)
[1032] settable  11  399 400  ; R11[K143(="Scale")] := K144(=1.0)
[1033] settable  10  377 11   ; R10[K121(="Transform")] := R11
[1034] settable  9   275 10   ; R9[K19(="Components")] := R10
[1035] newtable  10  0   0    ; R10 := {} , array_size=0, hash_size=0
[1036] settable  9   438 10   ; R9[K182(="IncompleteComponents")] := R10
[1037] settable  8   393 9    ; R8[K137(="VFX_Fence_Impact")] := R9
[1038] settable  7   364 8    ; R7[K108(="Children")] := R8
[1039] newtable  8   0   1    ; R8 := {} , array_size=0, hash_size=1
[1040] loadk     9   298      ; R9 := K298(="DinosaurBase/def_c_head_joint")
[1041] settable  8   377 9    ; R8[K121(="Transform")] := R9
[1042] settable  7   430 8    ; R7[K174(="ComponentSources")] := R8
[1043] newtable  8   0   2    ; R8 := {} , array_size=0, hash_size=2
[1044] newtable  9   0   2    ; R9 := {} , array_size=0, hash_size=2
[1045] settable  9   376 371  ; R9[K120(="AnimEntity")] := K115(="..")
[1046] settable  9   297 307  ; R9[K41(="BoneName")] := K51(="def_c_head_joint")
[1047] settable  8   375 9    ; R8[K119(="BoneTransform")] := R9
[1048] newtable  9   0   0    ; R9 := {} , array_size=0, hash_size=0
[1049] settable  8   377 9    ; R8[K121(="Transform")] := R9
[1050] settable  7   275 8    ; R7[K19(="Components")] := R8
[1051] newtable  8   0   0    ; R8 := {} , array_size=0, hash_size=0
[1052] settable  7   438 8    ; R7[K182(="IncompleteComponents")] := R8
[1053] settable  6   307 7    ; R6[K51(="def_c_head_joint")] := R7
[1054] loadk     7   299      ; R7 := K299(="def_c_root_joint")
[1055] newtable  8   0   2    ; R8 := {} , array_size=0, hash_size=2
[1056] newtable  9   0   2    ; R9 := {} , array_size=0, hash_size=2
[1057] newtable  10  0   2    ; R10 := {} , array_size=0, hash_size=2
[1058] settable  10  376 371  ; R10[K120(="AnimEntity")] := K115(="..")
[1059] loadk     11  299      ; R11 := K299(="def_c_root_joint")
[1060] settable  10  297 11   ; R10[K41(="BoneName")] := R11
[1061] settable  9   375 10   ; R9[K119(="BoneTransform")] := R10
[1062] newtable  10  0   0    ; R10 := {} , array_size=0, hash_size=0
[1063] settable  9   377 10   ; R9[K121(="Transform")] := R10
[1064] settable  8   275 9    ; R8[K19(="Components")] := R9
[1065] newtable  9   0   0    ; R9 := {} , array_size=0, hash_size=0
[1066] settable  8   438 9    ; R8[K182(="IncompleteComponents")] := R9
[1067] settable  6   7   8    ; R6[R7] := R8
[1068] newtable  7   0   3    ; R7 := {} , array_size=0, hash_size=3
[1069] newtable  8   0   1    ; R8 := {} , array_size=0, hash_size=1
[1070] newtable  9   0   4    ; R9 := {} , array_size=0, hash_size=4
[1071] newtable  10  0   6    ; R10 := {} , array_size=0, hash_size=6
[1072] settable  10  431 378  ; R10[K175(="AudioBoundingVolume")] := K122(="AudioDinosaurRagdoll")
[1073] settable  10  432 492  ; R10[K176(="AudioDoppler")] := K236(="AudioEmitter")
[1074] settable  10  433 492  ; R10[K177(="AudioPosition")] := K236(="AudioEmitter")
[1075] settable  10  434 378  ; R10[K178(="BoundingVolumeBroadphase")] := K122(="AudioDinosaurRagdoll")
[1076] settable  10  377 492  ; R10[K121(="Transform")] := K236(="AudioEmitter")
[1077] settable  10  435 492  ; R10[K179(="Velocity")] := K236(="AudioEmitter")
[1078] settable  9   430 10   ; R9[K174(="ComponentSources")] := R10
[1079] newtable  10  0   7    ; R10 := {} , array_size=0, hash_size=7
[1080] newtable  11  0   0    ; R11 := {} , array_size=0, hash_size=0
[1081] settable  10  431 11   ; R10[K175(="AudioBoundingVolume")] := R11
[1082] newtable  11  0   4    ; R11 := {} , array_size=0, hash_size=4
[1083] newtable  12  0   1    ; R12 := {} , array_size=0, hash_size=1
[1084] settable  12  437 379  ; R12[K181(="__property")] := K123(="CaptureRadius")
[1085] settable  11  379 12   ; R11[K123(="CaptureRadius")] := R12
[1086] newtable  12  0   1    ; R12 := {} , array_size=0, hash_size=1
[1087] settable  12  437 370  ; R12[K181(="__property")] := K114(="RootEntity")
[1088] settable  11  370 12   ; R11[K114(="RootEntity")] := R12
[1089] newtable  12  0   1    ; R12 := {} , array_size=0, hash_size=1
[1090] settable  12  437 387  ; R12[K181(="__property")] := K131(="Type")
[1091] settable  11  387 12   ; R11[K131(="Type")] := R12
[1092] newtable  12  0   1    ; R12 := {} , array_size=0, hash_size=1
[1093] settable  12  437 493  ; R12[K181(="__property")] := K237(="WeightType")
[1094] settable  11  493 12   ; R11[K237(="WeightType")] := R12
[1095] settable  10  378 11   ; R10[K122(="AudioDinosaurRagdoll")] := R11
[1096] newtable  11  0   0    ; R11 := {} , array_size=0, hash_size=0
[1097] settable  10  432 11   ; R10[K176(="AudioDoppler")] := R11
[1098] newtable  11  0   0    ; R11 := {} , array_size=0, hash_size=0
[1099] settable  10  433 11   ; R10[K177(="AudioPosition")] := R11
[1100] newtable  11  0   0    ; R11 := {} , array_size=0, hash_size=0
[1101] settable  10  434 11   ; R10[K178(="BoundingVolumeBroadphase")] := R11
[1102] newtable  11  0   0    ; R11 := {} , array_size=0, hash_size=0
[1103] settable  10  377 11   ; R10[K121(="Transform")] := R11
[1104] newtable  11  0   0    ; R11 := {} , array_size=0, hash_size=0
[1105] settable  10  435 11   ; R10[K179(="Velocity")] := R11
[1106] settable  9   275 10   ; R9[K19(="Components")] := R10
[1107] newtable  10  0   0    ; R10 := {} , array_size=0, hash_size=0
[1108] settable  9   438 10   ; R9[K182(="IncompleteComponents")] := R10
[1109] newtable  10  0   4    ; R10 := {} , array_size=0, hash_size=4
[1110] newtable  11  0   2    ; R11 := {} , array_size=0, hash_size=2
[1111] settable  11  268 360  ; R11[K12(="Default")] := K104(=2.5)
[1112] settable  11  387 494  ; R11[K131(="Type")] := K238(="float")
[1113] settable  10  379 11   ; R10[K123(="CaptureRadius")] := R11
[1114] newtable  11  0   2    ; R11 := {} , array_size=0, hash_size=2
[1115] settable  11  268 386  ; R11[K12(="Default")] := K130(="../..")
[1116] settable  11  387 439  ; R11[K131(="Type")] := K183(="entity")
[1117] settable  10  370 11   ; R10[K114(="RootEntity")] := R11
[1118] newtable  11  0   4    ; R11 := {} , array_size=0, hash_size=4
[1119] settable  11  268 495  ; R11[K12(="Default")] := K239(="BodyFront")
[1120] settable  11  441 496  ; R11[K185(="Enum")] := K240(="AudioDinosaurRagdollType")
[1121] settable  11  447 446  ; R11[K191(="Optional")] := K190(=false)
[1122] settable  11  387 443  ; R11[K131(="Type")] := K187(="uint8")
[1123] settable  10  387 11   ; R10[K131(="Type")] := R11
[1124] newtable  11  0   4    ; R11 := {} , array_size=0, hash_size=4
[1125] settable  11  268 293  ; R11[K12(="Default")] := K37(="Medium")
[1126] settable  11  441 497  ; R11[K185(="Enum")] := K241(="AudioDinosaurRagdollWeight")
[1127] settable  11  447 446  ; R11[K191(="Optional")] := K190(=false)
[1128] settable  11  387 443  ; R11[K131(="Type")] := K187(="uint8")
[1129] settable  10  493 11   ; R10[K237(="WeightType")] := R11
[1130] settable  9   266 10   ; R9[K10(="Properties")] := R10
[1131] settable  8   378 9    ; R8[K122(="AudioDinosaurRagdoll")] := R9
[1132] settable  7   364 8    ; R7[K108(="Children")] := R8
[1133] newtable  8   0   2    ; R8 := {} , array_size=0, hash_size=2
[1134] newtable  9   0   2    ; R9 := {} , array_size=0, hash_size=2
[1135] settable  9   376 371  ; R9[K120(="AnimEntity")] := K115(="..")
[1136] settable  9   297 401  ; R9[K41(="BoneName")] := K145(="def_c_spine01_joint")
[1137] settable  8   375 9    ; R8[K119(="BoneTransform")] := R9
[1138] newtable  9   0   0    ; R9 := {} , array_size=0, hash_size=0
[1139] settable  8   377 9    ; R8[K121(="Transform")] := R9
[1140] settable  7   275 8    ; R7[K19(="Components")] := R8
[1141] newtable  8   0   0    ; R8 := {} , array_size=0, hash_size=0
[1142] settable  7   438 8    ; R7[K182(="IncompleteComponents")] := R8
[1143] settable  6   401 7    ; R6[K145(="def_c_spine01_joint")] := R7
[1144] newtable  7   0   3    ; R7 := {} , array_size=0, hash_size=3
[1145] newtable  8   0   2    ; R8 := {} , array_size=0, hash_size=2
[1146] newtable  9   0   4    ; R9 := {} , array_size=0, hash_size=4
[1147] newtable  10  0   6    ; R10 := {} , array_size=0, hash_size=6
[1148] settable  10  431 378  ; R10[K175(="AudioBoundingVolume")] := K122(="AudioDinosaurRagdoll")
[1149] settable  10  432 492  ; R10[K176(="AudioDoppler")] := K236(="AudioEmitter")
[1150] settable  10  433 492  ; R10[K177(="AudioPosition")] := K236(="AudioEmitter")
[1151] settable  10  434 378  ; R10[K178(="BoundingVolumeBroadphase")] := K122(="AudioDinosaurRagdoll")
[1152] settable  10  377 492  ; R10[K121(="Transform")] := K236(="AudioEmitter")
[1153] settable  10  435 492  ; R10[K179(="Velocity")] := K236(="AudioEmitter")
[1154] settable  9   430 10   ; R9[K174(="ComponentSources")] := R10
[1155] newtable  10  0   7    ; R10 := {} , array_size=0, hash_size=7
[1156] newtable  11  0   0    ; R11 := {} , array_size=0, hash_size=0
[1157] settable  10  431 11   ; R10[K175(="AudioBoundingVolume")] := R11
[1158] newtable  11  0   4    ; R11 := {} , array_size=0, hash_size=4
[1159] newtable  12  0   1    ; R12 := {} , array_size=0, hash_size=1
[1160] settable  12  437 379  ; R12[K181(="__property")] := K123(="CaptureRadius")
[1161] settable  11  379 12   ; R11[K123(="CaptureRadius")] := R12
[1162] newtable  12  0   1    ; R12 := {} , array_size=0, hash_size=1
[1163] settable  12  437 370  ; R12[K181(="__property")] := K114(="RootEntity")
[1164] settable  11  370 12   ; R11[K114(="RootEntity")] := R12
[1165] newtable  12  0   1    ; R12 := {} , array_size=0, hash_size=1
[1166] settable  12  437 387  ; R12[K181(="__property")] := K131(="Type")
[1167] settable  11  387 12   ; R11[K131(="Type")] := R12
[1168] newtable  12  0   1    ; R12 := {} , array_size=0, hash_size=1
[1169] settable  12  437 493  ; R12[K181(="__property")] := K237(="WeightType")
[1170] settable  11  493 12   ; R11[K237(="WeightType")] := R12
[1171] settable  10  378 11   ; R10[K122(="AudioDinosaurRagdoll")] := R11
[1172] newtable  11  0   0    ; R11 := {} , array_size=0, hash_size=0
[1173] settable  10  432 11   ; R10[K176(="AudioDoppler")] := R11
[1174] newtable  11  0   0    ; R11 := {} , array_size=0, hash_size=0
[1175] settable  10  433 11   ; R10[K177(="AudioPosition")] := R11
[1176] newtable  11  0   0    ; R11 := {} , array_size=0, hash_size=0
[1177] settable  10  434 11   ; R10[K178(="BoundingVolumeBroadphase")] := R11
[1178] newtable  11  0   0    ; R11 := {} , array_size=0, hash_size=0
[1179] settable  10  377 11   ; R10[K121(="Transform")] := R11
[1180] newtable  11  0   0    ; R11 := {} , array_size=0, hash_size=0
[1181] settable  10  435 11   ; R10[K179(="Velocity")] := R11
[1182] settable  9   275 10   ; R9[K19(="Components")] := R10
[1183] newtable  10  0   0    ; R10 := {} , array_size=0, hash_size=0
[1184] settable  9   438 10   ; R9[K182(="IncompleteComponents")] := R10
[1185] newtable  10  0   4    ; R10 := {} , array_size=0, hash_size=4
[1186] newtable  11  0   2    ; R11 := {} , array_size=0, hash_size=2
[1187] settable  11  268 400  ; R11[K12(="Default")] := K144(=1.0)
[1188] settable  11  387 494  ; R11[K131(="Type")] := K238(="float")
[1189] settable  10  379 11   ; R10[K123(="CaptureRadius")] := R11
[1190] newtable  11  0   2    ; R11 := {} , array_size=0, hash_size=2
[1191] settable  11  268 386  ; R11[K12(="Default")] := K130(="../..")
[1192] settable  11  387 439  ; R11[K131(="Type")] := K183(="entity")
[1193] settable  10  370 11   ; R10[K114(="RootEntity")] := R11
[1194] newtable  11  0   4    ; R11 := {} , array_size=0, hash_size=4
[1195] settable  11  268 403  ; R11[K12(="Default")] := K147(="Tail")
[1196] settable  11  441 496  ; R11[K185(="Enum")] := K240(="AudioDinosaurRagdollType")
[1197] settable  11  447 446  ; R11[K191(="Optional")] := K190(=false)
[1198] settable  11  387 443  ; R11[K131(="Type")] := K187(="uint8")
[1199] settable  10  387 11   ; R10[K131(="Type")] := R11
[1200] newtable  11  0   4    ; R11 := {} , array_size=0, hash_size=4
[1201] settable  11  268 293  ; R11[K12(="Default")] := K37(="Medium")
[1202] settable  11  441 497  ; R11[K185(="Enum")] := K241(="AudioDinosaurRagdollWeight")
[1203] settable  11  447 446  ; R11[K191(="Optional")] := K190(=false)
[1204] settable  11  387 443  ; R11[K131(="Type")] := K187(="uint8")
[1205] settable  10  493 11   ; R10[K237(="WeightType")] := R11
[1206] settable  9   266 10   ; R9[K10(="Properties")] := R10
[1207] settable  8   378 9    ; R8[K122(="AudioDinosaurRagdoll")] := R9
[1208] newtable  9   0   4    ; R9 := {} , array_size=0, hash_size=4
[1209] newtable  10  0   6    ; R10 := {} , array_size=0, hash_size=6
[1210] settable  10  431 382  ; R10[K175(="AudioBoundingVolume")] := K126(="AudioDinosaurDetail")
[1211] settable  10  432 382  ; R10[K176(="AudioDoppler")] := K126(="AudioDinosaurDetail")
[1212] settable  10  433 382  ; R10[K177(="AudioPosition")] := K126(="AudioDinosaurDetail")
[1213] settable  10  434 382  ; R10[K178(="BoundingVolumeBroadphase")] := K126(="AudioDinosaurDetail")
[1214] settable  10  377 382  ; R10[K121(="Transform")] := K126(="AudioDinosaurDetail")
[1215] settable  10  435 382  ; R10[K179(="Velocity")] := K126(="AudioDinosaurDetail")
[1216] settable  9   430 10   ; R9[K174(="ComponentSources")] := R10
[1217] newtable  10  0   8    ; R10 := {} , array_size=0, hash_size=8
[1218] newtable  11  0   0    ; R11 := {} , array_size=0, hash_size=0
[1219] settable  10  431 11   ; R10[K175(="AudioBoundingVolume")] := R11
[1220] newtable  11  0   1    ; R11 := {} , array_size=0, hash_size=1
[1221] newtable  12  0   1    ; R12 := {} , array_size=0, hash_size=1
[1222] settable  12  437 385  ; R12[K181(="__property")] := K129(="DataStreamEntity")
[1223] settable  11  385 12   ; R11[K129(="DataStreamEntity")] := R12
[1224] settable  10  436 11   ; R10[K180(="AudioDataStream")] := R11
[1225] newtable  11  0   2    ; R11 := {} , array_size=0, hash_size=2
[1226] newtable  12  0   1    ; R12 := {} , array_size=0, hash_size=1
[1227] settable  12  437 383  ; R12[K181(="__property")] := K127(="Core")
[1228] settable  11  383 12   ; R11[K127(="Core")] := R12
[1229] newtable  12  0   1    ; R12 := {} , array_size=0, hash_size=1
[1230] settable  12  437 387  ; R12[K181(="__property")] := K131(="Type")
[1231] settable  11  387 12   ; R11[K131(="Type")] := R12
[1232] settable  10  382 11   ; R10[K126(="AudioDinosaurDetail")] := R11
[1233] newtable  11  0   0    ; R11 := {} , array_size=0, hash_size=0
[1234] settable  10  432 11   ; R10[K176(="AudioDoppler")] := R11
[1235] newtable  11  0   0    ; R11 := {} , array_size=0, hash_size=0
[1236] settable  10  433 11   ; R10[K177(="AudioPosition")] := R11
[1237] newtable  11  0   0    ; R11 := {} , array_size=0, hash_size=0
[1238] settable  10  434 11   ; R10[K178(="BoundingVolumeBroadphase")] := R11
[1239] newtable  11  0   0    ; R11 := {} , array_size=0, hash_size=0
[1240] settable  10  377 11   ; R10[K121(="Transform")] := R11
[1241] newtable  11  0   0    ; R11 := {} , array_size=0, hash_size=0
[1242] settable  10  435 11   ; R10[K179(="Velocity")] := R11
[1243] settable  9   275 10   ; R9[K19(="Components")] := R10
[1244] newtable  10  0   0    ; R10 := {} , array_size=0, hash_size=0
[1245] settable  9   438 10   ; R9[K182(="IncompleteComponents")] := R10
[1246] newtable  10  0   3    ; R10 := {} , array_size=0, hash_size=3
[1247] newtable  11  0   2    ; R11 := {} , array_size=0, hash_size=2
[1248] settable  11  268 384  ; R11[K12(="Default")] := K128(="../../AudioCore")
[1249] settable  11  387 439  ; R11[K131(="Type")] := K183(="entity")
[1250] settable  10  383 11   ; R10[K127(="Core")] := R11
[1251] newtable  11  0   2    ; R11 := {} , array_size=0, hash_size=2
[1252] settable  11  268 386  ; R11[K12(="Default")] := K130(="../..")
[1253] settable  11  387 439  ; R11[K131(="Type")] := K183(="entity")
[1254] settable  10  385 11   ; R10[K129(="DataStreamEntity")] := R11
[1255] newtable  11  0   3    ; R11 := {} , array_size=0, hash_size=3
[1256] settable  11  268 403  ; R11[K12(="Default")] := K147(="Tail")
[1257] settable  11  441 442  ; R11[K185(="Enum")] := K186(="AudioDinosaurType")
[1258] settable  11  387 443  ; R11[K131(="Type")] := K187(="uint8")
[1259] settable  10  387 11   ; R10[K131(="Type")] := R11
[1260] settable  9   266 10   ; R9[K10(="Properties")] := R10
[1261] settable  8   404 9    ; R8[K148(="AudioTail")] := R9
[1262] settable  7   364 8    ; R7[K108(="Children")] := R8
[1263] newtable  8   0   2    ; R8 := {} , array_size=0, hash_size=2
[1264] newtable  9   0   2    ; R9 := {} , array_size=0, hash_size=2
[1265] settable  9   376 371  ; R9[K120(="AnimEntity")] := K115(="..")
[1266] settable  9   297 402  ; R9[K41(="BoneName")] := K146(="def_c_tail05_joint")
[1267] settable  8   375 9    ; R8[K119(="BoneTransform")] := R9
[1268] newtable  9   0   0    ; R9 := {} , array_size=0, hash_size=0
[1269] settable  8   377 9    ; R8[K121(="Transform")] := R9
[1270] settable  7   275 8    ; R7[K19(="Components")] := R8
[1271] newtable  8   0   0    ; R8 := {} , array_size=0, hash_size=0
[1272] settable  7   438 8    ; R7[K182(="IncompleteComponents")] := R8
[1273] settable  6   402 7    ; R6[K146(="def_c_tail05_joint")] := R7
[1274] newtable  7   0   3    ; R7 := {} , array_size=0, hash_size=3
[1275] newtable  8   0   1    ; R8 := {} , array_size=0, hash_size=1
[1276] newtable  9   0   2    ; R9 := {} , array_size=0, hash_size=2
[1277] newtable  10  0   4    ; R10 := {} , array_size=0, hash_size=4
[1278] newtable  11  0   1    ; R11 := {} , array_size=0, hash_size=1
[1279] settable  11  408 386  ; R11[K152(="LoaderPath")] := K130(="../..")
[1280] settable  10  407 11   ; R10[K151(="AssetPackageProvider")] := R11
[1281] newtable  11  0   1    ; R11 := {} , array_size=0, hash_size=1
[1282] settable  11  410 411  ; R11[K154(="ParticleName")] := K155(="NERO_DF_Triceratops_Fall_Impact")
[1283] settable  10  409 11   ; R10[K153(="Particle")] := R11
[1284] newtable  11  0   1    ; R11 := {} , array_size=0, hash_size=1
[1285] settable  11  385 386  ; R11[K129(="DataStreamEntity")] := K130(="../..")
[1286] settable  10  396 11   ; R10[K140(="ParticleTrigger")] := R11
[1287] newtable  11  0   0    ; R11 := {} , array_size=0, hash_size=0
[1288] settable  10  377 11   ; R10[K121(="Transform")] := R11
[1289] settable  9   275 10   ; R9[K19(="Components")] := R10
[1290] newtable  10  0   0    ; R10 := {} , array_size=0, hash_size=0
[1291] settable  9   438 10   ; R9[K182(="IncompleteComponents")] := R10
[1292] settable  8   406 9    ; R8[K150(="VFX_Fall_Impact")] := R9
[1293] settable  7   364 8    ; R7[K108(="Children")] := R8
[1294] newtable  8   0   2    ; R8 := {} , array_size=0, hash_size=2
[1295] newtable  9   0   2    ; R9 := {} , array_size=0, hash_size=2
[1296] settable  9   376 371  ; R9[K120(="AnimEntity")] := K115(="..")
[1297] settable  9   297 405  ; R9[K41(="BoneName")] := K149(="def_l_frontLeglwr_joint")
[1298] settable  8   375 9    ; R8[K119(="BoneTransform")] := R9
[1299] newtable  9   0   0    ; R9 := {} , array_size=0, hash_size=0
[1300] settable  8   377 9    ; R8[K121(="Transform")] := R9
[1301] settable  7   275 8    ; R7[K19(="Components")] := R8
[1302] newtable  8   0   0    ; R8 := {} , array_size=0, hash_size=0
[1303] settable  7   438 8    ; R7[K182(="IncompleteComponents")] := R8
[1304] settable  6   405 7    ; R6[K149(="def_l_frontLeglwr_joint")] := R7
[1305] newtable  7   0   3    ; R7 := {} , array_size=0, hash_size=3
[1306] newtable  8   0   1    ; R8 := {} , array_size=0, hash_size=1
[1307] newtable  9   0   2    ; R9 := {} , array_size=0, hash_size=2
[1308] newtable  10  0   4    ; R10 := {} , array_size=0, hash_size=4
[1309] newtable  11  0   1    ; R11 := {} , array_size=0, hash_size=1
[1310] settable  11  408 386  ; R11[K152(="LoaderPath")] := K130(="../..")
[1311] settable  10  407 11   ; R10[K151(="AssetPackageProvider")] := R11
[1312] newtable  11  0   1    ; R11 := {} , array_size=0, hash_size=1
[1313] settable  11  410 411  ; R11[K154(="ParticleName")] := K155(="NERO_DF_Triceratops_Fall_Impact")
[1314] settable  10  409 11   ; R10[K153(="Particle")] := R11
[1315] newtable  11  0   1    ; R11 := {} , array_size=0, hash_size=1
[1316] settable  11  385 386  ; R11[K129(="DataStreamEntity")] := K130(="../..")
[1317] settable  10  396 11   ; R10[K140(="ParticleTrigger")] := R11
[1318] newtable  11  0   0    ; R11 := {} , array_size=0, hash_size=0
[1319] settable  10  377 11   ; R10[K121(="Transform")] := R11
[1320] settable  9   275 10   ; R9[K19(="Components")] := R10
[1321] newtable  10  0   0    ; R10 := {} , array_size=0, hash_size=0
[1322] settable  9   438 10   ; R9[K182(="IncompleteComponents")] := R10
[1323] settable  8   413 9    ; R8[K157(="VFX_Fall_Impact_02")] := R9
[1324] settable  7   364 8    ; R7[K108(="Children")] := R8
[1325] newtable  8   0   2    ; R8 := {} , array_size=0, hash_size=2
[1326] newtable  9   0   2    ; R9 := {} , array_size=0, hash_size=2
[1327] settable  9   376 371  ; R9[K120(="AnimEntity")] := K115(="..")
[1328] settable  9   297 412  ; R9[K41(="BoneName")] := K156(="def_l_frontLegupr_joint")
[1329] settable  8   375 9    ; R8[K119(="BoneTransform")] := R9
[1330] newtable  9   0   0    ; R9 := {} , array_size=0, hash_size=0
[1331] settable  8   377 9    ; R8[K121(="Transform")] := R9
[1332] settable  7   275 8    ; R7[K19(="Components")] := R8
[1333] newtable  8   0   0    ; R8 := {} , array_size=0, hash_size=0
[1334] settable  7   438 8    ; R7[K182(="IncompleteComponents")] := R8
[1335] settable  6   412 7    ; R6[K156(="def_l_frontLegupr_joint")] := R7
[1336] settable  5   364 6    ; R5[K108(="Children")] := R6
[1337] newtable  6   0   26   ; R6 := {} , array_size=0, hash_size=40
[1338] loadk     7   300      ; R7 := K300(="AmenityProvider")
[1339] settable  6   7   265  ; R6[R7] := K9(="DinosaurBase")
[1340] loadk     7   301      ; R7 := K301(="Animation")
[1341] settable  6   7   265  ; R6[R7] := K9(="DinosaurBase")
[1342] settable  6   407 265  ; R6[K151(="AssetPackageProvider")] := K9(="DinosaurBase")
[1343] loadk     7   302      ; R7 := K302(="AssetPackageStream")
[1344] settable  6   7   265  ; R6[R7] := K9(="DinosaurBase")
[1345] loadk     7   303      ; R7 := K303(="BehaviourTreeAgent")
[1346] settable  6   7   265  ; R6[R7] := K9(="DinosaurBase")
[1347] settable  6   434 265  ; R6[K178(="BoundingVolumeBroadphase")] := K9(="DinosaurBase")
[1348] loadk     7   304      ; R7 := K304(="Coordination")
[1349] settable  6   7   265  ; R6[R7] := K9(="DinosaurBase")
[1350] loadk     7   305      ; R7 := K305(="CrowdPhysicsCollider")
[1351] settable  6   7   265  ; R6[R7] := K9(="DinosaurBase")
[1352] loadk     7   306      ; R7 := K306(="DinosaurAmenities")
[1353] settable  6   7   265  ; R6[R7] := K9(="DinosaurBase")
[1354] loadk     7   307      ; R7 := K307(="DinosaurBehaviourTag")
[1355] settable  6   7   265  ; R6[R7] := K9(="DinosaurBase")
[1356] loadk     7   308      ; R7 := K308(="DinosaurHeadLookReaction")
[1357] settable  6   7   265  ; R6[R7] := K9(="DinosaurBase")
[1358] loadk     7   309      ; R7 := K309(="DinosaurMaterialDecay")
[1359] settable  6   7   265  ; R6[R7] := K9(="DinosaurBase")
[1360] loadk     7   310      ; R7 := K310(="DinosaurMovementTarget")
[1361] settable  6   7   265  ; R6[R7] := K9(="DinosaurBase")
[1362] loadk     7   311      ; R7 := K311(="DinosaurStatistics")
[1363] settable  6   7   265  ; R6[R7] := K9(="DinosaurBase")
[1364] loadk     7   312      ; R7 := K312(="DinosaurThreat")
[1365] settable  6   7   265  ; R6[R7] := K9(="DinosaurBase")
[1366] loadk     7   313      ; R7 := K313(="DinosaurTreeAgent")
[1367] settable  6   7   265  ; R6[R7] := K9(="DinosaurBase")
[1368] loadk     7   314      ; R7 := K314(="DinosaurUIContext")
[1369] settable  6   7   265  ; R6[R7] := K9(="DinosaurBase")
[1370] loadk     7   315      ; R7 := K315(="FlowDirection")
[1371] settable  6   7   265  ; R6[R7] := K9(="DinosaurBase")
[1372] loadk     7   316      ; R7 := K316(="FlowMotion")
[1373] settable  6   7   265  ; R6[R7] := K9(="DinosaurBase")
[1374] loadk     7   317      ; R7 := K317(="FlowParticle")
[1375] settable  6   7   265  ; R6[R7] := K9(="DinosaurBase")
[1376] loadk     7   318      ; R7 := K318(="FlowPath")
[1377] settable  6   7   265  ; R6[R7] := K9(="DinosaurBase")
[1378] loadk     7   319      ; R7 := K319(="FlowStreamPath")
[1379] settable  6   7   265  ; R6[R7] := K9(="DinosaurBase")
[1380] loadk     7   320      ; R7 := K320(="FlowTargetReservation")
[1381] settable  6   7   265  ; R6[R7] := K9(="DinosaurBase")
[1382] loadk     7   321      ; R7 := K321(="FlowTheatre")
[1383] settable  6   7   265  ; R6[R7] := K9(="DinosaurBase")
[1384] loadk     7   322      ; R7 := K322(="GuestThreatMap")
[1385] settable  6   7   265  ; R6[R7] := K9(="DinosaurBase")
[1386] loadk     7   323      ; R7 := K323(="HerdMembership")
[1387] settable  6   7   265  ; R6[R7] := K9(="DinosaurBase")
[1388] loadk     7   324      ; R7 := K324(="LevelOfDetail")
[1389] settable  6   7   265  ; R6[R7] := K9(="DinosaurBase")
[1390] loadk     7   325      ; R7 := K325(="Locomotion")
[1391] settable  6   7   265  ; R6[R7] := K9(="DinosaurBase")
[1392] loadk     7   326      ; R7 := K326(="MapIcon")
[1393] settable  6   7   265  ; R6[R7] := K9(="DinosaurBase")
[1394] loadk     7   327      ; R7 := K327(="MotionApplication")
[1395] settable  6   7   265  ; R6[R7] := K9(="DinosaurBase")
[1396] loadk     7   328      ; R7 := K328(="PhysicsProxy")
[1397] settable  6   7   265  ; R6[R7] := K9(="DinosaurBase")
[1398] loadk     7   329      ; R7 := K329(="PhysicsRagdollImpact")
[1399] settable  6   7   265  ; R6[R7] := K9(="DinosaurBase")
[1400] loadk     7   330      ; R7 := K330(="RenderBoundingVolume")
[1401] settable  6   7   265  ; R6[R7] := K9(="DinosaurBase")
[1402] loadk     7   331      ; R7 := K331(="SkeletonDebug")
[1403] settable  6   7   265  ; R6[R7] := K9(="DinosaurBase")
[1404] settable  6   464 265  ; R6[K208(="SpatialDatabase")] := K9(="DinosaurBase")
[1405] loadk     7   332      ; R7 := K332(="TheatreActor")
[1406] settable  6   7   265  ; R6[R7] := K9(="DinosaurBase")
[1407] settable  6   377 265  ; R6[K121(="Transform")] := K9(="DinosaurBase")
[1408] settable  6   435 265  ; R6[K179(="Velocity")] := K9(="DinosaurBase")
[1409] loadk     7   333      ; R7 := K333(="ViewFilter")
[1410] settable  6   7   265  ; R6[R7] := K9(="DinosaurBase")
[1411] loadk     7   334      ; R7 := K334(="ViewpointTarget")
[1412] settable  6   7   265  ; R6[R7] := K9(="DinosaurBase")
[1413] settable  5   430 6    ; R5[K174(="ComponentSources")] := R6
[1414] newtable  6   0   32   ; R6 := {} , array_size=0, hash_size=64
[1415] loadk     7   300      ; R7 := K300(="AmenityProvider")
[1416] newtable  8   0   0    ; R8 := {} , array_size=0, hash_size=0
[1417] settable  6   7   8    ; R6[R7] := R8
[1418] loadk     7   301      ; R7 := K301(="Animation")
[1419] newtable  8   0   1    ; R8 := {} , array_size=0, hash_size=1
[1420] loadk     9   335      ; R9 := K335(="HierName")
[1421] loadk     10  336      ; R10 := K336(="DinosaurBaseMotionGraph")
[1422] settable  8   9   10   ; R8[R9] := R10
[1423] settable  6   7   8    ; R6[R7] := R8
[1424] newtable  7   0   2    ; R7 := {} , array_size=0, hash_size=2
[1425] newtable  8   1   0    ; R8 := {} , array_size=1, hash_size=0
[1426] loadk     9   223      ; R9 := K223(="DinosaurCommon")
[1427] setlist   8   1   1    ; R8[1 to 1] := R9 to R9
[1428] settable  7   478 8    ; R7[K222(="ManualPackageNames")] := R8
[1429] newtable  8   0   1    ; R8 := {} , array_size=0, hash_size=1
[1430] settable  8   437 267  ; R8[K181(="__property")] := K11(="AssetPackages")
[1431] settable  7   420 8    ; R7[K164(="PackageNames")] := R8
[1432] settable  6   419 7    ; R6[K163(="AssetPackageLoader")] := R7
[1433] newtable  7   0   1    ; R7 := {} , array_size=0, hash_size=1
[1434] settable  7   408 480  ; R7[K152(="LoaderPath")] := K224(=".")
[1435] settable  6   407 7    ; R6[K151(="AssetPackageProvider")] := R7
[1436] loadk     7   302      ; R7 := K302(="AssetPackageStream")
[1437] newtable  8   0   1    ; R8 := {} , array_size=0, hash_size=1
[1438] loadk     9   337      ; R9 := K337(="RequestType")
[1439] loadk     10  338      ; R10 := K338(="LocationVolume")
[1440] settable  8   9   10   ; R8[R9] := R10
[1441] settable  6   7   8    ; R6[R7] := R8
[1442] loadk     7   303      ; R7 := K303(="BehaviourTreeAgent")
[1443] newtable  8   0   0    ; R8 := {} , array_size=0, hash_size=0
[1444] settable  6   7   8    ; R6[R7] := R8
[1445] loadk     7   339      ; R7 := K339(="BehaviourTreeProvider")
[1446] newtable  8   0   1    ; R8 := {} , array_size=0, hash_size=1
[1447] loadk     9   340      ; R9 := K340(="BehaviourTree")
[1448] newtable  10  0   1    ; R10 := {} , array_size=0, hash_size=1
[1449] loadk     11  340      ; R11 := K340(="BehaviourTree")
[1450] settable  10  437 11   ; R10[K181(="__property")] := R11
[1451] settable  8   9   10   ; R8[R9] := R10
[1452] settable  6   7   8    ; R6[R7] := R8
[1453] newtable  7   0   0    ; R7 := {} , array_size=0, hash_size=0
[1454] settable  6   434 7    ; R6[K178(="BoundingVolumeBroadphase")] := R7
[1455] loadk     7   304      ; R7 := K304(="Coordination")
[1456] newtable  8   0   0    ; R8 := {} , array_size=0, hash_size=0
[1457] settable  6   7   8    ; R6[R7] := R8
[1458] loadk     7   305      ; R7 := K305(="CrowdPhysicsCollider")
[1459] newtable  8   0   0    ; R8 := {} , array_size=0, hash_size=0
[1460] settable  6   7   8    ; R6[R7] := R8
[1461] loadk     7   306      ; R7 := K306(="DinosaurAmenities")
[1462] newtable  8   0   0    ; R8 := {} , array_size=0, hash_size=0
[1463] settable  6   7   8    ; R6[R7] := R8
[1464] loadk     7   307      ; R7 := K307(="DinosaurBehaviourTag")
[1465] newtable  8   0   0    ; R8 := {} , array_size=0, hash_size=0
[1466] settable  6   7   8    ; R6[R7] := R8
[1467] newtable  7   0   4    ; R7 := {} , array_size=0, hash_size=4
[1468] loadk     8   341      ; R8 := K341(="AlternateFocusBone")
[1469] loadk     9   299      ; R9 := K299(="def_c_root_joint")
[1470] settable  7   8   9    ; R7[R8] := R9
[1471] loadk     8   342      ; R8 := K342(="FocusBone")
[1472] settable  7   8   307  ; R7[R8] := K51(="def_c_head_joint")
[1473] settable  7   277 278  ; R7[K21(="FocusRadius")] := K22(=4.0)
[1474] newtable  8   0   3    ; R8 := {} , array_size=0, hash_size=3
[1475] settable  8   280 281  ; R8[K24(="FocusYOffset")] := K25(=0.1)
[1476] settable  8   282 283  ; R8[K26(="PivotDistanceMultiplier")] := K27(=1.2)
[1477] settable  8   284 285  ; R8[K28(="Radius")] := K29(=2.3)
[1478] settable  7   279 8    ; R7[K23(="HatcheryExit")] := R8
[1479] settable  6   276 7    ; R6[K20(="DinosaurCamera")] := R7
[1480] loadk     7   343      ; R7 := K343(="DinosaurDiseaseSource")
[1481] newtable  8   0   3    ; R8 := {} , array_size=0, hash_size=3
[1482] loadk     9   344      ; R9 := K344(="InfectAmount")
[1483] newtable  10  0   1    ; R10 := {} , array_size=0, hash_size=1
[1484] loadk     11  344      ; R11 := K344(="InfectAmount")
[1485] settable  10  437 11   ; R10[K181(="__property")] := R11
[1486] settable  8   9   10   ; R8[R9] := R10
[1487] loadk     9   345      ; R9 := K345(="InfectTimer")
[1488] newtable  10  0   1    ; R10 := {} , array_size=0, hash_size=1
[1489] loadk     11  345      ; R11 := K345(="InfectTimer")
[1490] settable  10  437 11   ; R10[K181(="__property")] := R11
[1491] settable  8   9   10   ; R8[R9] := R10
[1492] newtable  9   0   1    ; R9 := {} , array_size=0, hash_size=1
[1493] loadk     10  346      ; R10 := K346(="InfectRadius")
[1494] settable  9   437 10   ; R9[K181(="__property")] := R10
[1495] settable  8   284 9    ; R8[K28(="Radius")] := R9
[1496] settable  6   7   8    ; R6[R7] := R8
[1497] loadk     7   347      ; R7 := K347(="DinosaurGenome")
[1498] newtable  8   0   18   ; R8 := {} , array_size=0, hash_size=20
[1499] loadk     9   348      ; R9 := K348(="AttackModification")
[1500] newtable  10  0   1    ; R10 := {} , array_size=0, hash_size=1
[1501] loadk     11  348      ; R11 := K348(="AttackModification")
[1502] settable  10  437 11   ; R10[K181(="__property")] := R11
[1503] settable  8   9   10   ; R8[R9] := R10
[1504] loadk     9   349      ; R9 := K349(="CosmeticGenes")
[1505] newtable  10  0   1    ; R10 := {} , array_size=0, hash_size=1
[1506] loadk     11  349      ; R11 := K349(="CosmeticGenes")
[1507] settable  10  437 11   ; R10[K181(="__property")] := R11
[1508] settable  8   9   10   ; R8[R9] := R10
[1509] loadk     9   350      ; R9 := K350(="CostMultiplier")
[1510] newtable  10  0   1    ; R10 := {} , array_size=0, hash_size=1
[1511] loadk     11  350      ; R11 := K350(="CostMultiplier")
[1512] settable  10  437 11   ; R10[K181(="__property")] := R11
[1513] settable  8   9   10   ; R8[R9] := R10
[1514] loadk     9   351      ; R9 := K351(="DefenceModification")
[1515] newtable  10  0   1    ; R10 := {} , array_size=0, hash_size=1
[1516] loadk     11  351      ; R11 := K351(="DefenceModification")
[1517] settable  10  437 11   ; R10[K181(="__property")] := R11
[1518] settable  8   9   10   ; R8[R9] := R10
[1519] loadk     9   352      ; R9 := K352(="ForestMultiplierModification")
[1520] newtable  10  0   1    ; R10 := {} , array_size=0, hash_size=1
[1521] loadk     11  352      ; R11 := K352(="ForestMultiplierModification")
[1522] settable  10  437 11   ; R10[K181(="__property")] := R11
[1523] settable  8   9   10   ; R8[R9] := R10
[1524] loadk     9   353      ; R9 := K353(="GeneTypePriorities")
[1525] newtable  10  0   1    ; R10 := {} , array_size=0, hash_size=1
[1526] loadk     11  353      ; R11 := K353(="GeneTypePriorities")
[1527] settable  10  437 11   ; R10[K181(="__property")] := R11
[1528] settable  8   9   10   ; R8[R9] := R10
[1529] loadk     9   354      ; R9 := K354(="GeneTypes")
[1530] newtable  10  0   1    ; R10 := {} , array_size=0, hash_size=1
[1531] loadk     11  354      ; R11 := K354(="GeneTypes")
[1532] settable  10  437 11   ; R10[K181(="__property")] := R11
[1533] settable  8   9   10   ; R8[R9] := R10
[1534] loadk     9   355      ; R9 := K355(="GrasslandMultiplierModification")
[1535] newtable  10  0   1    ; R10 := {} , array_size=0, hash_size=1
[1536] loadk     11  355      ; R11 := K355(="GrasslandMultiplierModification")
[1537] settable  10  437 11   ; R10[K181(="__property")] := R11
[1538] settable  8   9   10   ; R8[R9] := R10
[1539] loadk     9   356      ; R9 := K356(="LifespanModification")
[1540] newtable  10  0   1    ; R10 := {} , array_size=0, hash_size=1
[1541] loadk     11  356      ; R11 := K356(="LifespanModification")
[1542] settable  10  437 11   ; R10[K181(="__property")] := R11
[1543] settable  8   9   10   ; R8[R9] := R10
[1544] loadk     9   357      ; R9 := K357(="MaxOvercrowdingAdjustmentModification")
[1545] newtable  10  0   1    ; R10 := {} , array_size=0, hash_size=1
[1546] loadk     11  357      ; R11 := K357(="MaxOvercrowdingAdjustmentModification")
[1547] settable  10  437 11   ; R10[K181(="__property")] := R11
[1548] settable  8   9   10   ; R8[R9] := R10
[1549] loadk     9   358      ; R9 := K358(="MaxSocialAdjustmentModification")
[1550] newtable  10  0   1    ; R10 := {} , array_size=0, hash_size=1
[1551] loadk     11  358      ; R11 := K358(="MaxSocialAdjustmentModification")
[1552] settable  10  437 11   ; R10[K181(="__property")] := R11
[1553] settable  8   9   10   ; R8[R9] := R10
[1554] loadk     9   359      ; R9 := K359(="MinOvercrowdingAdjustmentModification")
[1555] newtable  10  0   1    ; R10 := {} , array_size=0, hash_size=1
[1556] loadk     11  359      ; R11 := K359(="MinOvercrowdingAdjustmentModification")
[1557] settable  10  437 11   ; R10[K181(="__property")] := R11
[1558] settable  8   9   10   ; R8[R9] := R10
[1559] loadk     9   360      ; R9 := K360(="MinSocialAdjustmentModification")
[1560] newtable  10  0   1    ; R10 := {} , array_size=0, hash_size=1
[1561] loadk     11  360      ; R11 := K360(="MinSocialAdjustmentModification")
[1562] settable  10  437 11   ; R10[K181(="__property")] := R11
[1563] settable  8   9   10   ; R8[R9] := R10
[1564] loadk     9   361      ; R9 := K361(="NumModifiedGenes")
[1565] newtable  10  0   1    ; R10 := {} , array_size=0, hash_size=1
[1566] loadk     11  361      ; R11 := K361(="NumModifiedGenes")
[1567] settable  10  437 11   ; R10[K181(="__property")] := R11
[1568] settable  8   9   10   ; R8[R9] := R10
[1569] loadk     9   362      ; R9 := K362(="NumUnmodifiedGenes")
[1570] newtable  10  0   1    ; R10 := {} , array_size=0, hash_size=1
[1571] loadk     11  362      ; R11 := K362(="NumUnmodifiedGenes")
[1572] settable  10  437 11   ; R10[K181(="__property")] := R11
[1573] settable  8   9   10   ; R8[R9] := R10
[1574] loadk     9   363      ; R9 := K363(="Percentage")
[1575] newtable  10  0   1    ; R10 := {} , array_size=0, hash_size=1
[1576] loadk     11  364      ; R11 := K364(="GenomePercentage")
[1577] settable  10  437 11   ; R10[K181(="__property")] := R11
[1578] settable  8   9   10   ; R8[R9] := R10
[1579] loadk     9   365      ; R9 := K365(="PrestigeBonusModification")
[1580] newtable  10  0   1    ; R10 := {} , array_size=0, hash_size=1
[1581] loadk     11  365      ; R11 := K365(="PrestigeBonusModification")
[1582] settable  10  437 11   ; R10[K181(="__property")] := R11
[1583] settable  8   9   10   ; R8[R9] := R10
[1584] loadk     9   366      ; R9 := K366(="ResilienceModification")
[1585] newtable  10  0   1    ; R10 := {} , array_size=0, hash_size=1
[1586] loadk     11  366      ; R11 := K366(="ResilienceModification")
[1587] settable  10  437 11   ; R10[K181(="__property")] := R11
[1588] settable  8   9   10   ; R8[R9] := R10
[1589] loadk     9   367      ; R9 := K367(="StressThresholdAdjustmentModification")
[1590] newtable  10  0   1    ; R10 := {} , array_size=0, hash_size=1
[1591] loadk     11  367      ; R11 := K367(="StressThresholdAdjustmentModification")
[1592] settable  10  437 11   ; R10[K181(="__property")] := R11
[1593] settable  8   9   10   ; R8[R9] := R10
[1594] settable  6   7   8    ; R6[R7] := R8
[1595] loadk     7   308      ; R7 := K308(="DinosaurHeadLookReaction")
[1596] newtable  8   0   0    ; R8 := {} , array_size=0, hash_size=0
[1597] settable  6   7   8    ; R6[R7] := R8
[1598] loadk     7   368      ; R7 := K368(="DinosaurLifecycle")
[1599] newtable  8   0   5    ; R8 := {} , array_size=0, hash_size=5
[1600] loadk     9   369      ; R9 := K369(="EffectiveAge")
[1601] newtable  10  0   1    ; R10 := {} , array_size=0, hash_size=1
[1602] loadk     11  369      ; R11 := K369(="EffectiveAge")
[1603] settable  10  437 11   ; R10[K181(="__property")] := R11
[1604] settable  8   9   10   ; R8[R9] := R10
[1605] loadk     9   370      ; R9 := K370(="RealAge")
[1606] newtable  10  0   1    ; R10 := {} , array_size=0, hash_size=1
[1607] loadk     11  370      ; R11 := K370(="RealAge")
[1608] settable  10  437 11   ; R10[K181(="__property")] := R11
[1609] settable  8   9   10   ; R8[R9] := R10
[1610] loadk     9   371      ; R9 := K371(="SpawnFromHatcheryWithCutscene")
[1611] newtable  10  0   1    ; R10 := {} , array_size=0, hash_size=1
[1612] loadk     11  371      ; R11 := K371(="SpawnFromHatcheryWithCutscene")
[1613] settable  10  437 11   ; R10[K181(="__property")] := R11
[1614] settable  8   9   10   ; R8[R9] := R10
[1615] loadk     9   372      ; R9 := K372(="SpawnUnconscious")
[1616] newtable  10  0   1    ; R10 := {} , array_size=0, hash_size=1
[1617] loadk     11  373      ; R11 := K373(="StartUnconscious")
[1618] settable  10  437 11   ; R10[K181(="__property")] := R11
[1619] settable  8   9   10   ; R8[R9] := R10
[1620] loadk     9   374      ; R9 := K374(="SpawnedFromHatchery")
[1621] newtable  10  0   1    ; R10 := {} , array_size=0, hash_size=1
[1622] loadk     11  374      ; R11 := K374(="SpawnedFromHatchery")
[1623] settable  10  437 11   ; R10[K181(="__property")] := R11
[1624] settable  8   9   10   ; R8[R9] := R10
[1625] settable  6   7   8    ; R6[R7] := R8
[1626] loadk     7   309      ; R7 := K309(="DinosaurMaterialDecay")
[1627] newtable  8   0   0    ; R8 := {} , array_size=0, hash_size=0
[1628] settable  6   7   8    ; R6[R7] := R8
[1629] loadk     7   310      ; R7 := K310(="DinosaurMovementTarget")
[1630] newtable  8   0   1    ; R8 := {} , array_size=0, hash_size=1
[1631] loadk     9   375      ; R9 := K375(="Food_Tranquillised")
[1632] settable  8   503 9    ; R8[K247(="TargetType")] := R9
[1633] settable  6   7   8    ; R6[R7] := R8
[1634] loadk     7   376      ; R7 := K376(="DinosaurSimulation")
[1635] newtable  8   0   1    ; R8 := {} , array_size=0, hash_size=1
[1636] loadk     9   373      ; R9 := K373(="StartUnconscious")
[1637] newtable  10  0   1    ; R10 := {} , array_size=0, hash_size=1
[1638] loadk     11  373      ; R11 := K373(="StartUnconscious")
[1639] settable  10  437 11   ; R10[K181(="__property")] := R11
[1640] settable  8   9   10   ; R8[R9] := R10
[1641] settable  6   7   8    ; R6[R7] := R8
[1642] loadk     7   377      ; R7 := K377(="DinosaurSpecies")
[1643] newtable  8   0   2    ; R8 := {} , array_size=0, hash_size=2
[1644] loadk     9   378      ; R9 := K378(="IsDead")
[1645] newtable  10  0   1    ; R10 := {} , array_size=0, hash_size=1
[1646] loadk     11  378      ; R11 := K378(="IsDead")
[1647] settable  10  437 11   ; R10[K181(="__property")] := R11
[1648] settable  8   9   10   ; R8[R9] := R10
[1649] loadk     9   379      ; R9 := K379(="Species")
[1650] newtable  10  0   1    ; R10 := {} , array_size=0, hash_size=1
[1651] loadk     11  379      ; R11 := K379(="Species")
[1652] settable  10  437 11   ; R10[K181(="__property")] := R11
[1653] settable  8   9   10   ; R8[R9] := R10
[1654] settable  6   7   8    ; R6[R7] := R8
[1655] loadk     7   311      ; R7 := K311(="DinosaurStatistics")
[1656] newtable  8   0   0    ; R8 := {} , array_size=0, hash_size=0
[1657] settable  6   7   8    ; R6[R7] := R8
[1658] loadk     7   312      ; R7 := K312(="DinosaurThreat")
[1659] newtable  8   0   1    ; R8 := {} , array_size=0, hash_size=1
[1660] loadk     9   380      ; R9 := K380(="ThreatCategory")
[1661] settable  8   9   467  ; R8[R9] := K211(="Dinosaur")
[1662] settable  6   7   8    ; R6[R7] := R8
[1663] loadk     7   313      ; R7 := K313(="DinosaurTreeAgent")
[1664] newtable  8   0   0    ; R8 := {} , array_size=0, hash_size=0
[1665] settable  6   7   8    ; R6[R7] := R8
[1666] loadk     7   314      ; R7 := K314(="DinosaurUIContext")
[1667] newtable  8   0   0    ; R8 := {} , array_size=0, hash_size=0
[1668] settable  6   7   8    ; R6[R7] := R8
[1669] loadk     7   315      ; R7 := K315(="FlowDirection")
[1670] newtable  8   0   0    ; R8 := {} , array_size=0, hash_size=0
[1671] settable  6   7   8    ; R6[R7] := R8
[1672] newtable  7   0   4    ; R7 := {} , array_size=0, hash_size=4
[1673] loadk     8   381      ; R8 := K381(="ApplyDiscomfort")
[1674] settable  7   8   448  ; R7[R8] := K192(=true)
[1675] loadk     8   382      ; R8 := K382(="DiscomfortGradient")
[1676] settable  7   8   448  ; R7[R8] := K192(=true)
[1677] settable  7   287 288  ; R7[K31(="DiscomfortRadius")] := K32(=6.0)
[1678] settable  7   289 290  ; R7[K33(="DiscomfortValue")] := K34(=20.0)
[1679] settable  6   286 7    ; R6[K30(="FlowDiscomfort")] := R7
[1680] loadk     7   316      ; R7 := K316(="FlowMotion")
[1681] newtable  8   0   1    ; R8 := {} , array_size=0, hash_size=1
[1682] loadk     9   383      ; R9 := K383(="ObstructionType")
[1683] loadk     10  384      ; R10 := K384(="MediumDino")
[1684] settable  8   9   10   ; R8[R9] := R10
[1685] settable  6   7   8    ; R6[R7] := R8
[1686] loadk     7   317      ; R7 := K317(="FlowParticle")
[1687] newtable  8   0   2    ; R8 := {} , array_size=0, hash_size=2
[1688] loadk     9   385      ; R9 := K385(="Active")
[1689] settable  8   9   448  ; R8[R9] := K192(=true)
[1690] loadk     9   386      ; R9 := K386(="DensityMultiplier")
[1691] settable  8   9   350  ; R8[R9] := K94(=2.0)
[1692] settable  6   7   8    ; R6[R7] := R8
[1693] loadk     7   318      ; R7 := K318(="FlowPath")
[1694] newtable  8   0   0    ; R8 := {} , array_size=0, hash_size=0
[1695] settable  6   7   8    ; R6[R7] := R8
[1696] loadk     7   319      ; R7 := K319(="FlowStreamPath")
[1697] newtable  8   0   2    ; R8 := {} , array_size=0, hash_size=2
[1698] loadk     9   387      ; R9 := K387(="FillDistance")
[1699] loadk     10  388      ; R10 := K388(=90.0)
[1700] settable  8   9   10   ; R8[R9] := R10
[1701] loadk     9   389      ; R9 := K389(="MinDistance")
[1702] loadk     10  390      ; R10 := K390(=50.0)
[1703] settable  8   9   10   ; R8[R9] := R10
[1704] settable  6   7   8    ; R6[R7] := R8
[1705] loadk     7   320      ; R7 := K320(="FlowTargetReservation")
[1706] newtable  8   0   0    ; R8 := {} , array_size=0, hash_size=0
[1707] settable  6   7   8    ; R6[R7] := R8
[1708] loadk     7   321      ; R7 := K321(="FlowTheatre")
[1709] newtable  8   0   0    ; R8 := {} , array_size=0, hash_size=0
[1710] settable  6   7   8    ; R6[R7] := R8
[1711] loadk     7   322      ; R7 := K322(="GuestThreatMap")
[1712] newtable  8   0   0    ; R8 := {} , array_size=0, hash_size=0
[1713] settable  6   7   8    ; R6[R7] := R8
[1714] loadk     7   323      ; R7 := K323(="HerdMembership")
[1715] newtable  8   0   0    ; R8 := {} , array_size=0, hash_size=0
[1716] settable  6   7   8    ; R6[R7] := R8
[1717] newtable  7   0   4    ; R7 := {} , array_size=0, hash_size=4
[1718] settable  7   292 293  ; R7[K36(="FootEffectSize")] := K37(="Medium")
[1719] loadk     8   391      ; R8 := K391(="GlobalBlendWeightStreams")
[1720] newtable  9   1   0    ; R9 := {} , array_size=1, hash_size=0
[1721] newtable  10  0   3    ; R10 := {} , array_size=0, hash_size=3
[1722] loadk     11  392      ; R11 := K392(="IsInverseRelated")
[1723] settable  10  11  448  ; R10[R11] := K192(=true)
[1724] loadk     11  393      ; R11 := K393(="StreamName")
[1725] loadk     12  394      ; R12 := K394(="SleepBlendOff")
[1726] settable  10  11  12   ; R10[R11] := R12
[1727] loadk     11  395      ; R11 := K395(="StreamType")
[1728] loadk     12  396      ; R12 := K396(="Sleep")
[1729] settable  10  11  12   ; R10[R11] := R12
[1730] setlist   9   1   1    ; R9[1 to 1] := R10 to R10
[1731] settable  7   8   9    ; R7[R8] := R9
[1732] newtable  8   4   0    ; R8 := {} , array_size=4, hash_size=0
[1733] newtable  9   0   2    ; R9 := {} , array_size=0, hash_size=2
[1734] settable  9   295 296  ; R9[K39(="BoneChainDepth")] := K40(=4)
[1735] settable  9   297 298  ; R9[K41(="BoneName")] := K42(="def_l_frontFoot_joint")
[1736] newtable  10  0   2    ; R10 := {} , array_size=0, hash_size=2
[1737] settable  10  295 296  ; R10[K39(="BoneChainDepth")] := K40(=4)
[1738] settable  10  297 299  ; R10[K41(="BoneName")] := K43(="def_r_frontFoot_joint")
[1739] newtable  11  0   2    ; R11 := {} , array_size=0, hash_size=2
[1740] settable  11  295 296  ; R11[K39(="BoneChainDepth")] := K40(=4)
[1741] settable  11  297 300  ; R11[K41(="BoneName")] := K44(="def_l_rearFoot_joint")
[1742] newtable  12  0   2    ; R12 := {} , array_size=0, hash_size=2
[1743] settable  12  295 296  ; R12[K39(="BoneChainDepth")] := K40(=4)
[1744] settable  12  297 301  ; R12[K41(="BoneName")] := K45(="def_r_rearFoot_joint")
[1745] setlist   8   4   1    ; R8[1 to 4] := R9 to R12
[1746] settable  7   294 8    ; R7[K38(="PlantSpecs")] := R8
[1747] settable  7   302 303  ; R7[K46(="ZRotationLimit")] := K47(=45.0)
[1748] settable  6   291 7    ; R6[K35(="IKFootPlant")] := R7
[1749] newtable  7   0   2    ; R7 := {} , array_size=0, hash_size=2
[1750] newtable  8   0   2    ; R8 := {} , array_size=0, hash_size=2
[1751] settable  8   295 306  ; R8[K39(="BoneChainDepth")] := K50(=3)
[1752] settable  8   297 307  ; R8[K41(="BoneName")] := K51(="def_c_head_joint")
[1753] settable  7   305 8    ; R7[K49(="BoneChain")] := R8
[1754] newtable  8   0   4    ; R8 := {} , array_size=0, hash_size=4
[1755] newtable  9   0   4    ; R9 := {} , array_size=0, hash_size=4
[1756] settable  9   310 311  ; R9[K54(="RadiusD")] := K55(=0.901)
[1757] settable  9   312 313  ; R9[K56(="RadiusFB")] := K57(=0.8)
[1758] settable  9   314 315  ; R9[K58(="RadiusLR")] := K59(=1.073)
[1759] settable  9   316 311  ; R9[K60(="RadiusU")] := K55(=0.901)
[1760] settable  8   309 9    ; R8[K53(="Ellipsoid")] := R9
[1761] newtable  9   0   2    ; R9 := {} , array_size=0, hash_size=2
[1762] newtable  10  0   6    ; R10 := {} , array_size=0, hash_size=6
[1763] settable  10  319 320  ; R10[K63(="ComfortPitchDown")] := K64(=30.0)
[1764] settable  10  321 322  ; R10[K65(="ComfortPitchUp")] := K66(=40.0)
[1765] settable  10  323 324  ; R10[K67(="ComfortYaw")] := K68(=21.0)
[1766] settable  10  325 326  ; R10[K69(="StrainPitchDown")] := K70(=25.0)
[1767] settable  10  327 328  ; R10[K71(="StrainPitchUp")] := K72(=31.0)
[1768] settable  10  329 330  ; R10[K73(="StrainYaw")] := K74(=42.0)
[1769] settable  9   318 10   ; R9[K62(="Constraints")] := R10
[1770] newtable  10  0   3    ; R10 := {} , array_size=0, hash_size=3
[1771] settable  10  332 333  ; R10[K76(="Damping")] := K77(=55.0)
[1772] settable  10  334 335  ; R10[K78(="MaxStrength")] := K79(=100.0)
[1773] settable  10  336 322  ; R10[K80(="MinStrength")] := K66(=40.0)
[1774] settable  9   331 10   ; R9[K75(="TorsionSpring")] := R10
[1775] settable  8   317 9    ; R8[K61(="HeadDynamics")] := R9
[1776] newtable  9   0   2    ; R9 := {} , array_size=0, hash_size=2
[1777] newtable  10  0   6    ; R10 := {} , array_size=0, hash_size=6
[1778] settable  10  319 290  ; R10[K63(="ComfortPitchDown")] := K34(=20.0)
[1779] settable  10  321 326  ; R10[K65(="ComfortPitchUp")] := K70(=25.0)
[1780] settable  10  323 338  ; R10[K67(="ComfortYaw")] := K82(=18.0)
[1781] settable  10  325 326  ; R10[K69(="StrainPitchDown")] := K70(=25.0)
[1782] settable  10  327 320  ; R10[K71(="StrainPitchUp")] := K64(=30.0)
[1783] settable  10  329 338  ; R10[K73(="StrainYaw")] := K82(=18.0)
[1784] settable  9   318 10   ; R9[K62(="Constraints")] := R10
[1785] newtable  10  0   3    ; R10 := {} , array_size=0, hash_size=3
[1786] settable  10  332 333  ; R10[K76(="Damping")] := K77(=55.0)
[1787] settable  10  334 339  ; R10[K78(="MaxStrength")] := K83(=86.0)
[1788] settable  10  336 303  ; R10[K80(="MinStrength")] := K47(=45.0)
[1789] settable  9   331 10   ; R9[K75(="TorsionSpring")] := R10
[1790] settable  8   337 9    ; R8[K81(="NeckDynamics")] := R9
[1791] settable  8   340 341  ; R8[K84(="PivotOffset")] := K85(=nil)
[1792] settable  7   308 8    ; R7[K52(="HeadTranslationEllipsoid")] := R8
[1793] settable  6   304 7    ; R6[K48(="IKHeadLook")] := R7
[1794] newtable  7   0   2    ; R7 := {} , array_size=0, hash_size=2
[1795] loadk     8   397      ; R8 := K397(="ConeEase")
[1796] settable  7   8   281  ; R7[R8] := K25(=0.1)
[1797] settable  7   343 344  ; R7[K87(="WarmFactor")] := K88(=0.3)
[1798] settable  6   342 7    ; R6[K86(="IKSolver")] := R7
[1799] loadk     7   324      ; R7 := K324(="LevelOfDetail")
[1800] newtable  8   0   0    ; R8 := {} , array_size=0, hash_size=0
[1801] settable  6   7   8    ; R6[R7] := R8
[1802] loadk     7   325      ; R7 := K325(="Locomotion")
[1803] newtable  8   0   1    ; R8 := {} , array_size=0, hash_size=1
[1804] loadk     9   398      ; R9 := K398(="SafeZoneRadius")
[1805] settable  8   9   460  ; R8[R9] := K204(=3.0)
[1806] settable  6   7   8    ; R6[R7] := R8
[1807] loadk     7   326      ; R7 := K326(="MapIcon")
[1808] newtable  8   0   2    ; R8 := {} , array_size=0, hash_size=2
[1809] loadk     9   399      ; R9 := K399(="")
[1810] settable  8   468 9    ; R8[K212(="Icon")] := R9
[1811] loadk     9   400      ; R9 := K400(="IconClass")
[1812] loadk     10  401      ; R10 := K401(="DinosaurIcon")
[1813] settable  8   9   10   ; R8[R9] := R10
[1814] settable  6   7   8    ; R6[R7] := R8
[1815] loadk     7   402      ; R7 := K402(="MaterialCollection")
[1816] newtable  8   0   2    ; R8 := {} , array_size=0, hash_size=2
[1817] loadk     9   403      ; R9 := K403(="ForceOnAllLODs")
[1818] settable  8   9   448  ; R8[R9] := K192(=true)
[1819] loadk     9   404      ; R9 := K404(="MaterialCollectionResource")
[1820] newtable  10  2   0    ; R10 := {} , array_size=2, hash_size=0
[1821] newtable  11  0   1    ; R11 := {} , array_size=0, hash_size=1
[1822] newtable  12  0   1    ; R12 := {} , array_size=0, hash_size=1
[1823] settable  12  437 272  ; R12[K181(="__property")] := K16(="MaterialCollectionName")
[1824] settable  11  369 12   ; R11[K113(="Name")] := R12
[1825] newtable  12  0   1    ; R12 := {} , array_size=0, hash_size=1
[1826] newtable  13  0   1    ; R13 := {} , array_size=0, hash_size=1
[1827] loadk     14  405      ; R14 := K405(="MaterialCollectionVariantsName")
[1828] settable  13  437 14   ; R13[K181(="__property")] := R14
[1829] settable  12  369 13   ; R12[K113(="Name")] := R13
[1830] setlist   10  2   1    ; R10[1 to 2] := R11 to R12
[1831] settable  8   9   10   ; R8[R9] := R10
[1832] settable  6   7   8    ; R6[R7] := R8
[1833] newtable  7   0   2    ; R7 := {} , array_size=0, hash_size=2
[1834] settable  7   346 347  ; R7[K90(="BoundingScaler")] := K91(=1.85)
[1835] newtable  8   0   1    ; R8 := {} , array_size=0, hash_size=1
[1836] settable  8   437 273  ; R8[K181(="__property")] := K17(="ModelName")
[1837] settable  7   273 8    ; R7[K17(="ModelName")] := R8
[1838] settable  6   345 7    ; R6[K89(="Model")] := R7
[1839] loadk     7   406      ; R7 := K406(="ModelSkeleton")
[1840] newtable  8   0   1    ; R8 := {} , array_size=0, hash_size=1
[1841] newtable  9   0   1    ; R9 := {} , array_size=0, hash_size=1
[1842] settable  9   437 273  ; R9[K181(="__property")] := K17(="ModelName")
[1843] settable  8   273 9    ; R8[K17(="ModelName")] := R9
[1844] settable  6   7   8    ; R6[R7] := R8
[1845] loadk     7   327      ; R7 := K327(="MotionApplication")
[1846] newtable  8   0   0    ; R8 := {} , array_size=0, hash_size=0
[1847] settable  6   7   8    ; R6[R7] := R8
[1848] loadk     7   407      ; R7 := K407(="MotionGraph")
[1849] newtable  8   0   2    ; R8 := {} , array_size=0, hash_size=2
[1850] loadk     9   408      ; R9 := K408(="HookNodeName")
[1851] loadk     10  409      ; R10 := K409(="MotionGraphHook")
[1852] settable  8   9   10   ; R8[R9] := R10
[1853] newtable  9   0   1    ; R9 := {} , array_size=0, hash_size=1
[1854] settable  9   437 274  ; R9[K181(="__property")] := K18(="MotionGraphName")
[1855] settable  8   274 9    ; R8[K18(="MotionGraphName")] := R9
[1856] settable  6   7   8    ; R6[R7] := R8
[1857] newtable  7   0   15   ; R7 := {} , array_size=0, hash_size=15
[1858] loadk     8   410      ; R8 := K410(="ADLPlannerConfigName")
[1859] loadk     9   411      ; R9 := K411(="Nero")
[1860] settable  7   8   9    ; R7[R8] := R9
[1861] settable  7   349 350  ; R7[K93(="CurveExpansion")] := K94(=2.0)
[1862] loadk     8   412      ; R8 := K412(="DefaultMinCycles")
[1863] loadk     9   413      ; R9 := K413(=2)
[1864] settable  7   8   9    ; R7[R8] := R9
[1865] loadk     8   414      ; R8 := K414(="ForwardErrorTol")
[1866] settable  7   8   400  ; R7[R8] := K144(=1.0)
[1867] loadk     8   415      ; R8 := K415(="ForwardSpringConstant")
[1868] settable  7   8   352  ; R7[R8] := K96(=10.0)
[1869] loadk     8   416      ; R8 := K416(="ForwardSpringDamping")
[1870] settable  7   8   400  ; R7[R8] := K144(=1.0)
[1871] loadk     8   417      ; R8 := K417(="LateralErrorTol")
[1872] settable  7   8   400  ; R7[R8] := K144(=1.0)
[1873] loadk     8   418      ; R8 := K418(="LateralSpringConstant")
[1874] settable  7   8   352  ; R7[R8] := K96(=10.0)
[1875] loadk     8   419      ; R8 := K419(="LateralSpringDamping")
[1876] settable  7   8   400  ; R7[R8] := K144(=1.0)
[1877] loadk     8   420      ; R8 := K420(="PlaybackRateSpringConstant")
[1878] loadk     9   390      ; R9 := K390(=50.0)
[1879] settable  7   8   9    ; R7[R8] := R9
[1880] loadk     8   421      ; R8 := K421(="PlaybackRateSpringDamping")
[1881] settable  7   8   400  ; R7[R8] := K144(=1.0)
[1882] loadk     8   422      ; R8 := K422(="RadiusReduction")
[1883] settable  7   8   400  ; R7[R8] := K144(=1.0)
[1884] settable  7   351 352  ; R7[K95(="RotationSpringConstant")] := K96(=10.0)
[1885] loadk     8   423      ; R8 := K423(="RotationSpringDamping")
[1886] settable  7   8   400  ; R7[R8] := K144(=1.0)
[1887] loadk     8   424      ; R8 := K424(="SetTransformWhenStopped")
[1888] settable  7   8   446  ; R7[R8] := K190(=false)
[1889] settable  6   348 7    ; R6[K92(="MotionGraphLocomotion")] := R7
[1890] newtable  7   0   2    ; R7 := {} , array_size=0, hash_size=2
[1891] settable  7   354 350  ; R7[K98(="Length")] := K94(=2.0)
[1892] settable  7   284 355  ; R7[K28(="Radius")] := K99(=1.65)
[1893] settable  6   353 7    ; R6[K97(="PhysicsCapsuleShape")] := R7
[1894] loadk     7   425      ; R7 := K425(="PhysicsDrivenSkeleton")
[1895] newtable  8   0   5    ; R8 := {} , array_size=0, hash_size=5
[1896] loadk     9   426      ; R9 := K426(="CollisionEnabled")
[1897] settable  8   9   448  ; R8[R9] := K192(=true)
[1898] newtable  9   0   1    ; R9 := {} , array_size=0, hash_size=1
[1899] settable  9   437 273  ; R9[K181(="__property")] := K17(="ModelName")
[1900] settable  8   273 9    ; R8[K17(="ModelName")] := R9
[1901] loadk     9   427      ; R9 := K427(="PhysicsWorldEntity")
[1902] loadk     10  428      ; R10 := K428(="/MainPhysicsWorld")
[1903] settable  8   9   10   ; R8[R9] := R10
[1904] loadk     9   429      ; R9 := K429(="SpatialEnabled")
[1905] settable  8   9   448  ; R8[R9] := K192(=true)
[1906] loadk     9   430      ; R9 := K430(="Synchronised")
[1907] settable  8   9   448  ; R8[R9] := K192(=true)
[1908] settable  6   7   8    ; R6[R7] := R8
[1909] loadk     7   328      ; R7 := K328(="PhysicsProxy")
[1910] newtable  8   0   2    ; R8 := {} , array_size=0, hash_size=2
[1911] loadk     9   431      ; R9 := K431(="MinCollisionLOD")
[1912] loadk     10  432      ; R10 := K432(=1)
[1913] settable  8   9   10   ; R8[R9] := R10
[1914] loadk     9   433      ; R9 := K433(="MinSpatialLOD")
[1915] loadk     10  413      ; R10 := K413(=2)
[1916] settable  8   9   10   ; R8[R9] := R10
[1917] settable  6   7   8    ; R6[R7] := R8
[1918] loadk     7   329      ; R7 := K329(="PhysicsRagdollImpact")
[1919] newtable  8   0   0    ; R8 := {} , array_size=0, hash_size=0
[1920] settable  6   7   8    ; R6[R7] := R8
[1921] newtable  7   0   7    ; R7 := {} , array_size=0, hash_size=7
[1922] loadk     8   434      ; R8 := K434(="ClassificationName")
[1923] loadk     9   435      ; R9 := K435(="DinosaurCollisionProxy")
[1924] settable  7   8   9    ; R7[R8] := R9
[1925] loadk     8   436      ; R8 := K436(="PhysicsShapeEntity")
[1926] settable  7   8   480  ; R7[R8] := K224(=".")
[1927] loadk     8   437      ; R8 := K437(="PhysicsShapeType")
[1928] loadk     9   438      ; R9 := K438(="Capsule")
[1929] settable  7   8   9    ; R7[R8] := R9
[1930] loadk     8   427      ; R8 := K427(="PhysicsWorldEntity")
[1931] loadk     9   428      ; R9 := K428(="/MainPhysicsWorld")
[1932] settable  7   8   9    ; R7[R8] := R9
[1933] settable  7   357 358  ; R7[K101(="ShapeOffset")] := K102(=nil)
[1934] loadk     8   439      ; R8 := K439(="StartKinematicallyDriven")
[1935] settable  7   8   448  ; R7[R8] := K192(=true)
[1936] loadk     8   440      ; R8 := K440(="SurfaceName")
[1937] loadk     9   441      ; R9 := K441(="DinosaurLimb")
[1938] settable  7   8   9    ; R7[R8] := R9
[1939] settable  6   356 7    ; R6[K100(="PhysicsRigidBody")] := R7
[1940] loadk     7   330      ; R7 := K330(="RenderBoundingVolume")
[1941] newtable  8   0   1    ; R8 := {} , array_size=0, hash_size=1
[1942] settable  8   284 400  ; R8[K28(="Radius")] := K144(=1.0)
[1943] settable  6   7   8    ; R6[R7] := R8
[1944] loadk     7   331      ; R7 := K331(="SkeletonDebug")
[1945] newtable  8   0   1    ; R8 := {} , array_size=0, hash_size=1
[1946] loadk     9   442      ; R9 := K442(="EnableDebugRender")
[1947] settable  8   9   446  ; R8[R9] := K190(=false)
[1948] settable  6   7   8    ; R6[R7] := R8
[1949] newtable  7   0   0    ; R7 := {} , array_size=0, hash_size=0
[1950] settable  6   464 7    ; R6[K208(="SpatialDatabase")] := R7
[1951] newtable  7   0   2    ; R7 := {} , array_size=0, hash_size=2
[1952] settable  7   284 360  ; R7[K28(="Radius")] := K104(=2.5)
[1953] newtable  8   1   0    ; R8 := {} , array_size=1, hash_size=0
[1954] loadk     9   268      ; R9 := K268(="dinosaur")
[1955] setlist   8   1   1    ; R8[1 to 1] := R9 to R9
[1956] settable  7   462 8    ; R7[K206(="SpatialGroups")] := R8
[1957] settable  6   359 7    ; R6[K103(="SpatialSphere")] := R7
[1958] loadk     7   332      ; R7 := K332(="TheatreActor")
[1959] newtable  8   0   0    ; R8 := {} , array_size=0, hash_size=0
[1960] settable  6   7   8    ; R6[R7] := R8
[1961] newtable  7   0   0    ; R7 := {} , array_size=0, hash_size=0
[1962] settable  6   377 7    ; R6[K121(="Transform")] := R7
[1963] loadk     7   443      ; R7 := K443(="UIEntityName")
[1964] newtable  8   0   3    ; R8 := {} , array_size=0, hash_size=3
[1965] loadk     9   444      ; R9 := K444(="InitialNameFormat")
[1966] loadk     10  445      ; R10 := K445(="%s-%03i")
[1967] settable  8   9   10   ; R8[R9] := R10
[1968] loadk     9   446      ; R9 := K446(="InitialNamePrefix")
[1969] newtable  10  0   1    ; R10 := {} , array_size=0, hash_size=1
[1970] loadk     11  446      ; R11 := K446(="InitialNamePrefix")
[1971] settable  10  437 11   ; R10[K181(="__property")] := R11
[1972] settable  8   9   10   ; R8[R9] := R10
[1973] loadk     9   447      ; R9 := K447(="SaveName")
[1974] settable  8   9   448  ; R8[R9] := K192(=true)
[1975] settable  6   7   8    ; R6[R7] := R8
[1976] newtable  7   0   0    ; R7 := {} , array_size=0, hash_size=0
[1977] settable  6   435 7    ; R6[K179(="Velocity")] := R7
[1978] loadk     7   333      ; R7 := K333(="ViewFilter")
[1979] newtable  8   0   3    ; R8 := {} , array_size=0, hash_size=3
[1980] loadk     9   448      ; R9 := K448(="EnvironmentMap")
[1981] settable  8   9   446  ; R8[R9] := K190(=false)
[1982] loadk     9   449      ; R9 := K449(="Perturbation")
[1983] settable  8   9   448  ; R8[R9] := K192(=true)
[1984] loadk     9   450      ; R9 := K450(="ShadowCascade4to7")
[1985] settable  8   9   446  ; R8[R9] := K190(=false)
[1986] settable  6   7   8    ; R6[R7] := R8
[1987] loadk     7   334      ; R7 := K334(="ViewpointTarget")
[1988] newtable  8   0   0    ; R8 := {} , array_size=0, hash_size=0
[1989] settable  6   7   8    ; R6[R7] := R8
[1990] newtable  7   0   2    ; R7 := {} , array_size=0, hash_size=2
[1991] loadk     8   451      ; R8 := K451(="AttachPoints")
[1992] newtable  9   4   0    ; R9 := {} , array_size=4, hash_size=0
[1993] loadk     10  452      ; R10 := K452(="./WinchAttachPoints/Neck")
[1994] loadk     11  453      ; R11 := K453(="./WinchAttachPoints/Tail")
[1995] loadk     12  454      ; R12 := K454(="./WinchAttachPoints/UpperBack")
[1996] loadk     13  455      ; R13 := K455(="./WinchAttachPoints/LowerBack")
[1997] setlist   9   4   1    ; R9[1 to 4] := R10 to R13
[1998] settable  7   8   9    ; R7[R8] := R9
[1999] settable  7   362 363  ; R7[K106(="StrapsEntity")] := K107(="./Straps")
[2000] settable  6   361 7    ; R6[K105(="Winchable")] := R7
[2001] settable  5   275 6    ; R5[K19(="Components")] := R6
[2002] newtable  6   0   0    ; R6 := {} , array_size=0, hash_size=0
[2003] settable  5   438 6    ; R5[K182(="IncompleteComponents")] := R6
[2004] newtable  6   0   25   ; R6 := {} , array_size=0, hash_size=36
[2005] newtable  7   0   4    ; R7 := {} , array_size=0, hash_size=4
[2006] loadk     8   456      ; R8 := K456(="Contents")
[2007] newtable  9   0   1    ; R9 := {} , array_size=0, hash_size=1
[2008] settable  9   387 456  ; R9[K131(="Type")] := K200(="string")
[2009] settable  7   8   9    ; R7[R8] := R9
[2010] newtable  8   1   1    ; R8 := {} , array_size=1, hash_size=1
[2011] loadk     9   13       ; R9 := K13(="Nasutoceratops")
[2012] settable  8   270 271  ; R8[K14(="__inheritance")] := K15(="Append")
[2013] setlist   8   1   1    ; R8[1 to 1] := R9 to R9
[2014] settable  7   268 8    ; R7[K12(="Default")] := R8
[2015] loadk     8   457      ; R8 := K457(="array")
[2016] settable  7   387 8    ; R7[K131(="Type")] := R8
[2017] settable  7   481 482  ; R7[K225(="UIGroup")] := K226(="Visuals")
[2018] settable  6   267 7    ; R6[K11(="AssetPackages")] := R7
[2019] loadk     7   348      ; R7 := K348(="AttackModification")
[2020] newtable  8   0   4    ; R8 := {} , array_size=0, hash_size=4
[2021] loadk     9   458      ; R9 := K458(=0)
[2022] settable  8   268 9    ; R8[K12(="Default")] := R9
[2023] settable  8   447 448  ; R8[K191(="Optional")] := K192(=true)
[2024] loadk     9   459      ; R9 := K459(="int32")
[2025] settable  8   387 9    ; R8[K131(="Type")] := R9
[2026] loadk     9   460      ; R9 := K460(="Genetics")
[2027] settable  8   481 9    ; R8[K225(="UIGroup")] := R9
[2028] settable  6   7   8    ; R6[R7] := R8
[2029] loadk     7   340      ; R7 := K340(="BehaviourTree")
[2030] newtable  8   0   3    ; R8 := {} , array_size=0, hash_size=3
[2031] loadk     9   461      ; R9 := K461(="DinosaurBehaviours")
[2032] settable  8   268 9    ; R8[K12(="Default")] := R9
[2033] settable  8   387 456  ; R8[K131(="Type")] := K200(="string")
[2034] loadk     9   462      ; R9 := K462(="Behaviours")
[2035] settable  8   481 9    ; R8[K225(="UIGroup")] := R9
[2036] settable  6   7   8    ; R6[R7] := R8
[2037] loadk     7   349      ; R7 := K349(="CosmeticGenes")
[2038] newtable  8   0   5    ; R8 := {} , array_size=0, hash_size=5
[2039] loadk     9   456      ; R9 := K456(="Contents")
[2040] newtable  10  0   1    ; R10 := {} , array_size=0, hash_size=1
[2041] loadk     11  463      ; R11 := K463(="uint32")
[2042] settable  10  387 11   ; R10[K131(="Type")] := R11
[2043] settable  8   9   10   ; R8[R9] := R10
[2044] newtable  9   0   0    ; R9 := {} , array_size=0, hash_size=0
[2045] settable  8   268 9    ; R8[K12(="Default")] := R9
[2046] settable  8   447 448  ; R8[K191(="Optional")] := K192(=true)
[2047] loadk     9   457      ; R9 := K457(="array")
[2048] settable  8   387 9    ; R8[K131(="Type")] := R9
[2049] loadk     9   460      ; R9 := K460(="Genetics")
[2050] settable  8   481 9    ; R8[K225(="UIGroup")] := R9
[2051] settable  6   7   8    ; R6[R7] := R8
[2052] loadk     7   350      ; R7 := K350(="CostMultiplier")
[2053] newtable  8   0   4    ; R8 := {} , array_size=0, hash_size=4
[2054] settable  8   268 400  ; R8[K12(="Default")] := K144(=1.0)
[2055] settable  8   447 448  ; R8[K191(="Optional")] := K192(=true)
[2056] settable  8   387 494  ; R8[K131(="Type")] := K238(="float")
[2057] loadk     9   460      ; R9 := K460(="Genetics")
[2058] settable  8   481 9    ; R8[K225(="UIGroup")] := R9
[2059] settable  6   7   8    ; R6[R7] := R8
[2060] loadk     7   351      ; R7 := K351(="DefenceModification")
[2061] newtable  8   0   4    ; R8 := {} , array_size=0, hash_size=4
[2062] loadk     9   458      ; R9 := K458(=0)
[2063] settable  8   268 9    ; R8[K12(="Default")] := R9
[2064] settable  8   447 448  ; R8[K191(="Optional")] := K192(=true)
[2065] loadk     9   459      ; R9 := K459(="int32")
[2066] settable  8   387 9    ; R8[K131(="Type")] := R9
[2067] loadk     9   460      ; R9 := K460(="Genetics")
[2068] settable  8   481 9    ; R8[K225(="UIGroup")] := R9
[2069] settable  6   7   8    ; R6[R7] := R8
[2070] loadk     7   369      ; R7 := K369(="EffectiveAge")
[2071] newtable  8   0   4    ; R8 := {} , array_size=0, hash_size=4
[2072] loadk     9   464      ; R9 := K464(=0.0)
[2073] settable  8   268 9    ; R8[K12(="Default")] := R9
[2074] settable  8   447 448  ; R8[K191(="Optional")] := K192(=true)
[2075] settable  8   387 494  ; R8[K131(="Type")] := K238(="float")
[2076] loadk     9   465      ; R9 := K465(="Simulation")
[2077] settable  8   481 9    ; R8[K225(="UIGroup")] := R9
[2078] settable  6   7   8    ; R6[R7] := R8
[2079] loadk     7   352      ; R7 := K352(="ForestMultiplierModification")
[2080] newtable  8   0   3    ; R8 := {} , array_size=0, hash_size=3
[2081] loadk     9   464      ; R9 := K464(=0.0)
[2082] settable  8   268 9    ; R8[K12(="Default")] := R9
[2083] settable  8   387 494  ; R8[K131(="Type")] := K238(="float")
[2084] loadk     9   460      ; R9 := K460(="Genetics")
[2085] settable  8   481 9    ; R8[K225(="UIGroup")] := R9
[2086] settable  6   7   8    ; R6[R7] := R8
[2087] loadk     7   353      ; R7 := K353(="GeneTypePriorities")
[2088] newtable  8   0   5    ; R8 := {} , array_size=0, hash_size=5
[2089] loadk     9   456      ; R9 := K456(="Contents")
[2090] newtable  10  0   1    ; R10 := {} , array_size=0, hash_size=1
[2091] loadk     11  463      ; R11 := K463(="uint32")
[2092] settable  10  387 11   ; R10[K131(="Type")] := R11
[2093] settable  8   9   10   ; R8[R9] := R10
[2094] newtable  9   0   0    ; R9 := {} , array_size=0, hash_size=0
[2095] settable  8   268 9    ; R8[K12(="Default")] := R9
[2096] settable  8   447 448  ; R8[K191(="Optional")] := K192(=true)
[2097] loadk     9   457      ; R9 := K457(="array")
[2098] settable  8   387 9    ; R8[K131(="Type")] := R9
[2099] loadk     9   460      ; R9 := K460(="Genetics")
[2100] settable  8   481 9    ; R8[K225(="UIGroup")] := R9
[2101] settable  6   7   8    ; R6[R7] := R8
[2102] loadk     7   354      ; R7 := K354(="GeneTypes")
[2103] newtable  8   0   5    ; R8 := {} , array_size=0, hash_size=5
[2104] loadk     9   456      ; R9 := K456(="Contents")
[2105] newtable  10  0   1    ; R10 := {} , array_size=0, hash_size=1
[2106] loadk     11  463      ; R11 := K463(="uint32")
[2107] settable  10  387 11   ; R10[K131(="Type")] := R11
[2108] settable  8   9   10   ; R8[R9] := R10
[2109] newtable  9   0   0    ; R9 := {} , array_size=0, hash_size=0
[2110] settable  8   268 9    ; R8[K12(="Default")] := R9
[2111] settable  8   447 448  ; R8[K191(="Optional")] := K192(=true)
[2112] loadk     9   457      ; R9 := K457(="array")
[2113] settable  8   387 9    ; R8[K131(="Type")] := R9
[2114] loadk     9   460      ; R9 := K460(="Genetics")
[2115] settable  8   481 9    ; R8[K225(="UIGroup")] := R9
[2116] settable  6   7   8    ; R6[R7] := R8
[2117] loadk     7   364      ; R7 := K364(="GenomePercentage")
[2118] newtable  8   0   3    ; R8 := {} , array_size=0, hash_size=3
[2119] loadk     9   464      ; R9 := K464(=0.0)
[2120] settable  8   268 9    ; R8[K12(="Default")] := R9
[2121] settable  8   387 494  ; R8[K131(="Type")] := K238(="float")
[2122] loadk     9   460      ; R9 := K460(="Genetics")
[2123] settable  8   481 9    ; R8[K225(="UIGroup")] := R9
[2124] settable  6   7   8    ; R6[R7] := R8
[2125] loadk     7   355      ; R7 := K355(="GrasslandMultiplierModification")
[2126] newtable  8   0   3    ; R8 := {} , array_size=0, hash_size=3
[2127] loadk     9   464      ; R9 := K464(=0.0)
[2128] settable  8   268 9    ; R8[K12(="Default")] := R9
[2129] settable  8   387 494  ; R8[K131(="Type")] := K238(="float")
[2130] loadk     9   460      ; R9 := K460(="Genetics")
[2131] settable  8   481 9    ; R8[K225(="UIGroup")] := R9
[2132] settable  6   7   8    ; R6[R7] := R8
[2133] loadk     7   344      ; R7 := K344(="InfectAmount")
[2134] newtable  8   0   3    ; R8 := {} , array_size=0, hash_size=3
[2135] settable  8   268 281  ; R8[K12(="Default")] := K25(=0.1)
[2136] settable  8   387 494  ; R8[K131(="Type")] := K238(="float")
[2137] loadk     9   465      ; R9 := K465(="Simulation")
[2138] settable  8   481 9    ; R8[K225(="UIGroup")] := R9
[2139] settable  6   7   8    ; R6[R7] := R8
[2140] loadk     7   346      ; R7 := K346(="InfectRadius")
[2141] newtable  8   0   3    ; R8 := {} , array_size=0, hash_size=3
[2142] loadk     9   466      ; R9 := K466(=15.0)
[2143] settable  8   268 9    ; R8[K12(="Default")] := R9
[2144] settable  8   387 494  ; R8[K131(="Type")] := K238(="float")
[2145] loadk     9   465      ; R9 := K465(="Simulation")
[2146] settable  8   481 9    ; R8[K225(="UIGroup")] := R9
[2147] settable  6   7   8    ; R6[R7] := R8
[2148] loadk     7   345      ; R7 := K345(="InfectTimer")
[2149] newtable  8   0   3    ; R8 := {} , array_size=0, hash_size=3
[2150] settable  8   268 400  ; R8[K12(="Default")] := K144(=1.0)
[2151] settable  8   387 494  ; R8[K131(="Type")] := K238(="float")
[2152] loadk     9   465      ; R9 := K465(="Simulation")
[2153] settable  8   481 9    ; R8[K225(="UIGroup")] := R9
[2154] settable  6   7   8    ; R6[R7] := R8
[2155] loadk     7   446      ; R7 := K446(="InitialNamePrefix")
[2156] newtable  8   0   3    ; R8 := {} , array_size=0, hash_size=3
[2157] loadk     9   399      ; R9 := K399(="")
[2158] settable  8   268 9    ; R8[K12(="Default")] := R9
[2159] settable  8   387 456  ; R8[K131(="Type")] := K200(="string")
[2160] loadk     9   467      ; R9 := K467(="UI")
[2161] settable  8   481 9    ; R8[K225(="UIGroup")] := R9
[2162] settable  6   7   8    ; R6[R7] := R8
[2163] loadk     7   378      ; R7 := K378(="IsDead")
[2164] newtable  8   0   3    ; R8 := {} , array_size=0, hash_size=3
[2165] settable  8   268 446  ; R8[K12(="Default")] := K190(=false)
[2166] loadk     9   468      ; R9 := K468(="bool")
[2167] settable  8   387 9    ; R8[K131(="Type")] := R9
[2168] loadk     9   465      ; R9 := K465(="Simulation")
[2169] settable  8   481 9    ; R8[K225(="UIGroup")] := R9
[2170] settable  6   7   8    ; R6[R7] := R8
[2171] loadk     7   356      ; R7 := K356(="LifespanModification")
[2172] newtable  8   0   4    ; R8 := {} , array_size=0, hash_size=4
[2173] loadk     9   458      ; R9 := K458(=0)
[2174] settable  8   268 9    ; R8[K12(="Default")] := R9
[2175] settable  8   447 448  ; R8[K191(="Optional")] := K192(=true)
[2176] loadk     9   459      ; R9 := K459(="int32")
[2177] settable  8   387 9    ; R8[K131(="Type")] := R9
[2178] loadk     9   460      ; R9 := K460(="Genetics")
[2179] settable  8   481 9    ; R8[K225(="UIGroup")] := R9
[2180] settable  6   7   8    ; R6[R7] := R8
[2181] newtable  7   0   3    ; R7 := {} , array_size=0, hash_size=3
[2182] settable  7   268 269  ; R7[K12(="Default")] := K13(="Nasutoceratops")
[2183] settable  7   387 456  ; R7[K131(="Type")] := K200(="string")
[2184] settable  7   481 482  ; R7[K225(="UIGroup")] := K226(="Visuals")
[2185] settable  6   272 7    ; R6[K16(="MaterialCollectionName")] := R7
[2186] loadk     7   405      ; R7 := K405(="MaterialCollectionVariantsName")
[2187] newtable  8   0   3    ; R8 := {} , array_size=0, hash_size=3
[2188] loadk     9   399      ; R9 := K399(="")
[2189] settable  8   268 9    ; R8[K12(="Default")] := R9
[2190] settable  8   387 456  ; R8[K131(="Type")] := K200(="string")
[2191] settable  8   481 482  ; R8[K225(="UIGroup")] := K226(="Visuals")
[2192] settable  6   7   8    ; R6[R7] := R8
[2193] loadk     7   357      ; R7 := K357(="MaxOvercrowdingAdjustmentModification")
[2194] newtable  8   0   3    ; R8 := {} , array_size=0, hash_size=3
[2195] loadk     9   458      ; R9 := K458(=0)
[2196] settable  8   268 9    ; R8[K12(="Default")] := R9
[2197] loadk     9   459      ; R9 := K459(="int32")
[2198] settable  8   387 9    ; R8[K131(="Type")] := R9
[2199] loadk     9   460      ; R9 := K460(="Genetics")
[2200] settable  8   481 9    ; R8[K225(="UIGroup")] := R9
[2201] settable  6   7   8    ; R6[R7] := R8
[2202] loadk     7   358      ; R7 := K358(="MaxSocialAdjustmentModification")
[2203] newtable  8   0   3    ; R8 := {} , array_size=0, hash_size=3
[2204] loadk     9   458      ; R9 := K458(=0)
[2205] settable  8   268 9    ; R8[K12(="Default")] := R9
[2206] loadk     9   459      ; R9 := K459(="int32")
[2207] settable  8   387 9    ; R8[K131(="Type")] := R9
[2208] loadk     9   460      ; R9 := K460(="Genetics")
[2209] settable  8   481 9    ; R8[K225(="UIGroup")] := R9
[2210] settable  6   7   8    ; R6[R7] := R8
[2211] loadk     7   359      ; R7 := K359(="MinOvercrowdingAdjustmentModification")
[2212] newtable  8   0   3    ; R8 := {} , array_size=0, hash_size=3
[2213] loadk     9   458      ; R9 := K458(=0)
[2214] settable  8   268 9    ; R8[K12(="Default")] := R9
[2215] loadk     9   459      ; R9 := K459(="int32")
[2216] settable  8   387 9    ; R8[K131(="Type")] := R9
[2217] loadk     9   460      ; R9 := K460(="Genetics")
[2218] settable  8   481 9    ; R8[K225(="UIGroup")] := R9
[2219] settable  6   7   8    ; R6[R7] := R8
[2220] loadk     7   360      ; R7 := K360(="MinSocialAdjustmentModification")
[2221] newtable  8   0   3    ; R8 := {} , array_size=0, hash_size=3
[2222] loadk     9   458      ; R9 := K458(=0)
[2223] settable  8   268 9    ; R8[K12(="Default")] := R9
[2224] loadk     9   459      ; R9 := K459(="int32")
[2225] settable  8   387 9    ; R8[K131(="Type")] := R9
[2226] loadk     9   460      ; R9 := K460(="Genetics")
[2227] settable  8   481 9    ; R8[K225(="UIGroup")] := R9
[2228] settable  6   7   8    ; R6[R7] := R8
[2229] newtable  7   0   3    ; R7 := {} , array_size=0, hash_size=3
[2230] settable  7   268 269  ; R7[K12(="Default")] := K13(="Nasutoceratops")
[2231] settable  7   387 456  ; R7[K131(="Type")] := K200(="string")
[2232] settable  7   481 482  ; R7[K225(="UIGroup")] := K226(="Visuals")
[2233] settable  6   273 7    ; R6[K17(="ModelName")] := R7
[2234] newtable  7   0   3    ; R7 := {} , array_size=0, hash_size=3
[2235] settable  7   268 269  ; R7[K12(="Default")] := K13(="Nasutoceratops")
[2236] settable  7   387 456  ; R7[K131(="Type")] := K200(="string")
[2237] settable  7   481 482  ; R7[K225(="UIGroup")] := K226(="Visuals")
[2238] settable  6   274 7    ; R6[K18(="MotionGraphName")] := R7
[2239] loadk     7   361      ; R7 := K361(="NumModifiedGenes")
[2240] newtable  8   0   4    ; R8 := {} , array_size=0, hash_size=4
[2241] loadk     9   458      ; R9 := K458(=0)
[2242] settable  8   268 9    ; R8[K12(="Default")] := R9
[2243] settable  8   447 448  ; R8[K191(="Optional")] := K192(=true)
[2244] settable  8   387 443  ; R8[K131(="Type")] := K187(="uint8")
[2245] loadk     9   460      ; R9 := K460(="Genetics")
[2246] settable  8   481 9    ; R8[K225(="UIGroup")] := R9
[2247] settable  6   7   8    ; R6[R7] := R8
[2248] loadk     7   362      ; R7 := K362(="NumUnmodifiedGenes")
[2249] newtable  8   0   4    ; R8 := {} , array_size=0, hash_size=4
[2250] loadk     9   458      ; R9 := K458(=0)
[2251] settable  8   268 9    ; R8[K12(="Default")] := R9
[2252] settable  8   447 448  ; R8[K191(="Optional")] := K192(=true)
[2253] settable  8   387 443  ; R8[K131(="Type")] := K187(="uint8")
[2254] loadk     9   460      ; R9 := K460(="Genetics")
[2255] settable  8   481 9    ; R8[K225(="UIGroup")] := R9
[2256] settable  6   7   8    ; R6[R7] := R8
[2257] loadk     7   365      ; R7 := K365(="PrestigeBonusModification")
[2258] newtable  8   0   4    ; R8 := {} , array_size=0, hash_size=4
[2259] loadk     9   464      ; R9 := K464(=0.0)
[2260] settable  8   268 9    ; R8[K12(="Default")] := R9
[2261] settable  8   447 448  ; R8[K191(="Optional")] := K192(=true)
[2262] settable  8   387 494  ; R8[K131(="Type")] := K238(="float")
[2263] loadk     9   460      ; R9 := K460(="Genetics")
[2264] settable  8   481 9    ; R8[K225(="UIGroup")] := R9
[2265] settable  6   7   8    ; R6[R7] := R8
[2266] loadk     7   370      ; R7 := K370(="RealAge")
[2267] newtable  8   0   4    ; R8 := {} , array_size=0, hash_size=4
[2268] loadk     9   464      ; R9 := K464(=0.0)
[2269] settable  8   268 9    ; R8[K12(="Default")] := R9
[2270] settable  8   447 448  ; R8[K191(="Optional")] := K192(=true)
[2271] settable  8   387 494  ; R8[K131(="Type")] := K238(="float")
[2272] loadk     9   465      ; R9 := K465(="Simulation")
[2273] settable  8   481 9    ; R8[K225(="UIGroup")] := R9
[2274] settable  6   7   8    ; R6[R7] := R8
[2275] loadk     7   366      ; R7 := K366(="ResilienceModification")
[2276] newtable  8   0   4    ; R8 := {} , array_size=0, hash_size=4
[2277] loadk     9   458      ; R9 := K458(=0)
[2278] settable  8   268 9    ; R8[K12(="Default")] := R9
[2279] settable  8   447 448  ; R8[K191(="Optional")] := K192(=true)
[2280] loadk     9   459      ; R9 := K459(="int32")
[2281] settable  8   387 9    ; R8[K131(="Type")] := R9
[2282] loadk     9   460      ; R9 := K460(="Genetics")
[2283] settable  8   481 9    ; R8[K225(="UIGroup")] := R9
[2284] settable  6   7   8    ; R6[R7] := R8
[2285] loadk     7   371      ; R7 := K371(="SpawnFromHatcheryWithCutscene")
[2286] newtable  8   0   4    ; R8 := {} , array_size=0, hash_size=4
[2287] settable  8   268 446  ; R8[K12(="Default")] := K190(=false)
[2288] settable  8   447 448  ; R8[K191(="Optional")] := K192(=true)
[2289] loadk     9   468      ; R9 := K468(="bool")
[2290] settable  8   387 9    ; R8[K131(="Type")] := R9
[2291] settable  8   481 482  ; R8[K225(="UIGroup")] := K226(="Visuals")
[2292] settable  6   7   8    ; R6[R7] := R8
[2293] loadk     7   374      ; R7 := K374(="SpawnedFromHatchery")
[2294] newtable  8   0   3    ; R8 := {} , array_size=0, hash_size=3
[2295] loadk     9   399      ; R9 := K399(="")
[2296] settable  8   268 9    ; R8[K12(="Default")] := R9
[2297] settable  8   387 439  ; R8[K131(="Type")] := K183(="entity")
[2298] settable  8   481 482  ; R8[K225(="UIGroup")] := K226(="Visuals")
[2299] settable  6   7   8    ; R6[R7] := R8
[2300] loadk     7   379      ; R7 := K379(="Species")
[2301] newtable  8   0   4    ; R8 := {} , array_size=0, hash_size=4
[2302] loadk     9   399      ; R9 := K399(="")
[2303] settable  8   268 9    ; R8[K12(="Default")] := R9
[2304] settable  8   447 448  ; R8[K191(="Optional")] := K192(=true)
[2305] settable  8   387 456  ; R8[K131(="Type")] := K200(="string")
[2306] loadk     9   460      ; R9 := K460(="Genetics")
[2307] settable  8   481 9    ; R8[K225(="UIGroup")] := R9
[2308] settable  6   7   8    ; R6[R7] := R8
[2309] loadk     7   373      ; R7 := K373(="StartUnconscious")
[2310] newtable  8   0   3    ; R8 := {} , array_size=0, hash_size=3
[2311] settable  8   268 446  ; R8[K12(="Default")] := K190(=false)
[2312] loadk     9   468      ; R9 := K468(="bool")
[2313] settable  8   387 9    ; R8[K131(="Type")] := R9
[2314] loadk     9   465      ; R9 := K465(="Simulation")
[2315] settable  8   481 9    ; R8[K225(="UIGroup")] := R9
[2316] settable  6   7   8    ; R6[R7] := R8
[2317] loadk     7   367      ; R7 := K367(="StressThresholdAdjustmentModification")
[2318] newtable  8   0   3    ; R8 := {} , array_size=0, hash_size=3
[2319] loadk     9   464      ; R9 := K464(=0.0)
[2320] settable  8   268 9    ; R8[K12(="Default")] := R9
[2321] settable  8   387 494  ; R8[K131(="Type")] := K238(="float")
[2322] loadk     9   460      ; R9 := K460(="Genetics")
[2323] settable  8   481 9    ; R8[K225(="UIGroup")] := R9
[2324] settable  6   7   8    ; R6[R7] := R8
[2325] settable  5   266 6    ; R5[K10(="Properties")] := R6
[2326] settabup  0   428 5    ; U0[K172(="FlattenedRoot")] := R5
[2327] gettabup  5   0   263  ; R5 := U0[K7(="Root")]
[2328] gettabup  6   0   428  ; R6 := U0[K172(="FlattenedRoot")]
[2329] loadk     7   469      ; R7 := K469(=nil)
[2330] settabup  0   263 7    ; U0[K7(="Root")] := R7
[2331] loadk     7   469      ; R7 := K469(=nil)
[2332] settabup  0   428 7    ; U0[K172(="FlattenedRoot")] := R7
[2333] loadk     7   470      ; R7 := K470(="GetRoot")
[2334] closure   8   0        ; R8 := closure(function[0]) 1 upvalues
[2335] settabup  0   7   8    ; U0[R7] := R8
[2336] loadk     7   471      ; R7 := K471(="GetFlattenedRoot")
[2337] closure   8   1        ; R8 := closure(function[1]) 1 upvalues
[2338] settabup  0   7   8    ; U0[R7] := R8
[2339] return    0   1        ; return 

; function [0] definition (level 2) 0_0
; 1 upvalues, 0 params, is_vararg = 0, 2 stacks
.function  1 0 0 2
.upvalue  ""  1  5  ; 0  instack=1  idx=5
[1] getupval  0   0        ; R0 := U0
[2] return    0   2        ; return R0
[3] return    0   1        ; return 
; end of function 0_0


; function [1] definition (level 2) 0_1
; 1 upvalues, 0 params, is_vararg = 0, 2 stacks
.function  1 0 0 2
.upvalue  ""  1  6  ; 0  instack=1  idx=6
[1] getupval  0   0        ; R0 := U0
[2] return    0   2        ; return R0
[3] return    0   1        ; return 
; end of function 0_1

; end of function 0

